Workbook

Sheet Cover
A1: FY25 Dummy Accounting Workbook — July 2025
A3: Purpose | B3: Formula-linked accounting cycle from two raw bank statements
A4: Entity | B4: Truck It In (Private) Limited
A5: Currency | B5: PKR
A6: Period | B6: 01-Jul-2025 to 31-Jul-2025
A7: Model status | B7: =Checks!G3 -> Where to fix
A8: Blue font | B8: Editable inputs / mappings
A9: Green font | B9: Links to another worksheet
A11: Step | B11: Source | C11: Feeds | D11: What is formula-driven | E11: Manual review area | F11: Control
A12: 1 | B12: Chart of Accounts | C12: Mapping, Journal, GL, TB | D12: Account names and classifications | E12: Valid account structure | F12: All GL codes found
A13: 2 | B13: Raw bank statements | C13: Transaction Mapping | D13: Dates, references, debits, credits | E13: None—raw evidence remains unchanged | F13: Opening + credits − debits = closing
A14: 3 | B14: Transaction Mapping | C14: Journal Entries, Cash Flow | D14: GL names and transaction details | E14: Type, counterparty, tax, documents, GL selection | F14: All rows approved/matched
A15: 4 | B15: Non-Bank Entries | C15: Journal Entries | D15: Adjustment account names | E15: Accrual-basis adjustments | F15: Entry support and approval
A16: 5 | B16: Journal Entries | C16: General Ledger | D16: All posted lines | E16: Posting approval | F16: Debits = credits
A17: 6 | B17: General Ledger | C17: Trial Balance | D17: Account totals and balances | E17: None | F17: Ledger ties to journal
A18: 7 | B18: Trial Balance | C18: P&L and Balance Sheet | D18: Statement values | E18: None | F18: TB debits = credits
A19: 8 | B19: Mapping + statements | C19: Cash Flow and Checks | D19: Cash classifications and reconciliation | E19: None | F19: Ending cash ties everywhere

Sheet Chart of Accounts
A1: TRUCK IT IN PVT LTD
A2: Chart of Accounts
A3: FY25
J4: Opening | L4: Movement | N4: Adjustment | P4: Closing
A5: Nature | B5: Classification 1 | C5: Classification 2 | D5: Classification 3 | E5: Classification 4 | F5: Classification 5 | G5: Classification 7 | H5: Code | I5: Title | J5: Debit | K5: Credit | L5: Debit2 | M5: Credit3 | N5: Debit4 | O5: Credit5 | P5: Debit6 | Q5: Credit7 | R5: Column 1 | S5: Column 2
A6: B/S | B6: Assets | C6: Non Current Assets | D6: Property and equipment | E6: Cost | F6: Cost | G6: Furniture and fixture | H6: 1011 | I6: Furniture and fixture | P6: 0 | Q6: 0 | S6: People
A7: B/S | B7: Assets | C7: Non Current Assets | D7: Property and equipment | E7: Cost | F7: Cost | G7: Leasehold building | H7: 1012 | I7: Leasehold building | P7: 0 | Q7: 0 | S7: Travel & Entertainment
A8: B/S | B8: Assets | C8: Non Current Assets | D8: Property and equipment | E8: Cost | F8: Cost | G8: Computers | H8: 1013 | I8: Computers | P8: 0 | Q8: 0 | S8: Travel & Entertainment
A9: B/S | B9: Assets | C9: Non Current Assets | D9: Property and equipment | E9: Cost | F9: Cost | G9: Office Equipments | H9: 1014 | I9: Office Equipments | P9: 0 | Q9: 0 | S9: Travel & Entertainment
A10: B/S | B10: Assets | C10: Non Current Assets | D10: Property and equipment | E10: Cost | F10: Cost | G10: Vehicles | H10: 1015 | I10: Vehicles | P10: 0 | Q10: 0 | S10: Travel & Entertainment
A11: B/S | B11: Assets | C11: Non Current Assets | D11: Intanbgible assets | E11: Cost | F11: Cost | G11: Intangible Assets | H11: 1016 | I11: Intangible Assets | P11: 0 | Q11: 0 | S11: Travel & Entertainment
A12: B/S | B12: Assets | C12: Non Current Assets | D12: Property and equipment | E12: Accumulated Depreciation | F12: Accumulated Depreciation | G12: Accumulated depreciation | H12: 1017 | I12: Accumulated depreciation | P12: 0 | Q12: 0 | S12: Travel & Entertainment
A13: B/S | B13: Assets | C13: Current Assets | D13: Trade debts | E13: unsecured | F13: Considered good | G13: Trade Debtors | H13: 1018 | I13: Trade Debtors | P13: 0 | Q13: 0 | S13: Travel & Entertainment
A14: B/S | B14: Assets | C14: Current Assets | D14: Advances, deposits and prepayments | E14: Advances | F14: Carriers | G14: Advance to carriers | H14: 1019 | I14: Advance to carriers | P14: 0 | Q14: 0 | S14: Travel & Entertainment
A15: B/S | B15: Assets | C15: Non Current Assets | D15: Long term advances and deposits | E15: Advances | F15: To employees | G15: Advance to BYOD | H15: 1020 | I15: Advance to BYOD | P15: 0 | Q15: 0 | S15: Travel & Entertainment
A16: B/S | B16: Assets | C16: Non Current Assets | D16: Long term advances and deposits | E16: Deposits | F16: Security deposit office | G16: Security deposit-Office | H16: 1021 | I16: Security deposit-Office | P16: 0 | Q16: 0 | S16: Real Estate
A17: B/S | B17: Assets | C17: Current Assets | D17: Advances, deposits and prepayments | E17: Deposits | F17: Customers | G17: Security Deposits - Customer | H17: 1022 | I17: Security Deposits - Customer | P17: 0 | Q17: 0 | S17: Profit
... A67: P&L | B67: Expenses | C67: Taxation | D67: Final tax levy | E67: Final tax levy | F67: Final tax levy | G67: Final tax levy | H67: New code 3 | I67: Final tax levy | P67: 0 | Q67: 0 | S67: People

Sheet HBL Operating Account
A1: HBL — Raw Bank Statement
A2: Account title | B2: Truck It In (Private) Limited | F2: Opening balance | G2: 3250000
A3: Account number | B3: PK55HABB0022827200508103 | F3: Total debits | G3: =SUM(E8:E41) -> 3437724
A4: Statement period | B4: 01-Jul-2025 to 31-Jul-2025 | F4: Total credits | G4: =SUM(F8:F41) -> 4185650
A5: Currency | B5: PKR | F5: Closing balance | G5: =G2-G3+G4 -> 3997926
A7: Transaction Date | B7: Value Date | C7: Description | D7: Reference | E7: Debit (PKR) | F7: Credit (PKR) | G7: Balance (PKR)
A8: 45839 | B8: 45839 | C8: IBFT CR - Daraz Pakistan settlement INV-DZ-250701 | D8: HBL250701001 | F8: 685000 | G8: =$G$2-E8+F8 -> 3935000
A9: 45839 | B9: 45839 | C9: Online transfer - Office rent July - Blue Area Properties | D9: HBL250701002 | E9: 275000 | G9: =G8-E9+F9 -> 3660000
A10: 45840 | B10: 45840 | C10: Raast CR - Onic distribution collection Batch 0702 | D10: HBL250702003 | F10: 412500 | G10: =G9-E10+F10 -> 4072500
A11: 45840 | B11: 45840 | C11: POS 7712 - Shell F-8 Islamabad | D11: HBL250702004 | E11: 18450 | G11: =G10-E11+F11 -> 4054050
A12: 45841 | B12: 45841 | C12: Cheque 104583 - Pak Cargo Fleet Services | D12: CHQ104583 | E12: 335000 | G12: =G11-E12+F12 -> 3719050
A13: 45841 | B13: 45841 | C13: Withholding tax on cheque 104583 | D13: WHT104583 | E13: 3350 | G13: =G12-E13+F13 -> 3715700
A14: 45842 | B14: 45842 | C14: IBFT CR - Sapphire merchant COD settlement | D14: HBL250704007 | F14: 298750 | G14: =G13-E14+F14 -> 4014450
A15: 45842 | B15: 45842 | C15: Online payment - PTCL corporate internet June | D15: HBL250704008 | E15: 42800 | G15: =G14-E15+F15 -> 3971650
A16: 45843 | B16: 45843 | C16: ATM cash withdrawal - HBL Blue Area | D16: ATM250705 | E16: 50000 | G16: =G15-E16+F16 -> 3921650
A17: 45845 | B17: 45845 | C17: Transfer to Meezan Bank payroll account | D17: HBL250707011 | E17: 850000 | G17: =G16-E17+F17 -> 3071650
A18: 45846 | B18: 45846 | C18: IBFT CR - Merchant advance repayment - Saeed Ghani | D18: HBL250708012 | F18: 175000 | G18: =G17-E18+F18 -> 3246650
A19: 45846 | B19: 45846 | C19: Online transfer - Vehicle maintenance - Toyota Islamabad | D19: HBL250708013 | E19: 96750 | G19: =G18-E19+F19 -> 3149900
A20: 45847 | B20: 45847 | C20: Card 8821 - Microsoft 365 Business subscription | D20: HBL250709014 | E20: 36500 | G20: =G19-E20+F20 -> 3113400
A21: 45847 | B21: 45847 | C21: Foreign transaction fee - Microsoft subscription | D21: HBL250709015 | E21: 1095 | G21: =G20-E21+F21 -> 3112305
A22: 45848 | B22: 45848 | C22: Cash deposit - Islamabad operations collections | D22: CD250710 | F22: 224000 | G22: =G21-E22+F22 -> 3336305
A23: 45849 | B23: 45849 | C23: Cheque 104584 - Warehouse security deposit | D23: CHQ104584 | E23: 200000 | G23: =G22-E23+F23 -> 3136305
A24: 45850 | B24: 45850 | C24: IBFT CR - Daraz Pakistan settlement INV-DZ-250712 | D24: HBL250712018 | F24: 742500 | G24: =G23-E24+F24 -> 3878805
A25: 45852 | B25: 45852 | C25: Online transfer - Diesel supplier - PSO Fleet Card | D25: HBL250714019 | E25: 386200 | G25: =G24-E25+F25 -> 3492605
A26: 45853 | B26: 45853 | C26: Bank service charges - July | D26: HBL250715020 | E26: 2500 | G26: =G25-E26+F26 -> 3490105
A27: 45853 | B27: 45853 | C27: FED on bank service charges | D27: HBL250715021 | E27: 400 | G27: =G26-E27+F27 -> 3489705
A28: 45854 | B28: 45854 | C28: Raast CR - Corporate delivery customer AR-1098 | D28: HBL250716022 | F28: 455000 | G28: =G27-E28+F28 -> 3944705
A29: 45855 | B29: 45855 | C29: Online payment - Jazz corporate mobile bill | D29: HBL250717023 | E29: 58750 | G29: =G28-E29+F29 -> 3885955
A30: 45856 | B30: 45856 | C30: Cheque 104585 - Packaging material supplier | D30: CHQ104585 | E30: 148600 | G30: =G29-E30+F30 -> 3737355
A31: 45857 | B31: 45857 | C31: IBFT CR - Onic distribution collection Batch 0719 | D31: HBL250719025 | F31: 520000 | G31: =G30-E31+F31 -> 4257355
A32: 45859 | B32: 45859 | C32: Transfer to Meezan Bank payroll account | D32: HBL250721026 | E32: 550000 | G32: =G31-E32+F32 -> 3707355
A33: 45860 | B33: 45860 | C33: Online transfer - Insurance premium - EFU General | D33: HBL250722027 | E33: 180000 | G33: =G32-E33+F33 -> 3527355
A34: 45861 | B34: 45861 | C34: IBFT CR - COD settlement - Retail merchant pool | D34: HBL250723028 | F34: 389450 | G34: =G33-E34+F34 -> 3916805
A35: 45862 | B35: 45862 | C35: Card 8821 - AWS cloud services | D35: HBL250724029 | E35: 72600 | G35: =G34-E35+F35 -> 3844205
A36: 45863 | B36: 45863 | C36: Cheque return charges - customer cheque 77891 | D36: HBL250725030 | E36: 1500 | G36: =G35-E36+F36 -> 3842705
A37: 45866 | B37: 45866 | C37: IBFT CR - Customer cheque 77891 redeposited | D37: HBL250728031 | F37: 265000 | G37: =G36-E37+F37 -> 4107705
A38: 45867 | B38: 45867 | C38: Online transfer - Legal and professional fee | D38: HBL250729032 | E38: 125000 | G38: =G37-E38+F38 -> 3982705
A39: 45868 | B39: 45868 | C39: Profit credited on current-plus account | D39: HBL250730033 | F39: 18450 | G39: =G38-E39+F39 -> 4001155
A40: 45869 | B40: 45869 | C40: Zakat deduction on profit account | D40: HBL250731034 | E40: 461 | G40: =G39-E40+F40 -> 4000694
A41: 45869 | B41: 45869 | C41: Advance tax on bank profit | D41: HBL250731035 | E41: 2768 | G41: =G40-E41+F41 -> 3997926

Sheet Meezan Payroll Account
A1: Meezan Bank — Raw Bank Statement
A2: Account title | B2: Truck It In (Private) Limited | F2: Opening balance | G2: 480000
A3: Account number | B3: PK24MEZN0001110107095251 | F3: Total debits | G3: =SUM(E8:E32) -> 1875588
A4: Statement period | B4: 01-Jul-2025 to 31-Jul-2025 | F4: Total credits | G4: =SUM(F8:F32) -> 1454500
A5: Currency | B5: PKR | F5: Closing balance | G5: =G2-G3+G4 -> 58912
A7: Transaction Date | B7: Value Date | C7: Description | D7: Reference | E7: Debit (PKR) | F7: Credit (PKR) | G7: Balance (PKR)
A8: 45839 | B8: 45839 | C8: Opening-month cash deposit - payroll adjustments | D8: MBL250701001 | F8: 25000 | G8: =$G$2-E8+F8 -> 505000
A9: 45840 | B9: 45840 | C9: IBFT - Employee reimbursement - A. Khan | D9: MBL250702002 | E9: 18500 | G9: =G8-E9+F9 -> 486500
A10: 45841 | B10: 45841 | C10: IBFT - Rider incentive batch 01 | D10: MBL250703003 | E10: 96500 | G10: =G9-E10+F10 -> 390000
A11: 45842 | B11: 45842 | C11: Online payment - EOBI contribution June | D11: MBL250704004 | E11: 68400 | G11: =G10-E11+F11 -> 321600
A12: 45843 | B12: 45843 | C12: Online payment - Social Security contribution June | D12: MBL250705005 | E12: 42750 | G12: =G11-E12+F12 -> 278850
A13: 45845 | B13: 45845 | C13: Incoming IBFT from HBL operating account | D13: MBL250707006 | F13: 850000 | G13: =G12-E13+F13 -> 1128850
A14: 45845 | B14: 45845 | C14: Bulk salary transfer - July payroll batch A | D14: PAY250707A | E14: 625000 | G14: =G13-E14+F14 -> 503850
A15: 45845 | B15: 45845 | C15: Payroll processing charges | D15: MBL250707008 | E15: 3750 | G15: =G14-E15+F15 -> 500100
A16: 45845 | B16: 45845 | C16: FED on payroll processing charges | D16: MBL250707009 | E16: 600 | G16: =G15-E16+F16 -> 499500
A17: 45846 | B17: 45846 | C17: IBFT - Employee advance - M. Usman | D17: MBL250708010 | E17: 30000 | G17: =G16-E17+F17 -> 469500
A18: 45848 | B18: 45848 | C18: Bulk transfer - Contract drivers settlement W27 | D18: MBL250710011 | E18: 156000 | G18: =G17-E18+F18 -> 313500
A19: 45849 | B19: 45849 | C19: Raast reversal - failed driver payment W27 | D19: MBL250711012 | F19: 12000 | G19: =G18-E19+F19 -> 325500
A20: 45850 | B20: 45850 | C20: Raast retry - driver payment W27 | D20: MBL250712013 | E20: 12000 | G20: =G19-E20+F20 -> 313500
A21: 45852 | B21: 45852 | C21: IBFT - Staff travel advance - Lahore operations | D21: MBL250714014 | E21: 45000 | G21: =G20-E21+F21 -> 268500
A22: 45854 | B22: 45854 | C22: Cash deposit - unused staff advance returned | D22: CD250716 | F22: 7500 | G22: =G21-E22+F22 -> 276000
A23: 45856 | B23: 45856 | C23: Bulk transfer - Contract drivers settlement W28 | D23: MBL250718016 | E23: 142500 | G23: =G22-E23+F23 -> 133500
A24: 45859 | B24: 45859 | C24: Incoming IBFT from HBL operating account | D24: MBL250721017 | F24: 550000 | G24: =G23-E24+F24 -> 683500
A25: 45859 | B25: 45859 | C25: Bulk salary transfer - July payroll batch B | D25: PAY250721B | E25: 245000 | G25: =G24-E25+F25 -> 438500
A26: 45860 | B26: 45860 | C26: IBFT - Employee medical reimbursement | D26: MBL250722019 | E26: 22000 | G26: =G25-E26+F26 -> 416500
A27: 45862 | B27: 45862 | C27: Bulk transfer - Contract drivers settlement W29 | D27: MBL250724020 | E27: 138000 | G27: =G26-E27+F27 -> 278500
A28: 45863 | B28: 45863 | C28: Raast CR - employee advance recovery | D28: MBL250725021 | F28: 10000 | G28: =G27-E28+F28 -> 288500
A29: 45866 | B29: 45866 | C29: IBFT - Final settlement - Former employee | D29: MBL250728022 | E29: 78500 | G29: =G28-E29+F29 -> 210000
A30: 45867 | B30: 45867 | C30: Bulk transfer - Contract drivers settlement W30 | D30: MBL250729023 | E30: 149000 | G30: =G29-E30+F30 -> 61000
A31: 45869 | B31: 45869 | C31: Bank service charges - July | D31: MBL250731024 | E31: 1800 | G31: =G30-E31+F31 -> 59200
A32: 45869 | B32: 45869 | C32: FED on bank service charges | D32: MBL250731025 | E32: 288 | G32: =G31-E32+F32 -> 58912

Sheet Transaction Mapping
A1: Transaction Mapping and Review
A2: Map ID | B2: Bank | C2: Date | D2: Description | E2: Reference | F2: Debit | G2: Credit | H2: Transaction Type | I2: Counterparty | J2: Supporting Document | K2: Bank GL Code | L2: Bank GL Name | M2: Offset GL Code | N2: Offset GL Name | O2: Tax Treatment | P2: Entity | Q2: Review Status | R2: Transfer Match ID | S2: Posting Status | T2: Cash Flow Category
A3: MAP-001 | B3: HBL | C3: ='HBL Operating Account'!A8 -> 45839 | D3: ='HBL Operating Account'!C8 -> IBFT CR - Daraz Pakistan settlement INV-DZ-250701 | E3: ='HBL Operating Account'!D8 -> HBL250701001 | F3: ='HBL Operating Account'!E8 | G3: ='HBL Operating Account'!F8 -> 685000 | H3: Customer receipt | I3: Daraz Pakistan | J3: Invoice INV-DZ-250701 | K3: 1029 | L3: {=IFERROR(XLOOKUP(K3,'Chart of Accounts'!$H$6:$H$67,'Chart of Accounts'!$I$6:$I$67),"GL not found")} -> GL not found | M3: 1018 | N3: {=IFERROR(XLOOKUP(M3,'Chart of Accounts'!$H$6:$H$67,'Chart of Accounts'!$I$6:$I$67),"GL not found")} -> GL not found | O3: N/A | P3: Truck It In (Private) Limited | Q3: Approved | S3: Post | T3: Operating - Receipts
A4: MAP-002 | B4: HBL | C4: ='HBL Operating Account'!A9 -> 45839 | D4: ='HBL Operating Account'!C9 -> Online transfer - Office rent July - Blue Area Properties | E4: ='HBL Operating Account'!D9 -> HBL250701002 | F4: ='HBL Operating Account'!E9 -> 275000 | G4: ='HBL Operating Account'!F9 | H4: Rent payment | I4: Blue Area Properties | J4: Lease/rent invoice | K4: 1029 | L4: {=IFERROR(XLOOKUP(K4,'Chart of Accounts'!$H$6:$H$67,'Chart of Accounts'!$I$6:$I$67),"GL not found")} -> GL not found | M4: 1058 | N4: {=IFERROR(XLOOKUP(M4,'Chart of Accounts'!$H$6:$H$67,'Chart of Accounts'!$I$6:$I$67),"GL not found")} -> GL not found | O4: Input tax review | P4: Truck It In (Private) Limited | Q4: Approved | S4: Post | T4: Operating - Payments
A5: MAP-003 | B5: HBL | C5: ='HBL Operating Account'!A10 -> 45840 | D5: ='HBL Operating Account'!C10 -> Raast CR - Onic distribution collection Batch 0702 | E5: ='HBL Operating Account'!D10 -> HBL250702003 | F5: ='HBL Operating Account'!E10 | G5: ='HBL Operating Account'!F10 -> 412500 | H5: Customer receipt | I5: Onic | J5: Collection batch 0702 | K5: 1029 | L5: {=IFERROR(XLOOKUP(K5,'Chart of Accounts'!$H$6:$H$67,'Chart of Accounts'!$I$6:$I$67),"GL not found")} -> GL not found | M5: 1018 | N5: {=IFERROR(XLOOKUP(M5,'Chart of Accounts'!$H$6:$H$67,'Chart of Accounts'!$I$6:$I$67),"GL not found")} -> GL not found | O5: N/A | P5: Truck It In (Private) Limited | Q5: Approved | S5: Post | T5: Operating - Receipts
A6: MAP-004 | B6: HBL | C6: ='HBL Operating Account'!A11 -> 45840 | D6: ='HBL Operating Account'!C11 -> POS 7712 - Shell F-8 Islamabad | E6: ='HBL Operating Account'!D11 -> HBL250702004 | F6: ='HBL Operating Account'!E11 -> 18450 | G6: ='HBL Operating Account'!F11 | H6: Fuel expense | I6: Shell Pakistan | J6: POS slip 7712 | K6: 1029 | L6: {=IFERROR(XLOOKUP(K6,'Chart of Accounts'!$H$6:$H$67,'Chart of Accounts'!$I$6:$I$67),"GL not found")} -> GL not found | M6: 1055 | N6: {=IFERROR(XLOOKUP(M6,'Chart of Accounts'!$H$6:$H$67,'Chart of Accounts'!$I$6:$I$67),"GL not found")} -> GL not found | O6: Input tax review | P6: Truck It In (Private) Limited | Q6: Approved | S6: Post | T6: Operating - Payments
A7: MAP-005 | B7: HBL | C7: ='HBL Operating Account'!A12 -> 45841 | D7: ='HBL Operating Account'!C12 -> Cheque 104583 - Pak Cargo Fleet Services | E7: ='HBL Operating Account'!D12 -> CHQ104583 | F7: ='HBL Operating Account'!E12 -> 335000 | G7: ='HBL Operating Account'!F12 | H7: Carrier payment | I7: Pak Cargo Fleet Services | J7: Vendor bill + cheque | K7: 1029 | L7: {=IFERROR(XLOOKUP(K7,'Chart of Accounts'!$H$6:$H$67,'Chart of Accounts'!$I$6:$I$67),"GL not found")} -> GL not found | M7: 1054 | N7: {=IFERROR(XLOOKUP(M7,'Chart of Accounts'!$H$6:$H$67,'Chart of Accounts'!$I$6:$I$67),"GL not found")} -> GL not found | O7: WHT applicable | P7: Truck It In (Private) Limited | Q7: Approved | S7: Post | T7: Operating - Payments
A8: MAP-006 | B8: HBL | C8: ='HBL Operating Account'!A13 -> 45841 | D8: ='HBL Operating Account'!C13 -> Withholding tax on cheque 104583 | E8: ='HBL Operating Account'!D13 -> WHT104583 | F8: ='HBL Operating Account'!E13 -> 3350 | G8: ='HBL Operating Account'!F13 | H8: Vendor withholding tax | I8: FBR | J8: WHT challan / vendor bill | K8: 1029 | L8: {=IFERROR(XLOOKUP(K8,'Chart of Accounts'!$H$6:$H$67,'Chart of Accounts'!$I$6:$I$67),"GL not found")} -> GL not found | M8: 1036 | N8: {=IFERROR(XLOOKUP(M8,'Chart of Accounts'!$H$6:$H$67,'Chart of Accounts'!$I$6:$I$67),"GL not found")} -> GL not found | O8: Withholding tax | P8: Truck It In (Private) Limited | Q8: Approved | S8: Post | T8: Operating - Payments
A9: MAP-007 | B9: HBL | C9: ='HBL Operating Account'!A14 -> 45842 | D9: ='HBL Operating Account'!C14 -> IBFT CR - Sapphire merchant COD settlement | E9: ='HBL Operating Account'!D14 -> HBL250704007 | F9: ='HBL Operating Account'!E14 | G9: ='HBL Operating Account'!F14 -> 298750 | H9: Customer receipt | I9: Sapphire | J9: COD settlement report | K9: 1029 | L9: {=IFERROR(XLOOKUP(K9,'Chart of Accounts'!$H$6:$H$67,'Chart of Accounts'!$I$6:$I$67),"GL not found")} -> GL not found | M9: 1018 | N9: {=IFERROR(XLOOKUP(M9,'Chart of Accounts'!$H$6:$H$67,'Chart of Accounts'!$I$6:$I$67),"GL not found")} -> GL not found | O9: N/A | P9: Truck It In (Private) Limited | Q9: Approved | S9: Post | T9: Operating - Receipts
A10: MAP-008 | B10: HBL | C10: ='HBL Operating Account'!A15 -> 45842 | D10: ='HBL Operating Account'!C15 -> Online payment - PTCL corporate internet June | E10: ='HBL Operating Account'!D15 -> HBL250704008 | F10: ='HBL Operating Account'!E15 -> 42800 | G10: ='HBL Operating Account'!F15 | H10: Utility payment | I10: PTCL | J10: PTCL invoice | K10: 1029 | L10: {=IFERROR(XLOOKUP(K10,'Chart of Accounts'!$H$6:$H$67,'Chart of Accounts'!$I$6:$I$67),"GL not found")} -> GL not found | M10: 1058 | N10: {=IFERROR(XLOOKUP(M10,'Chart of Accounts'!$H$6:$H$67,'Chart of Accounts'!$I$6:$I$67),"GL not found")} -> GL not found | O10: Input tax review | P10: Truck It In (Private) Limited | Q10: Approved | S10: Post | T10: Operating - Payments
A11: MAP-009 | B11: HBL | C11: ='HBL Operating Account'!A16 -> 45843 | D11: ='HBL Operating Account'!C16 -> ATM cash withdrawal - HBL Blue Area | E11: ='HBL Operating Account'!D16 -> ATM250705 | F11: ='HBL Operating Account'!E16 -> 50000 | G11: ='HBL Operating Account'!F16 | H11: Petty cash withdrawal | I11: Petty Cash Custodian | J11: Cash withdrawal slip | K11: 1029 | L11: {=IFERROR(XLOOKUP(K11,'Chart of Accounts'!$H$6:$H$67,'Chart of Accounts'!$I$6:$I$67),"GL not found")} -> GL not found | M11: 1068 | N11: {=IFERROR(XLOOKUP(M11,'Chart of Accounts'!$H$6:$H$67,'Chart of Accounts'!$I$6:$I$67),"GL not found")} -> GL not found | O11: N/A | P11: Truck It In (Private) Limited | Q11: Approved | S11: Post | T11: Operating - Payments
A12: MAP-010 | B12: HBL | C12: ='HBL Operating Account'!A17 -> 45845 | D12: ='HBL Operating Account'!C17 -> Transfer to Meezan Bank payroll account | E12: ='HBL Operating Account'!D17 -> HBL250707011 | F12: ='HBL Operating Account'!E17 -> 850000 | G12: ='HBL Operating Account'!F17 | H12: Inter-bank transfer | I12: Meezan Payroll Account | J12: Transfer pair TRF-0707 | K12: 1029 | L12: {=IFERROR(XLOOKUP(K12,'Chart of Accounts'!$H$6:$H$67,'Chart of Accounts'!$I$6:$I$67),"GL not found")} -> GL not found | M12: 1030 | N12: {=IFERROR(XLOOKUP(M12,'Chart of Accounts'!$H$6:$H$67,'Chart of Accounts'!$I$6:$I$67),"GL not found")} -> GL not found | O12: N/A | P12: Truck It In (Private) Limited | Q12: Approved | R12: TRF-0707 | S12: Post | T12: Transfer
A13: MAP-011 | B13: HBL | C13: ='HBL Operating Account'!A18 -> 45846 | D13: ='HBL Operating Account'!C18 -> IBFT CR - Merchant advance repayment - Saeed Ghani | E13: ='HBL Operating Account'!D18 -> HBL250708012 | F13: ='HBL Operating Account'!E18 | G13: ='HBL Operating Account'!F18 -> 175000 | H13: Customer receipt | I13: Saeed Ghani | J13: Merchant settlement advice | K13: 1029 | L13: {=IFERROR(XLOOKUP(K13,'Chart of Accounts'!$H$6:$H$67,'Chart of Accounts'!$I$6:$I$67),"GL not found")} -> GL not found | M13: 1018 | N13: {=IFERROR(XLOOKUP(M13,'Chart of Accounts'!$H$6:$H$67,'Chart of Accounts'!$I$6:$I$67),"GL not found")} -> GL not found | O13: N/A | P13: Truck It In (Private) Limited | Q13: Approved | S13: Post | T13: Operating - Receipts
A14: MAP-012 | B14: HBL | C14: ='HBL Operating Account'!A19 -> 45846 | D14: ='HBL Operating Account'!C19 -> Online transfer - Vehicle maintenance - Toyota Islamabad | E14: ='HBL Operating Account'!D19 -> HBL250708013 | F14: ='HBL Operating Account'!E19 -> 96750 | G14: ='HBL Operating Account'!F19 | H14: Vehicle maintenance | I14: Toyota Islamabad | J14: Workshop invoice | K14: 1029 | L14: {=IFERROR(XLOOKUP(K14,'Chart of Accounts'!$H$6:$H$67,'Chart of Accounts'!$I$6:$I$67),"GL not found")} -> GL not found | M14: 1068 | N14: {=IFERROR(XLOOKUP(M14,'Chart of Accounts'!$H$6:$H$67,'Chart of Accounts'!$I$6:$I$67),"GL not found")} -> GL not found | O14: Input tax review | P14: Truck It In (Private) Limited | Q14: Approved | S14: Post | T14: Operating - Payments
A15: MAP-013 | B15: HBL | C15: ='HBL Operating Account'!A20 -> 45847 | D15: ='HBL Operating Account'!C20 -> Card 8821 - Microsoft 365 Business subscription | E15: ='HBL Operating Account'!D20 -> HBL250709014 | F15: ='HBL Operating Account'!E20 -> 36500 | G15: ='HBL Operating Account'!F20 | H15: Software subscription | I15: Microsoft | J15: Microsoft invoice | K15: 1029 | L15: {=IFERROR(XLOOKUP(K15,'Chart of Accounts'!$H$6:$H$67,'Chart of Accounts'!$I$6:$I$67),"GL not found")} -> GL not found | M15: 1068 | N15: {=IFERROR(XLOOKUP(M15,'Chart of Accounts'!$H$6:$H$67,'Chart of Accounts'!$I$6:$I$67),"GL not found")} -> GL not found | O15: Reverse charge review | P15: Truck It In (Private) Limited | Q15: Approved | S15: Post | T15: Operating - Payments
A16: MAP-014 | B16: HBL | C16: ='HBL Operating Account'!A21 -> 45847 | D16: ='HBL Operating Account'!C21 -> Foreign transaction fee - Microsoft subscription | E16: ='HBL Operating Account'!D21 -> HBL250709015 | F16: ='HBL Operating Account'!E21 -> 1095 | G16: ='HBL Operating Account'!F21 | H16: Bank fee | I16: HBL | J16: Bank statement | K16: 1029 | L16: {=IFERROR(XLOOKUP(K16,'Chart of Accounts'!$H$6:$H$67,'Chart of Accounts'!$I$6:$I$67),"GL not found")} -> GL not found | M16: 1057 | N16: {=IFERROR(XLOOKUP(M16,'Chart of Accounts'!$H$6:$H$67,'Chart of Accounts'!$I$6:$I$67),"GL not found")} -> GL not found | O16: N/A | P16: Truck It In (Private) Limited | Q16: Approved | S16: Post | T16: Operating - Payments
A17: MAP-015 | B17: HBL | C17: ='HBL Operating Account'!A22 -> 45848 | D17: ='HBL Operating Account'!C22 -> Cash deposit - Islamabad operations collections | E17: ='HBL Operating Account'!D22 -> CD250710 | F17: ='HBL Operating Account'!E22 | G17: ='HBL Operating Account'!F22 -> 224000 | H17: Operations collection | I17: Islamabad Operations | J17: Daily collection sheet | K17: 1029 | L17: {=IFERROR(XLOOKUP(K17,'Chart of Accounts'!$H$6:$H$67,'Chart of Accounts'!$I$6:$I$67),"GL not found")} -> GL not found | M17: 1050 | N17: {=IFERROR(XLOOKUP(M17,'Chart of Accounts'!$H$6:$H$67,'Chart of Accounts'!$I$6:$I$67),"GL not found")} -> GL not found | O17: Output tax review | P17: Truck It In (Private) Limited | Q17: Approved | S17: Post | T17: Operating - Receipts
A18: MAP-016 | B18: HBL | C18: ='HBL Operating Account'!A23 -> 45849 | D18: ='HBL Operating Account'!C23 -> Cheque 104584 - Warehouse security deposit | E18: ='HBL Operating Account'!D23 -> CHQ104584 | F18: ='HBL Operating Account'!E23 -> 200000 | G18: ='HBL Operating Account'!F23 | H18: Security deposit | I18: Warehouse landlord | J18: Deposit agreement | K18: 1029 | L18: {=IFERROR(XLOOKUP(K18,'Chart of Accounts'!$H$6:$H$67,'Chart of Accounts'!$I$6:$I$67),"GL not found")} -> GL not found | M18: 1021 | N18: {=IFERROR(XLOOKUP(M18,'Chart of Accounts'!$H$6:$H$67,'Chart of Accounts'!$I$6:$I$67),"GL not found")} -> GL not found | O18: N/A | P18: Truck It In (Private) Limited | Q18: Approved | S18: Post | T18: Investing - Payments
A19: MAP-017 | B19: HBL | C19: ='HBL Operating Account'!A24 -> 45850 | D19: ='HBL Operating Account'!C24 -> IBFT CR - Daraz Pakistan settlement INV-DZ-250712 | E19: ='HBL Operating Account'!D24 -> HBL250712018 | F19: ='HBL Operating Account'!E24 | G19: ='HBL Operating Account'!F24 -> 742500 | H19: Customer receipt | I19: Daraz Pakistan | J19: Invoice INV-DZ-250712 | K19: 1029 | L19: {=IFERROR(XLOOKUP(K19,'Chart of Accounts'!$H$6:$H$67,'Chart of Accounts'!$I$6:$I$67),"GL not found")} -> GL not found | M19: 1018 | N19: {=IFERROR(XLOOKUP(M19,'Chart of Accounts'!$H$6:$H$67,'Chart of Accounts'!$I$6:$I$67),"GL not found")} -> GL not found | O19: N/A | P19: Truck It In (Private) Limited | Q19: Approved | S19: Post | T19: Operating - Receipts
A20: MAP-018 | B20: HBL | C20: ='HBL Operating Account'!A25 -> 45852 | D20: ='HBL Operating Account'!C25 -> Online transfer - Diesel supplier - PSO Fleet Card | E20: ='HBL Operating Account'!D25 -> HBL250714019 | F20: ='HBL Operating Account'!E25 -> 386200 | G20: ='HBL Operating Account'!F25 | H20: Fuel expense | I20: PSO | J20: Fleet card statement | K20: 1029 | L20: {=IFERROR(XLOOKUP(K20,'Chart of Accounts'!$H$6:$H$67,'Chart of Accounts'!$I$6:$I$67),"GL not found")} -> GL not found | M20: 1055 | N20: {=IFERROR(XLOOKUP(M20,'Chart of Accounts'!$H$6:$H$67,'Chart of Accounts'!$I$6:$I$67),"GL not found")} -> GL not found | O20: Input tax review | P20: Truck It In (Private) Limited | Q20: Approved | S20: Post | T20: Operating - Payments
A21: MAP-019 | B21: HBL | C21: ='HBL Operating Account'!A26 -> 45853 | D21: ='HBL Operating Account'!C26 -> Bank service charges - July | E21: ='HBL Operating Account'!D26 -> HBL250715020 | F21: ='HBL Operating Account'!E26 -> 2500 | G21: ='HBL Operating Account'!F26 | H21: Bank fee | I21: HBL | J21: Bank statement | K21: 1029 | L21: {=IFERROR(XLOOKUP(K21,'Chart of Accounts'!$H$6:$H$67,'Chart of Accounts'!$I$6:$I$67),"GL not found")} -> GL not found | M21: 1057 | N21: {=IFERROR(XLOOKUP(M21,'Chart of Accounts'!$H$6:$H$67,'Chart of Accounts'!$I$6:$I$67),"GL not found")} -> GL not found | O21: N/A | P21: Truck It In (Private) Limited | Q21: Approved | S21: Post | T21: Operating - Payments
A22: MAP-020 | B22: HBL | C22: ='HBL Operating Account'!A27 -> 45853 | D22: ='HBL Operating Account'!C27 -> FED on bank service charges | E22: ='HBL Operating Account'!D27 -> HBL250715021 | F22: ='HBL Operating Account'!E27 -> 400 | G22: ='HBL Operating Account'!F27 | H22: Federal excise duty | I22: FBR / HBL | J22: Bank statement | K22: 1029 | L22: {=IFERROR(XLOOKUP(K22,'Chart of Accounts'!$H$6:$H$67,'Chart of Accounts'!$I$6:$I$67),"GL not found")} -> GL not found | M22: 1068 | N22: {=IFERROR(XLOOKUP(M22,'Chart of Accounts'!$H$6:$H$67,'Chart of Accounts'!$I$6:$I$67),"GL not found")} -> GL not found | O22: FED expense | P22: Truck It In (Private) Limited | Q22: Approved | S22: Post | T22: Operating - Payments
A23: MAP-021 | B23: HBL | C23: ='HBL Operating Account'!A28 -> 45854 | D23: ='HBL Operating Account'!C28 -> Raast CR - Corporate delivery customer AR-1098 | E23: ='HBL Operating Account'!D28 -> HBL250716022 | F23: ='HBL Operating Account'!E28 | G23: ='HBL Operating Account'!F28 -> 455000 | H23: Customer receipt | I23: Corporate customer | J23: Invoice AR-1098 | K23: 1029 | L23: {=IFERROR(XLOOKUP(K23,'Chart of Accounts'!$H$6:$H$67,'Chart of Accounts'!$I$6:$I$67),"GL not found")} -> GL not found | M23: 1018 | N23: {=IFERROR(XLOOKUP(M23,'Chart of Accounts'!$H$6:$H$67,'Chart of Accounts'!$I$6:$I$67),"GL not found")} -> GL not found | O23: N/A | P23: Truck It In (Private) Limited | Q23: Approved | S23: Post | T23: Operating - Receipts
A24: MAP-022 | B24: HBL | C24: ='HBL Operating Account'!A29 -> 45855 | D24: ='HBL Operating Account'!C29 -> Online payment - Jazz corporate mobile bill | E24: ='HBL Operating Account'!D29 -> HBL250717023 | F24: ='HBL Operating Account'!E29 -> 58750 | G24: ='HBL Operating Account'!F29 | H24: Utility payment | I24: Jazz | J24: Jazz invoice | K24: 1029 | L24: {=IFERROR(XLOOKUP(K24,'Chart of Accounts'!$H$6:$H$67,'Chart of Accounts'!$I$6:$I$67),"GL not found")} -> GL not found | M24: 1058 | N24: {=IFERROR(XLOOKUP(M24,'Chart of Accounts'!$H$6:$H$67,'Chart of Accounts'!$I$6:$I$67),"GL not found")} -> GL not found | O24: Input tax review | P24: Truck It In (Private) Limited | Q24: Approved | S24: Post | T24: Operating - Payments
... A26: MAP-024 | B26: HBL | C26: ='HBL Operating Account'!A31 -> 45857 | D26: ='HBL Operating Account'!C31 -> IBFT CR - Onic distribution collection Batch 0719 | E26: ='HBL Operating Account'!D31 -> HBL250719025 | F26: ='HBL Operating Account'!E31 | G26: ='HBL Operating Account'!F31 -> 520000 | H26: Customer receipt | I26: Onic | J26: Collection batch 0719 | K26: 1029 | L26: {=IFERROR(XLOOKUP(K26,'Chart of Accounts'!$H$6:$H$67,'Chart of Accounts'!$I$6:$I$67),"GL not found")} -> GL not found | M26: 1018 | N26: {=IFERROR(XLOOKUP(M26,'Chart of Accounts'!$H$6:$H$67,'Chart of Accounts'!$I$6:$I$67),"GL not found")} -> GL not found | O26: N/A | P26: Truck It In (Private) Limited | Q26: Approved | S26: Post | T26: Operating - Receipts
A27: MAP-025 | B27: HBL | C27: ='HBL Operating Account'!A32 -> 45859 | D27: ='HBL Operating Account'!C32 -> Transfer to Meezan Bank payroll account | E27: ='HBL Operating Account'!D32 -> HBL250721026 | F27: ='HBL Operating Account'!E32 -> 550000 | G27: ='HBL Operating Account'!F32 | H27: Inter-bank transfer | I27: Meezan Payroll Account | J27: Transfer pair TRF-0721 | K27: 1029 | L27: {=IFERROR(XLOOKUP(K27,'Chart of Accounts'!$H$6:$H$67,'Chart of Accounts'!$I$6:$I$67),"GL not found")} -> GL not found | M27: 1030 | N27: {=IFERROR(XLOOKUP(M27,'Chart of Accounts'!$H$6:$H$67,'Chart of Accounts'!$I$6:$I$67),"GL not found")} -> GL not found | O27: N/A | P27: Truck It In (Private) Limited | Q27: Approved | R27: TRF-0721 | S27: Post | T27: Transfer
A28: MAP-026 | B28: HBL | C28: ='HBL Operating Account'!A33 -> 45860 | D28: ='HBL Operating Account'!C33 -> Online transfer - Insurance premium - EFU General | E28: ='HBL Operating Account'!D33 -> HBL250722027 | F28: ='HBL Operating Account'!E33 -> 180000 | G28: ='HBL Operating Account'!F33 | H28: Insurance prepayment | I28: EFU General | J28: Insurance policy | K28: 1029 | L28: {=IFERROR(XLOOKUP(K28,'Chart of Accounts'!$H$6:$H$67,'Chart of Accounts'!$I$6:$I$67),"GL not found")} -> GL not found | M28: 1026 | N28: {=IFERROR(XLOOKUP(M28,'Chart of Accounts'!$H$6:$H$67,'Chart of Accounts'!$I$6:$I$67),"GL not found")} -> GL not found | O28: N/A | P28: Truck It In (Private) Limited | Q28: Approved | S28: Post | T28: Operating - Payments
A29: MAP-027 | B29: HBL | C29: ='HBL Operating Account'!A34 -> 45861 | D29: ='HBL Operating Account'!C34 -> IBFT CR - COD settlement - Retail merchant pool | E29: ='HBL Operating Account'!D34 -> HBL250723028 | F29: ='HBL Operating Account'!E34 | G29: ='HBL Operating Account'!F34 -> 389450 | H29: Customer receipt | I29: Retail merchant pool | J29: COD settlement report | K29: 1029 | L29: {=IFERROR(XLOOKUP(K29,'Chart of Accounts'!$H$6:$H$67,'Chart of Accounts'!$I$6:$I$67),"GL not found")} -> GL not found | M29: 1018 | N29: {=IFERROR(XLOOKUP(M29,'Chart of Accounts'!$H$6:$H$67,'Chart of Accounts'!$I$6:$I$67),"GL not found")} -> GL not found | O29: N/A | P29: Truck It In (Private) Limited | Q29: Approved | S29: Post | T29: Operating - Receipts
A30: MAP-028 | B30: HBL | C30: ='HBL Operating Account'!A35 -> 45862 | D30: ='HBL Operating Account'!C35 -> Card 8821 - AWS cloud services | E30: ='HBL Operating Account'!D35 -> HBL250724029 | F30: ='HBL Operating Account'!E35 -> 72600 | G30: ='HBL Operating Account'!F35 | H30: Cloud services | I30: Amazon Web Services | J30: AWS invoice | K30: 1029 | L30: {=IFERROR(XLOOKUP(K30,'Chart of Accounts'!$H$6:$H$67,'Chart of Accounts'!$I$6:$I$67),"GL not found")} -> GL not found | M30: 1068 | N30: {=IFERROR(XLOOKUP(M30,'Chart of Accounts'!$H$6:$H$67,'Chart of Accounts'!$I$6:$I$67),"GL not found")} -> GL not found | O30: Reverse charge review | P30: Truck It In (Private) Limited | Q30: Approved | S30: Post | T30: Operating - Payments
A31: MAP-029 | B31: HBL | C31: ='HBL Operating Account'!A36 -> 45863 | D31: ='HBL Operating Account'!C36 -> Cheque return charges - customer cheque 77891 | E31: ='HBL Operating Account'!D36 -> HBL250725030 | F31: ='HBL Operating Account'!E36 -> 1500 | G31: ='HBL Operating Account'!F36 | H31: Bank fee | I31: HBL | J31: Bank statement | K31: 1029 | L31: {=IFERROR(XLOOKUP(K31,'Chart of Accounts'!$H$6:$H$67,'Chart of Accounts'!$I$6:$I$67),"GL not found")} -> GL not found | M31: 1057 | N31: {=IFERROR(XLOOKUP(M31,'Chart of Accounts'!$H$6:$H$67,'Chart of Accounts'!$I$6:$I$67),"GL not found")} -> GL not found | O31: N/A | P31: Truck It In (Private) Limited | Q31: Approved | S31: Post | T31: Operating - Payments
A32: MAP-030 | B32: HBL | C32: ='HBL Operating Account'!A37 -> 45866 | D32: ='HBL Operating Account'!C37 -> IBFT CR - Customer cheque 77891 redeposited | E32: ='HBL Operating Account'!D37 -> HBL250728031 | F32: ='HBL Operating Account'!E37 | G32: ='HBL Operating Account'!F37 -> 265000 | H32: Customer receipt | I32: Customer 77891 | J32: Cheque / deposit slip | K32: 1029 | L32: {=IFERROR(XLOOKUP(K32,'Chart of Accounts'!$H$6:$H$67,'Chart of Accounts'!$I$6:$I$67),"GL not found")} -> GL not found | M32: 1018 | N32: {=IFERROR(XLOOKUP(M32,'Chart of Accounts'!$H$6:$H$67,'Chart of Accounts'!$I$6:$I$67),"GL not found")} -> GL not found | O32: N/A | P32: Truck It In (Private) Limited | Q32: Approved | S32: Post | T32: Operating - Receipts
A33: MAP-031 | B33: HBL | C33: ='HBL Operating Account'!A38 -> 45867 | D33: ='HBL Operating Account'!C38 -> Online transfer - Legal and professional fee | E33: ='HBL Operating Account'!D38 -> HBL250729032 | F33: ='HBL Operating Account'!E38 -> 125000 | G33: ='HBL Operating Account'!F38 | H33: Professional fee | I33: Legal Adviser | J33: Professional invoice | K33: 1029 | L33: {=IFERROR(XLOOKUP(K33,'Chart of Accounts'!$H$6:$H$67,'Chart of Accounts'!$I$6:$I$67),"GL not found")} -> GL not found | M33: 1060 | N33: {=IFERROR(XLOOKUP(M33,'Chart of Accounts'!$H$6:$H$67,'Chart of Accounts'!$I$6:$I$67),"GL not found")} -> GL not found | O33: WHT review | P33: Truck It In (Private) Limited | Q33: Approved | S33: Post | T33: Operating - Payments
A34: MAP-032 | B34: HBL | C34: ='HBL Operating Account'!A39 -> 45868 | D34: ='HBL Operating Account'!C39 -> Profit credited on current-plus account | E34: ='HBL Operating Account'!D39 -> HBL250730033 | F34: ='HBL Operating Account'!E39 | G34: ='HBL Operating Account'!F39 -> 18450 | H34: Bank profit | I34: HBL | J34: Bank statement | K34: 1029 | L34: {=IFERROR(XLOOKUP(K34,'Chart of Accounts'!$H$6:$H$67,'Chart of Accounts'!$I$6:$I$67),"GL not found")} -> GL not found | M34: 1066 | N34: {=IFERROR(XLOOKUP(M34,'Chart of Accounts'!$H$6:$H$67,'Chart of Accounts'!$I$6:$I$67),"GL not found")} -> GL not found | O34: Advance tax review | P34: Truck It In (Private) Limited | Q34: Approved | S34: Post | T34: Operating - Receipts
A35: MAP-033 | B35: HBL | C35: ='HBL Operating Account'!A40 -> 45869 | D35: ='HBL Operating Account'!C40 -> Zakat deduction on profit account | E35: ='HBL Operating Account'!D40 -> HBL250731034 | F35: ='HBL Operating Account'!E40 -> 461 | G35: ='HBL Operating Account'!F40 | H35: Zakat expense | I35: HBL | J35: Bank statement | K35: 1029 | L35: {=IFERROR(XLOOKUP(K35,'Chart of Accounts'!$H$6:$H$67,'Chart of Accounts'!$I$6:$I$67),"GL not found")} -> GL not found | M35: 1068 | N35: {=IFERROR(XLOOKUP(M35,'Chart of Accounts'!$H$6:$H$67,'Chart of Accounts'!$I$6:$I$67),"GL not found")} -> GL not found | O35: N/A | P35: Truck It In (Private) Limited | Q35: Approved | S35: Post | T35: Operating - Payments
A36: MAP-034 | B36: HBL | C36: ='HBL Operating Account'!A41 -> 45869 | D36: ='HBL Operating Account'!C41 -> Advance tax on bank profit | E36: ='HBL Operating Account'!D41 -> HBL250731035 | F36: ='HBL Operating Account'!E41 -> 2768 | G36: ='HBL Operating Account'!F41 | H36: Advance tax | I36: FBR / HBL | J36: Bank statement | K36: 1029 | L36: {=IFERROR(XLOOKUP(K36,'Chart of Accounts'!$H$6:$H$67,'Chart of Accounts'!$I$6:$I$67),"GL not found")} -> GL not found | M36: 1045 | N36: {=IFERROR(XLOOKUP(M36,'Chart of Accounts'!$H$6:$H$67,'Chart of Accounts'!$I$6:$I$67),"GL not found")} -> GL not found | O36: Advance income tax | P36: Truck It In (Private) Limited | Q36: Approved | S36: Post | T36: Operating - Payments
A37: MAP-035 | B37: Meezan | C37: ='Meezan Payroll Account'!A8 -> 45839 | D37: ='Meezan Payroll Account'!C8 -> Opening-month cash deposit - payroll adjustments | E37: ='Meezan Payroll Account'!D8 -> MBL250701001 | F37: ='Meezan Payroll Account'!E8 | G37: ='Meezan Payroll Account'!F8 -> 25000 | H37: Payroll adjustment deposit | I37: Payroll Custodian | J37: Deposit slip | K37: 1030 | L37: {=IFERROR(XLOOKUP(K37,'Chart of Accounts'!$H$6:$H$67,'Chart of Accounts'!$I$6:$I$67),"GL not found")} -> GL not found | M37: 1034 | N37: {=IFERROR(XLOOKUP(M37,'Chart of Accounts'!$H$6:$H$67,'Chart of Accounts'!$I$6:$I$67),"GL not found")} -> GL not found | O37: N/A | P37: Truck It In (Private) Limited | Q37: Approved | S37: Post | T37: Operating - Receipts
A38: MAP-036 | B38: Meezan | C38: ='Meezan Payroll Account'!A9 -> 45840 | D38: ='Meezan Payroll Account'!C9 -> IBFT - Employee reimbursement - A. Khan | E38: ='Meezan Payroll Account'!D9 -> MBL250702002 | F38: ='Meezan Payroll Account'!E9 -> 18500 | G38: ='Meezan Payroll Account'!F9 | H38: Employee reimbursement | I38: A. Khan | J38: Expense claim | K38: 1030 | L38: {=IFERROR(XLOOKUP(K38,'Chart of Accounts'!$H$6:$H$67,'Chart of Accounts'!$I$6:$I$67),"GL not found")} -> GL not found | M38: 1068 | N38: {=IFERROR(XLOOKUP(M38,'Chart of Accounts'!$H$6:$H$67,'Chart of Accounts'!$I$6:$I$67),"GL not found")} -> GL not found | O38: N/A | P38: Truck It In (Private) Limited | Q38: Approved | S38: Post | T38: Operating - Payments
A39: MAP-037 | B39: Meezan | C39: ='Meezan Payroll Account'!A10 -> 45841 | D39: ='Meezan Payroll Account'!C10 -> IBFT - Rider incentive batch 01 | E39: ='Meezan Payroll Account'!D10 -> MBL250703003 | F39: ='Meezan Payroll Account'!E10 -> 96500 | G39: ='Meezan Payroll Account'!F10 | H39: Rider incentives | I39: Riders | J39: Incentive register | K39: 1030 | L39: {=IFERROR(XLOOKUP(K39,'Chart of Accounts'!$H$6:$H$67,'Chart of Accounts'!$I$6:$I$67),"GL not found")} -> GL not found | M39: 1056 | N39: {=IFERROR(XLOOKUP(M39,'Chart of Accounts'!$H$6:$H$67,'Chart of Accounts'!$I$6:$I$67),"GL not found")} -> GL not found | O39: Payroll | P39: Truck It In (Private) Limited | Q39: Approved | S39: Post | T39: Operating - Payments
A40: MAP-038 | B40: Meezan | C40: ='Meezan Payroll Account'!A11 -> 45842 | D40: ='Meezan Payroll Account'!C11 -> Online payment - EOBI contribution June | E40: ='Meezan Payroll Account'!D11 -> MBL250704004 | F40: ='Meezan Payroll Account'!E11 -> 68400 | G40: ='Meezan Payroll Account'!F11 | H40: Payroll liability payment | I40: EOBI | J40: EOBI challan | K40: 1030 | L40: {=IFERROR(XLOOKUP(K40,'Chart of Accounts'!$H$6:$H$67,'Chart of Accounts'!$I$6:$I$67),"GL not found")} -> GL not found | M40: 1034 | N40: {=IFERROR(XLOOKUP(M40,'Chart of Accounts'!$H$6:$H$67,'Chart of Accounts'!$I$6:$I$67),"GL not found")} -> GL not found | O40: Payroll statutory | P40: Truck It In (Private) Limited | Q40: Approved | S40: Post | T40: Operating - Payments
A41: MAP-039 | B41: Meezan | C41: ='Meezan Payroll Account'!A12 -> 45843 | D41: ='Meezan Payroll Account'!C12 -> Online payment - Social Security contribution June | E41: ='Meezan Payroll Account'!D12 -> MBL250705005 | F41: ='Meezan Payroll Account'!E12 -> 42750 | G41: ='Meezan Payroll Account'!F12 | H41: Payroll liability payment | I41: Social Security | J41: Contribution challan | K41: 1030 | L41: {=IFERROR(XLOOKUP(K41,'Chart of Accounts'!$H$6:$H$67,'Chart of Accounts'!$I$6:$I$67),"GL not found")} -> GL not found | M41: 1034 | N41: {=IFERROR(XLOOKUP(M41,'Chart of Accounts'!$H$6:$H$67,'Chart of Accounts'!$I$6:$I$67),"GL not found")} -> GL not found | O41: Payroll statutory | P41: Truck It In (Private) Limited | Q41: Approved | S41: Post | T41: Operating - Payments
A42: MAP-040 | B42: Meezan | C42: ='Meezan Payroll Account'!A13 -> 45845 | D42: ='Meezan Payroll Account'!C13 -> Incoming IBFT from HBL operating account | E42: ='Meezan Payroll Account'!D13 -> MBL250707006 | F42: ='Meezan Payroll Account'!E13 | G42: ='Meezan Payroll Account'!F13 -> 850000 | H42: Inter-bank transfer | I42: HBL Operating Account | J42: Transfer pair TRF-0707 | K42: 1030 | L42: {=IFERROR(XLOOKUP(K42,'Chart of Accounts'!$H$6:$H$67,'Chart of Accounts'!$I$6:$I$67),"GL not found")} -> GL not found | M42: 1029 | N42: {=IFERROR(XLOOKUP(M42,'Chart of Accounts'!$H$6:$H$67,'Chart of Accounts'!$I$6:$I$67),"GL not found")} -> GL not found | O42: N/A | P42: Truck It In (Private) Limited | Q42: Approved | R42: TRF-0707 | S42: Matched - Do Not Post | T42: Transfer
A43: MAP-041 | B43: Meezan | C43: ='Meezan Payroll Account'!A14 -> 45845 | D43: ='Meezan Payroll Account'!C14 -> Bulk salary transfer - July payroll batch A | E43: ='Meezan Payroll Account'!D14 -> PAY250707A | F43: ='Meezan Payroll Account'!E14 -> 625000 | G43: ='Meezan Payroll Account'!F14 | H43: Salary payment | I43: Employees | J43: Payroll batch A | K43: 1030 | L43: {=IFERROR(XLOOKUP(K43,'Chart of Accounts'!$H$6:$H$67,'Chart of Accounts'!$I$6:$I$67),"GL not found")} -> GL not found | M43: 1034 | N43: {=IFERROR(XLOOKUP(M43,'Chart of Accounts'!$H$6:$H$67,'Chart of Accounts'!$I$6:$I$67),"GL not found")} -> GL not found | O43: Payroll | P43: Truck It In (Private) Limited | Q43: Approved | S43: Post | T43: Operating - Payments
A44: MAP-042 | B44: Meezan | C44: ='Meezan Payroll Account'!A15 -> 45845 | D44: ='Meezan Payroll Account'!C15 -> Payroll processing charges | E44: ='Meezan Payroll Account'!D15 -> MBL250707008 | F44: ='Meezan Payroll Account'!E15 -> 3750 | G44: ='Meezan Payroll Account'!F15 | H44: Bank fee | I44: Meezan Bank | J44: Bank statement | K44: 1030 | L44: {=IFERROR(XLOOKUP(K44,'Chart of Accounts'!$H$6:$H$67,'Chart of Accounts'!$I$6:$I$67),"GL not found")} -> GL not found | M44: 1057 | N44: {=IFERROR(XLOOKUP(M44,'Chart of Accounts'!$H$6:$H$67,'Chart of Accounts'!$I$6:$I$67),"GL not found")} -> GL not found | O44: N/A | P44: Truck It In (Private) Limited | Q44: Approved | S44: Post | T44: Operating - Payments
A45: MAP-043 | B45: Meezan | C45: ='Meezan Payroll Account'!A16 -> 45845 | D45: ='Meezan Payroll Account'!C16 -> FED on payroll processing charges | E45: ='Meezan Payroll Account'!D16 -> MBL250707009 | F45: ='Meezan Payroll Account'!E16 -> 600 | G45: ='Meezan Payroll Account'!F16 | H45: Federal excise duty | I45: FBR / Meezan | J45: Bank statement | K45: 1030 | L45: {=IFERROR(XLOOKUP(K45,'Chart of Accounts'!$H$6:$H$67,'Chart of Accounts'!$I$6:$I$67),"GL not found")} -> GL not found | M45: 1068 | N45: {=IFERROR(XLOOKUP(M45,'Chart of Accounts'!$H$6:$H$67,'Chart of Accounts'!$I$6:$I$67),"GL not found")} -> GL not found | O45: FED expense | P45: Truck It In (Private) Limited | Q45: Approved | S45: Post | T45: Operating - Payments
A46: MAP-044 | B46: Meezan | C46: ='Meezan Payroll Account'!A17 -> 45846 | D46: ='Meezan Payroll Account'!C17 -> IBFT - Employee advance - M. Usman | E46: ='Meezan Payroll Account'!D17 -> MBL250708010 | F46: ='Meezan Payroll Account'!E17 -> 30000 | G46: ='Meezan Payroll Account'!F17 | H46: Employee advance | I46: M. Usman | J46: Advance request | K46: 1030 | L46: {=IFERROR(XLOOKUP(K46,'Chart of Accounts'!$H$6:$H$67,'Chart of Accounts'!$I$6:$I$67),"GL not found")} -> GL not found | M46: 1025 | N46: {=IFERROR(XLOOKUP(M46,'Chart of Accounts'!$H$6:$H$67,'Chart of Accounts'!$I$6:$I$67),"GL not found")} -> GL not found | O46: N/A | P46: Truck It In (Private) Limited | Q46: Approved | S46: Post | T46: Operating - Payments
A47: MAP-045 | B47: Meezan | C47: ='Meezan Payroll Account'!A18 -> 45848 | D47: ='Meezan Payroll Account'!C18 -> Bulk transfer - Contract drivers settlement W27 | E47: ='Meezan Payroll Account'!D18 -> MBL250710011 | F47: ='Meezan Payroll Account'!E18 -> 156000 | G47: ='Meezan Payroll Account'!F18 | H47: Contract driver cost | I47: Contract Drivers | J47: Settlement W27 | K47: 1030 | L47: {=IFERROR(XLOOKUP(K47,'Chart of Accounts'!$H$6:$H$67,'Chart of Accounts'!$I$6:$I$67),"GL not found")} -> GL not found | M47: 1054 | N47: {=IFERROR(XLOOKUP(M47,'Chart of Accounts'!$H$6:$H$67,'Chart of Accounts'!$I$6:$I$67),"GL not found")} -> GL not found | O47: WHT review | P47: Truck It In (Private) Limited | Q47: Approved | S47: Post | T47: Operating - Payments
A48: MAP-046 | B48: Meezan | C48: ='Meezan Payroll Account'!A19 -> 45849 | D48: ='Meezan Payroll Account'!C19 -> Raast reversal - failed driver payment W27 | E48: ='Meezan Payroll Account'!D19 -> MBL250711012 | F48: ='Meezan Payroll Account'!E19 | G48: ='Meezan Payroll Account'!F19 -> 12000 | H48: Payment reversal | I48: Contract Drivers | J48: Failed payment report | K48: 1030 | L48: {=IFERROR(XLOOKUP(K48,'Chart of Accounts'!$H$6:$H$67,'Chart of Accounts'!$I$6:$I$67),"GL not found")} -> GL not found | M48: 1054 | N48: {=IFERROR(XLOOKUP(M48,'Chart of Accounts'!$H$6:$H$67,'Chart of Accounts'!$I$6:$I$67),"GL not found")} -> GL not found | O48: N/A | P48: Truck It In (Private) Limited | Q48: Approved | S48: Post | T48: Operating - Receipts
A49: MAP-047 | B49: Meezan | C49: ='Meezan Payroll Account'!A20 -> 45850 | D49: ='Meezan Payroll Account'!C20 -> Raast retry - driver payment W27 | E49: ='Meezan Payroll Account'!D20 -> MBL250712013 | F49: ='Meezan Payroll Account'!E20 -> 12000 | G49: ='Meezan Payroll Account'!F20 | H49: Contract driver cost | I49: Contract Drivers | J49: Settlement W27 retry | K49: 1030 | L49: {=IFERROR(XLOOKUP(K49,'Chart of Accounts'!$H$6:$H$67,'Chart of Accounts'!$I$6:$I$67),"GL not found")} -> GL not found | M49: 1054 | N49: {=IFERROR(XLOOKUP(M49,'Chart of Accounts'!$H$6:$H$67,'Chart of Accounts'!$I$6:$I$67),"GL not found")} -> GL not found | O49: WHT review | P49: Truck It In (Private) Limited | Q49: Approved | S49: Post | T49: Operating - Payments
A50: MAP-048 | B50: Meezan | C50: ='Meezan Payroll Account'!A21 -> 45852 | D50: ='Meezan Payroll Account'!C21 -> IBFT - Staff travel advance - Lahore operations | E50: ='Meezan Payroll Account'!D21 -> MBL250714014 | F50: ='Meezan Payroll Account'!E21 -> 45000 | G50: ='Meezan Payroll Account'!F21 | H50: Staff travel advance | I50: Lahore Operations | J50: Advance request | K50: 1030 | L50: {=IFERROR(XLOOKUP(K50,'Chart of Accounts'!$H$6:$H$67,'Chart of Accounts'!$I$6:$I$67),"GL not found")} -> GL not found | M50: 1025 | N50: {=IFERROR(XLOOKUP(M50,'Chart of Accounts'!$H$6:$H$67,'Chart of Accounts'!$I$6:$I$67),"GL not found")} -> GL not found | O50: N/A | P50: Truck It In (Private) Limited | Q50: Approved | S50: Post | T50: Operating - Payments
A51: MAP-049 | B51: Meezan | C51: ='Meezan Payroll Account'!A22 -> 45854 | D51: ='Meezan Payroll Account'!C22 -> Cash deposit - unused staff advance returned | E51: ='Meezan Payroll Account'!D22 -> CD250716 | F51: ='Meezan Payroll Account'!E22 | G51: ='Meezan Payroll Account'!F22 -> 7500 | H51: Employee advance return | I51: Employee | J51: Deposit slip | K51: 1030 | L51: {=IFERROR(XLOOKUP(K51,'Chart of Accounts'!$H$6:$H$67,'Chart of Accounts'!$I$6:$I$67),"GL not found")} -> GL not found | M51: 1025 | N51: {=IFERROR(XLOOKUP(M51,'Chart of Accounts'!$H$6:$H$67,'Chart of Accounts'!$I$6:$I$67),"GL not found")} -> GL not found | O51: N/A | P51: Truck It In (Private) Limited | Q51: Approved | S51: Post | T51: Operating - Receipts
A52: MAP-050 | B52: Meezan | C52: ='Meezan Payroll Account'!A23 -> 45856 | D52: ='Meezan Payroll Account'!C23 -> Bulk transfer - Contract drivers settlement W28 | E52: ='Meezan Payroll Account'!D23 -> MBL250718016 | F52: ='Meezan Payroll Account'!E23 -> 142500 | G52: ='Meezan Payroll Account'!F23 | H52: Contract driver cost | I52: Contract Drivers | J52: Settlement W28 | K52: 1030 | L52: {=IFERROR(XLOOKUP(K52,'Chart of Accounts'!$H$6:$H$67,'Chart of Accounts'!$I$6:$I$67),"GL not found")} -> GL not found | M52: 1054 | N52: {=IFERROR(XLOOKUP(M52,'Chart of Accounts'!$H$6:$H$67,'Chart of Accounts'!$I$6:$I$67),"GL not found")} -> GL not found | O52: WHT review | P52: Truck It In (Private) Limited | Q52: Approved | S52: Post | T52: Operating - Payments
A53: MAP-051 | B53: Meezan | C53: ='Meezan Payroll Account'!A24 -> 45859 | D53: ='Meezan Payroll Account'!C24 -> Incoming IBFT from HBL operating account | E53: ='Meezan Payroll Account'!D24 -> MBL250721017 | F53: ='Meezan Payroll Account'!E24 | G53: ='Meezan Payroll Account'!F24 -> 550000 | H53: Inter-bank transfer | I53: HBL Operating Account | J53: Transfer pair TRF-0721 | K53: 1030 | L53: {=IFERROR(XLOOKUP(K53,'Chart of Accounts'!$H$6:$H$67,'Chart of Accounts'!$I$6:$I$67),"GL not found")} -> GL not found | M53: 1029 | N53: {=IFERROR(XLOOKUP(M53,'Chart of Accounts'!$H$6:$H$67,'Chart of Accounts'!$I$6:$I$67),"GL not found")} -> GL not found | O53: N/A | P53: Truck It In (Private) Limited | Q53: Approved | R53: TRF-0721 | S53: Matched - Do Not Post | T53: Transfer
A54: MAP-052 | B54: Meezan | C54: ='Meezan Payroll Account'!A25 -> 45859 | D54: ='Meezan Payroll Account'!C25 -> Bulk salary transfer - July payroll batch B | E54: ='Meezan Payroll Account'!D25 -> PAY250721B | F54: ='Meezan Payroll Account'!E25 -> 245000 | G54: ='Meezan Payroll Account'!F25 | H54: Salary payment | I54: Employees | J54: Payroll batch B | K54: 1030 | L54: {=IFERROR(XLOOKUP(K54,'Chart of Accounts'!$H$6:$H$67,'Chart of Accounts'!$I$6:$I$67),"GL not found")} -> GL not found | M54: 1034 | N54: {=IFERROR(XLOOKUP(M54,'Chart of Accounts'!$H$6:$H$67,'Chart of Accounts'!$I$6:$I$67),"GL not found")} -> GL not found | O54: Payroll | P54: Truck It In (Private) Limited | Q54: Approved | S54: Post | T54: Operating - Payments
A55: MAP-053 | B55: Meezan | C55: ='Meezan Payroll Account'!A26 -> 45860 | D55: ='Meezan Payroll Account'!C26 -> IBFT - Employee medical reimbursement | E55: ='Meezan Payroll Account'!D26 -> MBL250722019 | F55: ='Meezan Payroll Account'!E26 -> 22000 | G55: ='Meezan Payroll Account'!F26 | H55: Medical reimbursement | I55: Employee | J55: Expense claim | K55: 1030 | L55: {=IFERROR(XLOOKUP(K55,'Chart of Accounts'!$H$6:$H$67,'Chart of Accounts'!$I$6:$I$67),"GL not found")} -> GL not found | M55: 1068 | N55: {=IFERROR(XLOOKUP(M55,'Chart of Accounts'!$H$6:$H$67,'Chart of Accounts'!$I$6:$I$67),"GL not found")} -> GL not found | O55: N/A | P55: Truck It In (Private) Limited | Q55: Approved | S55: Post | T55: Operating - Payments
A56: MAP-054 | B56: Meezan | C56: ='Meezan Payroll Account'!A27 -> 45862 | D56: ='Meezan Payroll Account'!C27 -> Bulk transfer - Contract drivers settlement W29 | E56: ='Meezan Payroll Account'!D27 -> MBL250724020 | F56: ='Meezan Payroll Account'!E27 -> 138000 | G56: ='Meezan Payroll Account'!F27 | H56: Contract driver cost | I56: Contract Drivers | J56: Settlement W29 | K56: 1030 | L56: {=IFERROR(XLOOKUP(K56,'Chart of Accounts'!$H$6:$H$67,'Chart of Accounts'!$I$6:$I$67),"GL not found")} -> GL not found | M56: 1054 | N56: {=IFERROR(XLOOKUP(M56,'Chart of Accounts'!$H$6:$H$67,'Chart of Accounts'!$I$6:$I$67),"GL not found")} -> GL not found | O56: WHT review | P56: Truck It In (Private) Limited | Q56: Approved | S56: Post | T56: Operating - Payments
A57: MAP-055 | B57: Meezan | C57: ='Meezan Payroll Account'!A28 -> 45863 | D57: ='Meezan Payroll Account'!C28 -> Raast CR - employee advance recovery | E57: ='Meezan Payroll Account'!D28 -> MBL250725021 | F57: ='Meezan Payroll Account'!E28 | G57: ='Meezan Payroll Account'!F28 -> 10000 | H57: Employee advance recovery | I57: Employee | J57: Payroll recovery report | K57: 1030 | L57: {=IFERROR(XLOOKUP(K57,'Chart of Accounts'!$H$6:$H$67,'Chart of Accounts'!$I$6:$I$67),"GL not found")} -> GL not found | M57: 1025 | N57: {=IFERROR(XLOOKUP(M57,'Chart of Accounts'!$H$6:$H$67,'Chart of Accounts'!$I$6:$I$67),"GL not found")} -> GL not found | O57: N/A | P57: Truck It In (Private) Limited | Q57: Approved | S57: Post | T57: Operating - Receipts
A58: MAP-056 | B58: Meezan | C58: ='Meezan Payroll Account'!A29 -> 45866 | D58: ='Meezan Payroll Account'!C29 -> IBFT - Final settlement - Former employee | E58: ='Meezan Payroll Account'!D29 -> MBL250728022 | F58: ='Meezan Payroll Account'!E29 -> 78500 | G58: ='Meezan Payroll Account'!F29 | H58: Final settlement | I58: Former Employee | J58: Final settlement sheet | K58: 1030 | L58: {=IFERROR(XLOOKUP(K58,'Chart of Accounts'!$H$6:$H$67,'Chart of Accounts'!$I$6:$I$67),"GL not found")} -> GL not found | M58: 1034 | N58: {=IFERROR(XLOOKUP(M58,'Chart of Accounts'!$H$6:$H$67,'Chart of Accounts'!$I$6:$I$67),"GL not found")} -> GL not found | O58: Payroll | P58: Truck It In (Private) Limited | Q58: Approved | S58: Post | T58: Operating - Payments
A59: MAP-057 | B59: Meezan | C59: ='Meezan Payroll Account'!A30 -> 45867 | D59: ='Meezan Payroll Account'!C30 -> Bulk transfer - Contract drivers settlement W30 | E59: ='Meezan Payroll Account'!D30 -> MBL250729023 | F59: ='Meezan Payroll Account'!E30 -> 149000 | G59: ='Meezan Payroll Account'!F30 | H59: Contract driver cost | I59: Contract Drivers | J59: Settlement W30 | K59: 1030 | L59: {=IFERROR(XLOOKUP(K59,'Chart of Accounts'!$H$6:$H$67,'Chart of Accounts'!$I$6:$I$67),"GL not found")} -> GL not found | M59: 1054 | N59: {=IFERROR(XLOOKUP(M59,'Chart of Accounts'!$H$6:$H$67,'Chart of Accounts'!$I$6:$I$67),"GL not found")} -> GL not found | O59: WHT review | P59: Truck It In (Private) Limited | Q59: Approved | S59: Post | T59: Operating - Payments
A60: MAP-058 | B60: Meezan | C60: ='Meezan Payroll Account'!A31 -> 45869 | D60: ='Meezan Payroll Account'!C31 -> Bank service charges - July | E60: ='Meezan Payroll Account'!D31 -> MBL250731024 | F60: ='Meezan Payroll Account'!E31 -> 1800 | G60: ='Meezan Payroll Account'!F31 | H60: Bank fee | I60: Meezan Bank | J60: Bank statement | K60: 1030 | L60: {=IFERROR(XLOOKUP(K60,'Chart of Accounts'!$H$6:$H$67,'Chart of Accounts'!$I$6:$I$67),"GL not found")} -> GL not found | M60: 1057 | N60: {=IFERROR(XLOOKUP(M60,'Chart of Accounts'!$H$6:$H$67,'Chart of Accounts'!$I$6:$I$67),"GL not found")} -> GL not found | O60: N/A | P60: Truck It In (Private) Limited | Q60: Approved | S60: Post | T60: Operating - Payments
A61: MAP-059 | B61: Meezan | C61: ='Meezan Payroll Account'!A32 -> 45869 | D61: ='Meezan Payroll Account'!C32 -> FED on bank service charges | E61: ='Meezan Payroll Account'!D32 -> MBL250731025 | F61: ='Meezan Payroll Account'!E32 -> 288 | G61: ='Meezan Payroll Account'!F32 | H61: Federal excise duty | I61: FBR / Meezan | J61: Bank statement | K61: 1030 | L61: {=IFERROR(XLOOKUP(K61,'Chart of Accounts'!$H$6:$H$67,'Chart of Accounts'!$I$6:$I$67),"GL not found")} -> GL not found | M61: 1068 | N61: {=IFERROR(XLOOKUP(M61,'Chart of Accounts'!$H$6:$H$67,'Chart of Accounts'!$I$6:$I$67),"GL not found")} -> GL not found | O61: FED expense | P61: Truck It In (Private) Limited | Q61: Approved | S61: Post | T61: Operating - Payments

Sheet Non-Bank Entries
A1: Non-Bank Journal Entries
A2: Entry ID | B2: Date | C2: Description | D2: Debit GL | E2: Debit Account | F2: Credit GL | G2: Credit Account | H2: Amount | I2: Tax Treatment | J2: Entity | K2: Supporting Document | L2: Review Status | M2: Cash Flow Impact
A3: NB-001 | B3: 45869 | C3: Unpaid customer invoice - July services | D3: 1018 | E3: {=IFERROR(XLOOKUP(D3,'Chart of Accounts'!$H$6:$H$67,'Chart of Accounts'!$I$6:$I$67),"GL not found")} -> GL not found | F3: 1050 | G3: {=IFERROR(XLOOKUP(F3,'Chart of Accounts'!$H$6:$H$67,'Chart of Accounts'!$I$6:$I$67),"GL not found")} -> GL not found | H3: 925000 | I3: Output tax review | J3: Truck It In (Private) Limited | K3: Customer invoice INV-250731 | L3: Approved | M3: Non-cash
A4: NB-002 | B4: 45869 | C4: Unpaid supplier bill - carrier services | D4: 1054 | E4: {=IFERROR(XLOOKUP(D4,'Chart of Accounts'!$H$6:$H$67,'Chart of Accounts'!$I$6:$I$67),"GL not found")} -> GL not found | F4: 1035 | G4: {=IFERROR(XLOOKUP(F4,'Chart of Accounts'!$H$6:$H$67,'Chart of Accounts'!$I$6:$I$67),"GL not found")} -> GL not found | H4: 315000 | I4: WHT review | J4: Truck It In (Private) Limited | K4: Supplier bill BILL-250731 | L4: Approved | M4: Non-cash
A5: NB-003 | B5: 45869 | C5: Month-end utilities accrual | D5: 1058 | E5: {=IFERROR(XLOOKUP(D5,'Chart of Accounts'!$H$6:$H$67,'Chart of Accounts'!$I$6:$I$67),"GL not found")} -> GL not found | F5: 1035 | G5: {=IFERROR(XLOOKUP(F5,'Chart of Accounts'!$H$6:$H$67,'Chart of Accounts'!$I$6:$I$67),"GL not found")} -> GL not found | H5: 85000 | I5: Input tax review | J5: Truck It In (Private) Limited | K5: Accrual schedule | L5: Approved | M5: Non-cash
A6: NB-004 | B6: 45869 | C6: One month insurance expense released from prepayment | D6: 1068 | E6: {=IFERROR(XLOOKUP(D6,'Chart of Accounts'!$H$6:$H$67,'Chart of Accounts'!$I$6:$I$67),"GL not found")} -> GL not found | F6: 1026 | G6: {=IFERROR(XLOOKUP(F6,'Chart of Accounts'!$H$6:$H$67,'Chart of Accounts'!$I$6:$I$67),"GL not found")} -> GL not found | H6: 15000 | I6: N/A | J6: Truck It In (Private) Limited | K6: Insurance amortization schedule | L6: Approved | M6: Non-cash
A7: NB-005 | B7: 45869 | C7: Monthly depreciation on equipment | D7: 1064 | E7: {=IFERROR(XLOOKUP(D7,'Chart of Accounts'!$H$6:$H$67,'Chart of Accounts'!$I$6:$I$67),"GL not found")} -> GL not found | F7: 1017 | G7: {=IFERROR(XLOOKUP(F7,'Chart of Accounts'!$H$6:$H$67,'Chart of Accounts'!$I$6:$I$67),"GL not found")} -> GL not found | H7: 120000 | I7: N/A | J7: Truck It In (Private) Limited | K7: Fixed asset register | L7: Approved | M7: Non-cash
A8: NB-006 | B8: 45869 | C8: Payroll expense accrued but unpaid | D8: 1056 | E8: {=IFERROR(XLOOKUP(D8,'Chart of Accounts'!$H$6:$H$67,'Chart of Accounts'!$I$6:$I$67),"GL not found")} -> GL not found | F8: 1034 | G8: {=IFERROR(XLOOKUP(F8,'Chart of Accounts'!$H$6:$H$67,'Chart of Accounts'!$I$6:$I$67),"GL not found")} -> GL not found | H8: 290000 | I8: Payroll | J8: Truck It In (Private) Limited | K8: Payroll register | L8: Approved | M8: Non-cash
A9: NB-007 | B9: 45869 | C9: Current income tax provision | D9: 1048 | E9: {=IFERROR(XLOOKUP(D9,'Chart of Accounts'!$H$6:$H$67,'Chart of Accounts'!$I$6:$I$67),"GL not found")} -> GL not found | F9: 1047 | G9: {=IFERROR(XLOOKUP(F9,'Chart of Accounts'!$H$6:$H$67,'Chart of Accounts'!$I$6:$I$67),"GL not found")} -> GL not found | H9: 140000 | I9: Current tax | J9: Truck It In (Private) Limited | K9: Tax computation | L9: Approved | M9: Non-cash

Sheet Journal Entries
A1: Journal Entries — Formula Linked
A2: JE ID | B2: Date | C2: Source | D2: Source Reference | E2: Description | F2: GL Code | G2: GL Account | H2: Debit | I2: Credit | J2: Entity | K2: Tax Treatment | L2: Posting Status | M2: Cash Flow Category
A3: ="JE-001" -> JE-001 | B3: ='Transaction Mapping'!C3 -> 45839 | C3: ="Bank Statement" -> Bank Statement | D3: ='Transaction Mapping'!E3 -> HBL250701001 | E3: ='Transaction Mapping'!D3 -> IBFT CR - Daraz Pakistan settlement INV-DZ-250701 | F3: ='Transaction Mapping'!K3 -> 1029 | G3: ='Transaction Mapping'!L3 -> GL not found | H3: =IF('Transaction Mapping'!G3>0,'Transaction Mapping'!G3,0) -> 685000 | I3: =IF('Transaction Mapping'!F3>0,'Transaction Mapping'!F3,0) -> 0 | J3: ='Transaction Mapping'!P3 -> Truck It In (Private) Limited | K3: ='Transaction Mapping'!O3 -> N/A | L3: ="Posted" -> Posted | M3: ='Transaction Mapping'!T3 -> Operating - Receipts
A4: ="JE-001" -> JE-001 | B4: ='Transaction Mapping'!C3 -> 45839 | C4: ="Bank Statement" -> Bank Statement | D4: ='Transaction Mapping'!E3 -> HBL250701001 | E4: ='Transaction Mapping'!D3 -> IBFT CR - Daraz Pakistan settlement INV-DZ-250701 | F4: ='Transaction Mapping'!M3 -> 1018 | G4: ='Transaction Mapping'!N3 -> GL not found | H4: =IF('Transaction Mapping'!F3>0,'Transaction Mapping'!F3,0) -> 0 | I4: =IF('Transaction Mapping'!G3>0,'Transaction Mapping'!G3,0) -> 685000 | J4: ='Transaction Mapping'!P3 -> Truck It In (Private) Limited | K4: ='Transaction Mapping'!O3 -> N/A | L4: ="Posted" -> Posted | M4: ='Transaction Mapping'!T3 -> Operating - Receipts
A5: ="JE-002" -> JE-002 | B5: ='Transaction Mapping'!C4 -> 45839 | C5: ="Bank Statement" -> Bank Statement | D5: ='Transaction Mapping'!E4 -> HBL250701002 | E5: ='Transaction Mapping'!D4 -> Online transfer - Office rent July - Blue Area Properties | F5: ='Transaction Mapping'!K4 -> 1029 | G5: ='Transaction Mapping'!L4 -> GL not found | H5: =IF('Transaction Mapping'!G4>0,'Transaction Mapping'!G4,0) -> 0 | I5: =IF('Transaction Mapping'!F4>0,'Transaction Mapping'!F4,0) -> 275000 | J5: ='Transaction Mapping'!P4 -> Truck It In (Private) Limited | K5: ='Transaction Mapping'!O4 -> Input tax review | L5: ="Posted" -> Posted | M5: ='Transaction Mapping'!T4 -> Operating - Payments
A6: ="JE-002" -> JE-002 | B6: ='Transaction Mapping'!C4 -> 45839 | C6: ="Bank Statement" -> Bank Statement | D6: ='Transaction Mapping'!E4 -> HBL250701002 | E6: ='Transaction Mapping'!D4 -> Online transfer - Office rent July - Blue Area Properties | F6: ='Transaction Mapping'!M4 -> 1058 | G6: ='Transaction Mapping'!N4 -> GL not found | H6: =IF('Transaction Mapping'!F4>0,'Transaction Mapping'!F4,0) -> 275000 | I6: =IF('Transaction Mapping'!G4>0,'Transaction Mapping'!G4,0) -> 0 | J6: ='Transaction Mapping'!P4 -> Truck It In (Private) Limited | K6: ='Transaction Mapping'!O4 -> Input tax review | L6: ="Posted" -> Posted | M6: ='Transaction Mapping'!T4 -> Operating - Payments
A7: ="JE-003" -> JE-003 | B7: ='Transaction Mapping'!C5 -> 45840 | C7: ="Bank Statement" -> Bank Statement | D7: ='Transaction Mapping'!E5 -> HBL250702003 | E7: ='Transaction Mapping'!D5 -> Raast CR - Onic distribution collection Batch 0702 | F7: ='Transaction Mapping'!K5 -> 1029 | G7: ='Transaction Mapping'!L5 -> GL not found | H7: =IF('Transaction Mapping'!G5>0,'Transaction Mapping'!G5,0) -> 412500 | I7: =IF('Transaction Mapping'!F5>0,'Transaction Mapping'!F5,0) -> 0 | J7: ='Transaction Mapping'!P5 -> Truck It In (Private) Limited | K7: ='Transaction Mapping'!O5 -> N/A | L7: ="Posted" -> Posted | M7: ='Transaction Mapping'!T5 -> Operating - Receipts
A8: ="JE-003" -> JE-003 | B8: ='Transaction Mapping'!C5 -> 45840 | C8: ="Bank Statement" -> Bank Statement | D8: ='Transaction Mapping'!E5 -> HBL250702003 | E8: ='Transaction Mapping'!D5 -> Raast CR - Onic distribution collection Batch 0702 | F8: ='Transaction Mapping'!M5 -> 1018 | G8: ='Transaction Mapping'!N5 -> GL not found | H8: =IF('Transaction Mapping'!F5>0,'Transaction Mapping'!F5,0) -> 0 | I8: =IF('Transaction Mapping'!G5>0,'Transaction Mapping'!G5,0) -> 412500 | J8: ='Transaction Mapping'!P5 -> Truck It In (Private) Limited | K8: ='Transaction Mapping'!O5 -> N/A | L8: ="Posted" -> Posted | M8: ='Transaction Mapping'!T5 -> Operating - Receipts
A9: ="JE-004" -> JE-004 | B9: ='Transaction Mapping'!C6 -> 45840 | C9: ="Bank Statement" -> Bank Statement | D9: ='Transaction Mapping'!E6 -> HBL250702004 | E9: ='Transaction Mapping'!D6 -> POS 7712 - Shell F-8 Islamabad | F9: ='Transaction Mapping'!K6 -> 1029 | G9: ='Transaction Mapping'!L6 -> GL not found | H9: =IF('Transaction Mapping'!G6>0,'Transaction Mapping'!G6,0) -> 0 | I9: =IF('Transaction Mapping'!F6>0,'Transaction Mapping'!F6,0) -> 18450 | J9: ='Transaction Mapping'!P6 -> Truck It In (Private) Limited | K9: ='Transaction Mapping'!O6 -> Input tax review | L9: ="Posted" -> Posted | M9: ='Transaction Mapping'!T6 -> Operating - Payments
A10: ="JE-004" -> JE-004 | B10: ='Transaction Mapping'!C6 -> 45840 | C10: ="Bank Statement" -> Bank Statement | D10: ='Transaction Mapping'!E6 -> HBL250702004 | E10: ='Transaction Mapping'!D6 -> POS 7712 - Shell F-8 Islamabad | F10: ='Transaction Mapping'!M6 -> 1055 | G10: ='Transaction Mapping'!N6 -> GL not found | H10: =IF('Transaction Mapping'!F6>0,'Transaction Mapping'!F6,0) -> 18450 | I10: =IF('Transaction Mapping'!G6>0,'Transaction Mapping'!G6,0) -> 0 | J10: ='Transaction Mapping'!P6 -> Truck It In (Private) Limited | K10: ='Transaction Mapping'!O6 -> Input tax review | L10: ="Posted" -> Posted | M10: ='Transaction Mapping'!T6 -> Operating - Payments
A11: ="JE-005" -> JE-005 | B11: ='Transaction Mapping'!C7 -> 45841 | C11: ="Bank Statement" -> Bank Statement | D11: ='Transaction Mapping'!E7 -> CHQ104583 | E11: ='Transaction Mapping'!D7 -> Cheque 104583 - Pak Cargo Fleet Services | F11: ='Transaction Mapping'!K7 -> 1029 | G11: ='Transaction Mapping'!L7 -> GL not found | H11: =IF('Transaction Mapping'!G7>0,'Transaction Mapping'!G7,0) -> 0 | I11: =IF('Transaction Mapping'!F7>0,'Transaction Mapping'!F7,0) -> 335000 | J11: ='Transaction Mapping'!P7 -> Truck It In (Private) Limited | K11: ='Transaction Mapping'!O7 -> WHT applicable | L11: ="Posted" -> Posted | M11: ='Transaction Mapping'!T7 -> Operating - Payments
A12: ="JE-005" -> JE-005 | B12: ='Transaction Mapping'!C7 -> 45841 | C12: ="Bank Statement" -> Bank Statement | D12: ='Transaction Mapping'!E7 -> CHQ104583 | E12: ='Transaction Mapping'!D7 -> Cheque 104583 - Pak Cargo Fleet Services | F12: ='Transaction Mapping'!M7 -> 1054 | G12: ='Transaction Mapping'!N7 -> GL not found | H12: =IF('Transaction Mapping'!F7>0,'Transaction Mapping'!F7,0) -> 335000 | I12: =IF('Transaction Mapping'!G7>0,'Transaction Mapping'!G7,0) -> 0 | J12: ='Transaction Mapping'!P7 -> Truck It In (Private) Limited | K12: ='Transaction Mapping'!O7 -> WHT applicable | L12: ="Posted" -> Posted | M12: ='Transaction Mapping'!T7 -> Operating - Payments
A13: ="JE-006" -> JE-006 | B13: ='Transaction Mapping'!C8 -> 45841 | C13: ="Bank Statement" -> Bank Statement | D13: ='Transaction Mapping'!E8 -> WHT104583 | E13: ='Transaction Mapping'!D8 -> Withholding tax on cheque 104583 | F13: ='Transaction Mapping'!K8 -> 1029 | G13: ='Transaction Mapping'!L8 -> GL not found | H13: =IF('Transaction Mapping'!G8>0,'Transaction Mapping'!G8,0) -> 0 | I13: =IF('Transaction Mapping'!F8>0,'Transaction Mapping'!F8,0) -> 3350 | J13: ='Transaction Mapping'!P8 -> Truck It In (Private) Limited | K13: ='Transaction Mapping'!O8 -> Withholding tax | L13: ="Posted" -> Posted | M13: ='Transaction Mapping'!T8 -> Operating - Payments
A14: ="JE-006" -> JE-006 | B14: ='Transaction Mapping'!C8 -> 45841 | C14: ="Bank Statement" -> Bank Statement | D14: ='Transaction Mapping'!E8 -> WHT104583 | E14: ='Transaction Mapping'!D8 -> Withholding tax on cheque 104583 | F14: ='Transaction Mapping'!M8 -> 1036 | G14: ='Transaction Mapping'!N8 -> GL not found | H14: =IF('Transaction Mapping'!F8>0,'Transaction Mapping'!F8,0) -> 3350 | I14: =IF('Transaction Mapping'!G8>0,'Transaction Mapping'!G8,0) -> 0 | J14: ='Transaction Mapping'!P8 -> Truck It In (Private) Limited | K14: ='Transaction Mapping'!O8 -> Withholding tax | L14: ="Posted" -> Posted | M14: ='Transaction Mapping'!T8 -> Operating - Payments
A15: ="JE-007" -> JE-007 | B15: ='Transaction Mapping'!C9 -> 45842 | C15: ="Bank Statement" -> Bank Statement | D15: ='Transaction Mapping'!E9 -> HBL250704007 | E15: ='Transaction Mapping'!D9 -> IBFT CR - Sapphire merchant COD settlement | F15: ='Transaction Mapping'!K9 -> 1029 | G15: ='Transaction Mapping'!L9 -> GL not found | H15: =IF('Transaction Mapping'!G9>0,'Transaction Mapping'!G9,0) -> 298750 | I15: =IF('Transaction Mapping'!F9>0,'Transaction Mapping'!F9,0) -> 0 | J15: ='Transaction Mapping'!P9 -> Truck It In (Private) Limited | K15: ='Transaction Mapping'!O9 -> N/A | L15: ="Posted" -> Posted | M15: ='Transaction Mapping'!T9 -> Operating - Receipts
A16: ="JE-007" -> JE-007 | B16: ='Transaction Mapping'!C9 -> 45842 | C16: ="Bank Statement" -> Bank Statement | D16: ='Transaction Mapping'!E9 -> HBL250704007 | E16: ='Transaction Mapping'!D9 -> IBFT CR - Sapphire merchant COD settlement | F16: ='Transaction Mapping'!M9 -> 1018 | G16: ='Transaction Mapping'!N9 -> GL not found | H16: =IF('Transaction Mapping'!F9>0,'Transaction Mapping'!F9,0) -> 0 | I16: =IF('Transaction Mapping'!G9>0,'Transaction Mapping'!G9,0) -> 298750 | J16: ='Transaction Mapping'!P9 -> Truck It In (Private) Limited | K16: ='Transaction Mapping'!O9 -> N/A | L16: ="Posted" -> Posted | M16: ='Transaction Mapping'!T9 -> Operating - Receipts
A17: ="JE-008" -> JE-008 | B17: ='Transaction Mapping'!C10 -> 45842 | C17: ="Bank Statement" -> Bank Statement | D17: ='Transaction Mapping'!E10 -> HBL250704008 | E17: ='Transaction Mapping'!D10 -> Online payment - PTCL corporate internet June | F17: ='Transaction Mapping'!K10 -> 1029 | G17: ='Transaction Mapping'!L10 -> GL not found | H17: =IF('Transaction Mapping'!G10>0,'Transaction Mapping'!G10,0) -> 0 | I17: =IF('Transaction Mapping'!F10>0,'Transaction Mapping'!F10,0) -> 42800 | J17: ='Transaction Mapping'!P10 -> Truck It In (Private) Limited | K17: ='Transaction Mapping'!O10 -> Input tax review | L17: ="Posted" -> Posted | M17: ='Transaction Mapping'!T10 -> Operating - Payments
A18: ="JE-008" -> JE-008 | B18: ='Transaction Mapping'!C10 -> 45842 | C18: ="Bank Statement" -> Bank Statement | D18: ='Transaction Mapping'!E10 -> HBL250704008 | E18: ='Transaction Mapping'!D10 -> Online payment - PTCL corporate internet June | F18: ='Transaction Mapping'!M10 -> 1058 | G18: ='Transaction Mapping'!N10 -> GL not found | H18: =IF('Transaction Mapping'!F10>0,'Transaction Mapping'!F10,0) -> 42800 | I18: =IF('Transaction Mapping'!G10>0,'Transaction Mapping'!G10,0) -> 0 | J18: ='Transaction Mapping'!P10 -> Truck It In (Private) Limited | K18: ='Transaction Mapping'!O10 -> Input tax review | L18: ="Posted" -> Posted | M18: ='Transaction Mapping'!T10 -> Operating - Payments
A19: ="JE-009" -> JE-009 | B19: ='Transaction Mapping'!C11 -> 45843 | C19: ="Bank Statement" -> Bank Statement | D19: ='Transaction Mapping'!E11 -> ATM250705 | E19: ='Transaction Mapping'!D11 -> ATM cash withdrawal - HBL Blue Area | F19: ='Transaction Mapping'!K11 -> 1029 | G19: ='Transaction Mapping'!L11 -> GL not found | H19: =IF('Transaction Mapping'!G11>0,'Transaction Mapping'!G11,0) -> 0 | I19: =IF('Transaction Mapping'!F11>0,'Transaction Mapping'!F11,0) -> 50000 | J19: ='Transaction Mapping'!P11 -> Truck It In (Private) Limited | K19: ='Transaction Mapping'!O11 -> N/A | L19: ="Posted" -> Posted | M19: ='Transaction Mapping'!T11 -> Operating - Payments
A20: ="JE-009" -> JE-009 | B20: ='Transaction Mapping'!C11 -> 45843 | C20: ="Bank Statement" -> Bank Statement | D20: ='Transaction Mapping'!E11 -> ATM250705 | E20: ='Transaction Mapping'!D11 -> ATM cash withdrawal - HBL Blue Area | F20: ='Transaction Mapping'!M11 -> 1068 | G20: ='Transaction Mapping'!N11 -> GL not found | H20: =IF('Transaction Mapping'!F11>0,'Transaction Mapping'!F11,0) -> 50000 | I20: =IF('Transaction Mapping'!G11>0,'Transaction Mapping'!G11,0) -> 0 | J20: ='Transaction Mapping'!P11 -> Truck It In (Private) Limited | K20: ='Transaction Mapping'!O11 -> N/A | L20: ="Posted" -> Posted | M20: ='Transaction Mapping'!T11 -> Operating - Payments
A21: ="JE-010" -> JE-010 | B21: ='Transaction Mapping'!C12 -> 45845 | C21: ="Bank Statement" -> Bank Statement | D21: ='Transaction Mapping'!E12 -> HBL250707011 | E21: ='Transaction Mapping'!D12 -> Transfer to Meezan Bank payroll account | F21: ='Transaction Mapping'!K12 -> 1029 | G21: ='Transaction Mapping'!L12 -> GL not found | H21: =IF('Transaction Mapping'!G12>0,'Transaction Mapping'!G12,0) -> 0 | I21: =IF('Transaction Mapping'!F12>0,'Transaction Mapping'!F12,0) -> 850000 | J21: ='Transaction Mapping'!P12 -> Truck It In (Private) Limited | K21: ='Transaction Mapping'!O12 -> N/A | L21: ="Posted" -> Posted | M21: ='Transaction Mapping'!T12 -> Transfer
A22: ="JE-010" -> JE-010 | B22: ='Transaction Mapping'!C12 -> 45845 | C22: ="Bank Statement" -> Bank Statement | D22: ='Transaction Mapping'!E12 -> HBL250707011 | E22: ='Transaction Mapping'!D12 -> Transfer to Meezan Bank payroll account | F22: ='Transaction Mapping'!M12 -> 1030 | G22: ='Transaction Mapping'!N12 -> GL not found | H22: =IF('Transaction Mapping'!F12>0,'Transaction Mapping'!F12,0) -> 850000 | I22: =IF('Transaction Mapping'!G12>0,'Transaction Mapping'!G12,0) -> 0 | J22: ='Transaction Mapping'!P12 -> Truck It In (Private) Limited | K22: ='Transaction Mapping'!O12 -> N/A | L22: ="Posted" -> Posted | M22: ='Transaction Mapping'!T12 -> Transfer
A23: ="JE-011" -> JE-011 | B23: ='Transaction Mapping'!C13 -> 45846 | C23: ="Bank Statement" -> Bank Statement | D23: ='Transaction Mapping'!E13 -> HBL250708012 | E23: ='Transaction Mapping'!D13 -> IBFT CR - Merchant advance repayment - Saeed Ghani | F23: ='Transaction Mapping'!K13 -> 1029 | G23: ='Transaction Mapping'!L13 -> GL not found | H23: =IF('Transaction Mapping'!G13>0,'Transaction Mapping'!G13,0) -> 175000 | I23: =IF('Transaction Mapping'!F13>0,'Transaction Mapping'!F13,0) -> 0 | J23: ='Transaction Mapping'!P13 -> Truck It In (Private) Limited | K23: ='Transaction Mapping'!O13 -> N/A | L23: ="Posted" -> Posted | M23: ='Transaction Mapping'!T13 -> Operating - Receipts
A24: ="JE-011" -> JE-011 | B24: ='Transaction Mapping'!C13 -> 45846 | C24: ="Bank Statement" -> Bank Statement | D24: ='Transaction Mapping'!E13 -> HBL250708012 | E24: ='Transaction Mapping'!D13 -> IBFT CR - Merchant advance repayment - Saeed Ghani | F24: ='Transaction Mapping'!M13 -> 1018 | G24: ='Transaction Mapping'!N13 -> GL not found | H24: =IF('Transaction Mapping'!F13>0,'Transaction Mapping'!F13,0) -> 0 | I24: =IF('Transaction Mapping'!G13>0,'Transaction Mapping'!G13,0) -> 175000 | J24: ='Transaction Mapping'!P13 -> Truck It In (Private) Limited | K24: ='Transaction Mapping'!O13 -> N/A | L24: ="Posted" -> Posted | M24: ='Transaction Mapping'!T13 -> Operating - Receipts
A25: ="JE-012" -> JE-012 | B25: ='Transaction Mapping'!C14 -> 45846 | C25: ="Bank Statement" -> Bank Statement | D25: ='Transaction Mapping'!E14 -> HBL250708013 | E25: ='Transaction Mapping'!D14 -> Online transfer - Vehicle maintenance - Toyota Islamabad | F25: ='Transaction Mapping'!K14 -> 1029 | G25: ='Transaction Mapping'!L14 -> GL not found | H25: =IF('Transaction Mapping'!G14>0,'Transaction Mapping'!G14,0) -> 0 | I25: =IF('Transaction Mapping'!F14>0,'Transaction Mapping'!F14,0) -> 96750 | J25: ='Transaction Mapping'!P14 -> Truck It In (Private) Limited | K25: ='Transaction Mapping'!O14 -> Input tax review | L25: ="Posted" -> Posted | M25: ='Transaction Mapping'!T14 -> Operating - Payments
A26: ="JE-012" -> JE-012 | B26: ='Transaction Mapping'!C14 -> 45846 | C26: ="Bank Statement" -> Bank Statement | D26: ='Transaction Mapping'!E14 -> HBL250708013 | E26: ='Transaction Mapping'!D14 -> Online transfer - Vehicle maintenance - Toyota Islamabad | F26: ='Transaction Mapping'!M14 -> 1068 | G26: ='Transaction Mapping'!N14 -> GL not found | H26: =IF('Transaction Mapping'!F14>0,'Transaction Mapping'!F14,0) -> 96750 | I26: =IF('Transaction Mapping'!G14>0,'Transaction Mapping'!G14,0) -> 0 | J26: ='Transaction Mapping'!P14 -> Truck It In (Private) Limited | K26: ='Transaction Mapping'!O14 -> Input tax review | L26: ="Posted" -> Posted | M26: ='Transaction Mapping'!T14 -> Operating - Payments
A27: ="JE-013" -> JE-013 | B27: ='Transaction Mapping'!C15 -> 45847 | C27: ="Bank Statement" -> Bank Statement | D27: ='Transaction Mapping'!E15 -> HBL250709014 | E27: ='Transaction Mapping'!D15 -> Card 8821 - Microsoft 365 Business subscription | F27: ='Transaction Mapping'!K15 -> 1029 | G27: ='Transaction Mapping'!L15 -> GL not found | H27: =IF('Transaction Mapping'!G15>0,'Transaction Mapping'!G15,0) -> 0 | I27: =IF('Transaction Mapping'!F15>0,'Transaction Mapping'!F15,0) -> 36500 | J27: ='Transaction Mapping'!P15 -> Truck It In (Private) Limited | K27: ='Transaction Mapping'!O15 -> Reverse charge review | L27: ="Posted" -> Posted | M27: ='Transaction Mapping'!T15 -> Operating - Payments
A28: ="JE-013" -> JE-013 | B28: ='Transaction Mapping'!C15 -> 45847 | C28: ="Bank Statement" -> Bank Statement | D28: ='Transaction Mapping'!E15 -> HBL250709014 | E28: ='Transaction Mapping'!D15 -> Card 8821 - Microsoft 365 Business subscription | F28: ='Transaction Mapping'!M15 -> 1068 | G28: ='Transaction Mapping'!N15 -> GL not found | H28: =IF('Transaction Mapping'!F15>0,'Transaction Mapping'!F15,0) -> 36500 | I28: =IF('Transaction Mapping'!G15>0,'Transaction Mapping'!G15,0) -> 0 | J28: ='Transaction Mapping'!P15 -> Truck It In (Private) Limited | K28: ='Transaction Mapping'!O15 -> Reverse charge review | L28: ="Posted" -> Posted | M28: ='Transaction Mapping'!T15 -> Operating - Payments
A29: ="JE-014" -> JE-014 | B29: ='Transaction Mapping'!C16 -> 45847 | C29: ="Bank Statement" -> Bank Statement | D29: ='Transaction Mapping'!E16 -> HBL250709015 | E29: ='Transaction Mapping'!D16 -> Foreign transaction fee - Microsoft subscription | F29: ='Transaction Mapping'!K16 -> 1029 | G29: ='Transaction Mapping'!L16 -> GL not found | H29: =IF('Transaction Mapping'!G16>0,'Transaction Mapping'!G16,0) -> 0 | I29: =IF('Transaction Mapping'!F16>0,'Transaction Mapping'!F16,0) -> 1095 | J29: ='Transaction Mapping'!P16 -> Truck It In (Private) Limited | K29: ='Transaction Mapping'!O16 -> N/A | L29: ="Posted" -> Posted | M29: ='Transaction Mapping'!T16 -> Operating - Payments
A30: ="JE-014" -> JE-014 | B30: ='Transaction Mapping'!C16 -> 45847 | C30: ="Bank Statement" -> Bank Statement | D30: ='Transaction Mapping'!E16 -> HBL250709015 | E30: ='Transaction Mapping'!D16 -> Foreign transaction fee - Microsoft subscription | F30: ='Transaction Mapping'!M16 -> 1057 | G30: ='Transaction Mapping'!N16 -> GL not found | H30: =IF('Transaction Mapping'!F16>0,'Transaction Mapping'!F16,0) -> 1095 | I30: =IF('Transaction Mapping'!G16>0,'Transaction Mapping'!G16,0) -> 0 | J30: ='Transaction Mapping'!P16 -> Truck It In (Private) Limited | K30: ='Transaction Mapping'!O16 -> N/A | L30: ="Posted" -> Posted | M30: ='Transaction Mapping'!T16 -> Operating - Payments
A31: ="JE-015" -> JE-015 | B31: ='Transaction Mapping'!C17 -> 45848 | C31: ="Bank Statement" -> Bank Statement | D31: ='Transaction Mapping'!E17 -> CD250710 | E31: ='Transaction Mapping'!D17 -> Cash deposit - Islamabad operations collections | F31: ='Transaction Mapping'!K17 -> 1029 | G31: ='Transaction Mapping'!L17 -> GL not found | H31: =IF('Transaction Mapping'!G17>0,'Transaction Mapping'!G17,0) -> 224000 | I31: =IF('Transaction Mapping'!F17>0,'Transaction Mapping'!F17,0) -> 0 | J31: ='Transaction Mapping'!P17 -> Truck It In (Private) Limited | K31: ='Transaction Mapping'!O17 -> Output tax review | L31: ="Posted" -> Posted | M31: ='Transaction Mapping'!T17 -> Operating - Receipts
A32: ="JE-015" -> JE-015 | B32: ='Transaction Mapping'!C17 -> 45848 | C32: ="Bank Statement" -> Bank Statement | D32: ='Transaction Mapping'!E17 -> CD250710 | E32: ='Transaction Mapping'!D17 -> Cash deposit - Islamabad operations collections | F32: ='Transaction Mapping'!M17 -> 1050 | G32: ='Transaction Mapping'!N17 -> GL not found | H32: =IF('Transaction Mapping'!F17>0,'Transaction Mapping'!F17,0) -> 0 | I32: =IF('Transaction Mapping'!G17>0,'Transaction Mapping'!G17,0) -> 224000 | J32: ='Transaction Mapping'!P17 -> Truck It In (Private) Limited | K32: ='Transaction Mapping'!O17 -> Output tax review | L32: ="Posted" -> Posted | M32: ='Transaction Mapping'!T17 -> Operating - Receipts
A33: ="JE-016" -> JE-016 | B33: ='Transaction Mapping'!C18 -> 45849 | C33: ="Bank Statement" -> Bank Statement | D33: ='Transaction Mapping'!E18 -> CHQ104584 | E33: ='Transaction Mapping'!D18 -> Cheque 104584 - Warehouse security deposit | F33: ='Transaction Mapping'!K18 -> 1029 | G33: ='Transaction Mapping'!L18 -> GL not found | H33: =IF('Transaction Mapping'!G18>0,'Transaction Mapping'!G18,0) -> 0 | I33: =IF('Transaction Mapping'!F18>0,'Transaction Mapping'!F18,0) -> 200000 | J33: ='Transaction Mapping'!P18 -> Truck It In (Private) Limited | K33: ='Transaction Mapping'!O18 -> N/A | L33: ="Posted" -> Posted | M33: ='Transaction Mapping'!T18 -> Investing - Payments
A34: ="JE-016" -> JE-016 | B34: ='Transaction Mapping'!C18 -> 45849 | C34: ="Bank Statement" -> Bank Statement | D34: ='Transaction Mapping'!E18 -> CHQ104584 | E34: ='Transaction Mapping'!D18 -> Cheque 104584 - Warehouse security deposit | F34: ='Transaction Mapping'!M18 -> 1021 | G34: ='Transaction Mapping'!N18 -> GL not found | H34: =IF('Transaction Mapping'!F18>0,'Transaction Mapping'!F18,0) -> 200000 | I34: =IF('Transaction Mapping'!G18>0,'Transaction Mapping'!G18,0) -> 0 | J34: ='Transaction Mapping'!P18 -> Truck It In (Private) Limited | K34: ='Transaction Mapping'!O18 -> N/A | L34: ="Posted" -> Posted | M34: ='Transaction Mapping'!T18 -> Investing - Payments
A35: ="JE-017" -> JE-017 | B35: ='Transaction Mapping'!C19 -> 45850 | C35: ="Bank Statement" -> Bank Statement | D35: ='Transaction Mapping'!E19 -> HBL250712018 | E35: ='Transaction Mapping'!D19 -> IBFT CR - Daraz Pakistan settlement INV-DZ-250712 | F35: ='Transaction Mapping'!K19 -> 1029 | G35: ='Transaction Mapping'!L19 -> GL not found | H35: =IF('Transaction Mapping'!G19>0,'Transaction Mapping'!G19,0) -> 742500 | I35: =IF('Transaction Mapping'!F19>0,'Transaction Mapping'!F19,0) -> 0 | J35: ='Transaction Mapping'!P19 -> Truck It In (Private) Limited | K35: ='Transaction Mapping'!O19 -> N/A | L35: ="Posted" -> Posted | M35: ='Transaction Mapping'!T19 -> Operating - Receipts
A36: ="JE-017" -> JE-017 | B36: ='Transaction Mapping'!C19 -> 45850 | C36: ="Bank Statement" -> Bank Statement | D36: ='Transaction Mapping'!E19 -> HBL250712018 | E36: ='Transaction Mapping'!D19 -> IBFT CR - Daraz Pakistan settlement INV-DZ-250712 | F36: ='Transaction Mapping'!M19 -> 1018 | G36: ='Transaction Mapping'!N19 -> GL not found | H36: =IF('Transaction Mapping'!F19>0,'Transaction Mapping'!F19,0) -> 0 | I36: =IF('Transaction Mapping'!G19>0,'Transaction Mapping'!G19,0) -> 742500 | J36: ='Transaction Mapping'!P19 -> Truck It In (Private) Limited | K36: ='Transaction Mapping'!O19 -> N/A | L36: ="Posted" -> Posted | M36: ='Transaction Mapping'!T19 -> Operating - Receipts
A37: ="JE-018" -> JE-018 | B37: ='Transaction Mapping'!C20 -> 45852 | C37: ="Bank Statement" -> Bank Statement | D37: ='Transaction Mapping'!E20 -> HBL250714019 | E37: ='Transaction Mapping'!D20 -> Online transfer - Diesel supplier - PSO Fleet Card | F37: ='Transaction Mapping'!K20 -> 1029 | G37: ='Transaction Mapping'!L20 -> GL not found | H37: =IF('Transaction Mapping'!G20>0,'Transaction Mapping'!G20,0) -> 0 | I37: =IF('Transaction Mapping'!F20>0,'Transaction Mapping'!F20,0) -> 386200 | J37: ='Transaction Mapping'!P20 -> Truck It In (Private) Limited | K37: ='Transaction Mapping'!O20 -> Input tax review | L37: ="Posted" -> Posted | M37: ='Transaction Mapping'!T20 -> Operating - Payments
A38: ="JE-018" -> JE-018 | B38: ='Transaction Mapping'!C20 -> 45852 | C38: ="Bank Statement" -> Bank Statement | D38: ='Transaction Mapping'!E20 -> HBL250714019 | E38: ='Transaction Mapping'!D20 -> Online transfer - Diesel supplier - PSO Fleet Card | F38: ='Transaction Mapping'!M20 -> 1055 | G38: ='Transaction Mapping'!N20 -> GL not found | H38: =IF('Transaction Mapping'!F20>0,'Transaction Mapping'!F20,0) -> 386200 | I38: =IF('Transaction Mapping'!G20>0,'Transaction Mapping'!G20,0) -> 0 | J38: ='Transaction Mapping'!P20 -> Truck It In (Private) Limited | K38: ='Transaction Mapping'!O20 -> Input tax review | L38: ="Posted" -> Posted | M38: ='Transaction Mapping'!T20 -> Operating - Payments
A39: ="JE-019" -> JE-019 | B39: ='Transaction Mapping'!C21 -> 45853 | C39: ="Bank Statement" -> Bank Statement | D39: ='Transaction Mapping'!E21 -> HBL250715020 | E39: ='Transaction Mapping'!D21 -> Bank service charges - July | F39: ='Transaction Mapping'!K21 -> 1029 | G39: ='Transaction Mapping'!L21 -> GL not found | H39: =IF('Transaction Mapping'!G21>0,'Transaction Mapping'!G21,0) -> 0 | I39: =IF('Transaction Mapping'!F21>0,'Transaction Mapping'!F21,0) -> 2500 | J39: ='Transaction Mapping'!P21 -> Truck It In (Private) Limited | K39: ='Transaction Mapping'!O21 -> N/A | L39: ="Posted" -> Posted | M39: ='Transaction Mapping'!T21 -> Operating - Payments
A40: ="JE-019" -> JE-019 | B40: ='Transaction Mapping'!C21 -> 45853 | C40: ="Bank Statement" -> Bank Statement | D40: ='Transaction Mapping'!E21 -> HBL250715020 | E40: ='Transaction Mapping'!D21 -> Bank service charges - July | F40: ='Transaction Mapping'!M21 -> 1057 | G40: ='Transaction Mapping'!N21 -> GL not found | H40: =IF('Transaction Mapping'!F21>0,'Transaction Mapping'!F21,0) -> 2500 | I40: =IF('Transaction Mapping'!G21>0,'Transaction Mapping'!G21,0) -> 0 | J40: ='Transaction Mapping'!P21 -> Truck It In (Private) Limited | K40: ='Transaction Mapping'!O21 -> N/A | L40: ="Posted" -> Posted | M40: ='Transaction Mapping'!T21 -> Operating - Payments
A41: ="JE-020" -> JE-020 | B41: ='Transaction Mapping'!C22 -> 45853 | C41: ="Bank Statement" -> Bank Statement | D41: ='Transaction Mapping'!E22 -> HBL250715021 | E41: ='Transaction Mapping'!D22 -> FED on bank service charges | F41: ='Transaction Mapping'!K22 -> 1029 | G41: ='Transaction Mapping'!L22 -> GL not found | H41: =IF('Transaction Mapping'!G22>0,'Transaction Mapping'!G22,0) -> 0 | I41: =IF('Transaction Mapping'!F22>0,'Transaction Mapping'!F22,0) -> 400 | J41: ='Transaction Mapping'!P22 -> Truck It In (Private) Limited | K41: ='Transaction Mapping'!O22 -> FED expense | L41: ="Posted" -> Posted | M41: ='Transaction Mapping'!T22 -> Operating - Payments
A42: ="JE-020" -> JE-020 | B42: ='Transaction Mapping'!C22 -> 45853 | C42: ="Bank Statement" -> Bank Statement | D42: ='Transaction Mapping'!E22 -> HBL250715021 | E42: ='Transaction Mapping'!D22 -> FED on bank service charges | F42: ='Transaction Mapping'!M22 -> 1068 | G42: ='Transaction Mapping'!N22 -> GL not found | H42: =IF('Transaction Mapping'!F22>0,'Transaction Mapping'!F22,0) -> 400 | I42: =IF('Transaction Mapping'!G22>0,'Transaction Mapping'!G22,0) -> 0 | J42: ='Transaction Mapping'!P22 -> Truck It In (Private) Limited | K42: ='Transaction Mapping'!O22 -> FED expense | L42: ="Posted" -> Posted | M42: ='Transaction Mapping'!T22 -> Operating - Payments
A43: ="JE-021" -> JE-021 | B43: ='Transaction Mapping'!C23 -> 45854 | C43: ="Bank Statement" -> Bank Statement | D43: ='Transaction Mapping'!E23 -> HBL250716022 | E43: ='Transaction Mapping'!D23 -> Raast CR - Corporate delivery customer AR-1098 | F43: ='Transaction Mapping'!K23 -> 1029 | G43: ='Transaction Mapping'!L23 -> GL not found | H43: =IF('Transaction Mapping'!G23>0,'Transaction Mapping'!G23,0) -> 455000 | I43: =IF('Transaction Mapping'!F23>0,'Transaction Mapping'!F23,0) -> 0 | J43: ='Transaction Mapping'!P23 -> Truck It In (Private) Limited | K43: ='Transaction Mapping'!O23 -> N/A | L43: ="Posted" -> Posted | M43: ='Transaction Mapping'!T23 -> Operating - Receipts
A44: ="JE-021" -> JE-021 | B44: ='Transaction Mapping'!C23 -> 45854 | C44: ="Bank Statement" -> Bank Statement | D44: ='Transaction Mapping'!E23 -> HBL250716022 | E44: ='Transaction Mapping'!D23 -> Raast CR - Corporate delivery customer AR-1098 | F44: ='Transaction Mapping'!M23 -> 1018 | G44: ='Transaction Mapping'!N23 -> GL not found | H44: =IF('Transaction Mapping'!F23>0,'Transaction Mapping'!F23,0) -> 0 | I44: =IF('Transaction Mapping'!G23>0,'Transaction Mapping'!G23,0) -> 455000 | J44: ='Transaction Mapping'!P23 -> Truck It In (Private) Limited | K44: ='Transaction Mapping'!O23 -> N/A | L44: ="Posted" -> Posted | M44: ='Transaction Mapping'!T23 -> Operating - Receipts
A45: ="JE-022" -> JE-022 | B45: ='Transaction Mapping'!C24 -> 45855 | C45: ="Bank Statement" -> Bank Statement | D45: ='Transaction Mapping'!E24 -> HBL250717023 | E45: ='Transaction Mapping'!D24 -> Online payment - Jazz corporate mobile bill | F45: ='Transaction Mapping'!K24 -> 1029 | G45: ='Transaction Mapping'!L24 -> GL not found | H45: =IF('Transaction Mapping'!G24>0,'Transaction Mapping'!G24,0) -> 0 | I45: =IF('Transaction Mapping'!F24>0,'Transaction Mapping'!F24,0) -> 58750 | J45: ='Transaction Mapping'!P24 -> Truck It In (Private) Limited | K45: ='Transaction Mapping'!O24 -> Input tax review | L45: ="Posted" -> Posted | M45: ='Transaction Mapping'!T24 -> Operating - Payments
A46: ="JE-022" -> JE-022 | B46: ='Transaction Mapping'!C24 -> 45855 | C46: ="Bank Statement" -> Bank Statement | D46: ='Transaction Mapping'!E24 -> HBL250717023 | E46: ='Transaction Mapping'!D24 -> Online payment - Jazz corporate mobile bill | F46: ='Transaction Mapping'!M24 -> 1058 | G46: ='Transaction Mapping'!N24 -> GL not found | H46: =IF('Transaction Mapping'!F24>0,'Transaction Mapping'!F24,0) -> 58750 | I46: =IF('Transaction Mapping'!G24>0,'Transaction Mapping'!G24,0) -> 0 | J46: ='Transaction Mapping'!P24 -> Truck It In (Private) Limited | K46: ='Transaction Mapping'!O24 -> Input tax review | L46: ="Posted" -> Posted | M46: ='Transaction Mapping'!T24 -> Operating - Payments
A47: ="JE-023" -> JE-023 | B47: ='Transaction Mapping'!C25 -> 45856 | C47: ="Bank Statement" -> Bank Statement | D47: ='Transaction Mapping'!E25 -> CHQ104585 | E47: ='Transaction Mapping'!D25 -> Cheque 104585 - Packaging material supplier | F47: ='Transaction Mapping'!K25 -> 1029 | G47: ='Transaction Mapping'!L25 -> GL not found | H47: =IF('Transaction Mapping'!G25>0,'Transaction Mapping'!G25,0) -> 0 | I47: =IF('Transaction Mapping'!F25>0,'Transaction Mapping'!F25,0) -> 148600 | J47: ='Transaction Mapping'!P25 -> Truck It In (Private) Limited | K47: ='Transaction Mapping'!O25 -> Input tax review | L47: ="Posted" -> Posted | M47: ='Transaction Mapping'!T25 -> Operating - Payments
A48: ="JE-023" -> JE-023 | B48: ='Transaction Mapping'!C25 -> 45856 | C48: ="Bank Statement" -> Bank Statement | D48: ='Transaction Mapping'!E25 -> CHQ104585 | E48: ='Transaction Mapping'!D25 -> Cheque 104585 - Packaging material supplier | F48: ='Transaction Mapping'!M25 -> 1068 | G48: ='Transaction Mapping'!N25 -> GL not found | H48: =IF('Transaction Mapping'!F25>0,'Transaction Mapping'!F25,0) -> 148600 | I48: =IF('Transaction Mapping'!G25>0,'Transaction Mapping'!G25,0) -> 0 | J48: ='Transaction Mapping'!P25 -> Truck It In (Private) Limited | K48: ='Transaction Mapping'!O25 -> Input tax review | L48: ="Posted" -> Posted | M48: ='Transaction Mapping'!T25 -> Operating - Payments
A49: ="JE-024" -> JE-024 | B49: ='Transaction Mapping'!C26 -> 45857 | C49: ="Bank Statement" -> Bank Statement | D49: ='Transaction Mapping'!E26 -> HBL250719025 | E49: ='Transaction Mapping'!D26 -> IBFT CR - Onic distribution collection Batch 0719 | F49: ='Transaction Mapping'!K26 -> 1029 | G49: ='Transaction Mapping'!L26 -> GL not found | H49: =IF('Transaction Mapping'!G26>0,'Transaction Mapping'!G26,0) -> 520000 | I49: =IF('Transaction Mapping'!F26>0,'Transaction Mapping'!F26,0) -> 0 | J49: ='Transaction Mapping'!P26 -> Truck It In (Private) Limited | K49: ='Transaction Mapping'!O26 -> N/A | L49: ="Posted" -> Posted | M49: ='Transaction Mapping'!T26 -> Operating - Receipts
A50: ="JE-024" -> JE-024 | B50: ='Transaction Mapping'!C26 -> 45857 | C50: ="Bank Statement" -> Bank Statement | D50: ='Transaction Mapping'!E26 -> HBL250719025 | E50: ='Transaction Mapping'!D26 -> IBFT CR - Onic distribution collection Batch 0719 | F50: ='Transaction Mapping'!M26 -> 1018 | G50: ='Transaction Mapping'!N26 -> GL not found | H50: =IF('Transaction Mapping'!F26>0,'Transaction Mapping'!F26,0) -> 0 | I50: =IF('Transaction Mapping'!G26>0,'Transaction Mapping'!G26,0) -> 520000 | J50: ='Transaction Mapping'!P26 -> Truck It In (Private) Limited | K50: ='Transaction Mapping'!O26 -> N/A | L50: ="Posted" -> Posted | M50: ='Transaction Mapping'!T26 -> Operating - Receipts
A51: ="JE-025" -> JE-025 | B51: ='Transaction Mapping'!C27 -> 45859 | C51: ="Bank Statement" -> Bank Statement | D51: ='Transaction Mapping'!E27 -> HBL250721026 | E51: ='Transaction Mapping'!D27 -> Transfer to Meezan Bank payroll account | F51: ='Transaction Mapping'!K27 -> 1029 | G51: ='Transaction Mapping'!L27 -> GL not found | H51: =IF('Transaction Mapping'!G27>0,'Transaction Mapping'!G27,0) -> 0 | I51: =IF('Transaction Mapping'!F27>0,'Transaction Mapping'!F27,0) -> 550000 | J51: ='Transaction Mapping'!P27 -> Truck It In (Private) Limited | K51: ='Transaction Mapping'!O27 -> N/A | L51: ="Posted" -> Posted | M51: ='Transaction Mapping'!T27 -> Transfer
A52: ="JE-025" -> JE-025 | B52: ='Transaction Mapping'!C27 -> 45859 | C52: ="Bank Statement" -> Bank Statement | D52: ='Transaction Mapping'!E27 -> HBL250721026 | E52: ='Transaction Mapping'!D27 -> Transfer to Meezan Bank payroll account | F52: ='Transaction Mapping'!M27 -> 1030 | G52: ='Transaction Mapping'!N27 -> GL not found | H52: =IF('Transaction Mapping'!F27>0,'Transaction Mapping'!F27,0) -> 550000 | I52: =IF('Transaction Mapping'!G27>0,'Transaction Mapping'!G27,0) -> 0 | J52: ='Transaction Mapping'!P27 -> Truck It In (Private) Limited | K52: ='Transaction Mapping'!O27 -> N/A | L52: ="Posted" -> Posted | M52: ='Transaction Mapping'!T27 -> Transfer
A53: ="JE-026" -> JE-026 | B53: ='Transaction Mapping'!C28 -> 45860 | C53: ="Bank Statement" -> Bank Statement | D53: ='Transaction Mapping'!E28 -> HBL250722027 | E53: ='Transaction Mapping'!D28 -> Online transfer - Insurance premium - EFU General | F53: ='Transaction Mapping'!K28 -> 1029 | G53: ='Transaction Mapping'!L28 -> GL not found | H53: =IF('Transaction Mapping'!G28>0,'Transaction Mapping'!G28,0) -> 0 | I53: =IF('Transaction Mapping'!F28>0,'Transaction Mapping'!F28,0) -> 180000 | J53: ='Transaction Mapping'!P28 -> Truck It In (Private) Limited | K53: ='Transaction Mapping'!O28 -> N/A | L53: ="Posted" -> Posted | M53: ='Transaction Mapping'!T28 -> Operating - Payments
A54: ="JE-026" -> JE-026 | B54: ='Transaction Mapping'!C28 -> 45860 | C54: ="Bank Statement" -> Bank Statement | D54: ='Transaction Mapping'!E28 -> HBL250722027 | E54: ='Transaction Mapping'!D28 -> Online transfer - Insurance premium - EFU General | F54: ='Transaction Mapping'!M28 -> 1026 | G54: ='Transaction Mapping'!N28 -> GL not found | H54: =IF('Transaction Mapping'!F28>0,'Transaction Mapping'!F28,0) -> 180000 | I54: =IF('Transaction Mapping'!G28>0,'Transaction Mapping'!G28,0) -> 0 | J54: ='Transaction Mapping'!P28 -> Truck It In (Private) Limited | K54: ='Transaction Mapping'!O28 -> N/A | L54: ="Posted" -> Posted | M54: ='Transaction Mapping'!T28 -> Operating - Payments
A55: ="JE-027" -> JE-027 | B55: ='Transaction Mapping'!C29 -> 45861 | C55: ="Bank Statement" -> Bank Statement | D55: ='Transaction Mapping'!E29 -> HBL250723028 | E55: ='Transaction Mapping'!D29 -> IBFT CR - COD settlement - Retail merchant pool | F55: ='Transaction Mapping'!K29 -> 1029 | G55: ='Transaction Mapping'!L29 -> GL not found | H55: =IF('Transaction Mapping'!G29>0,'Transaction Mapping'!G29,0) -> 389450 | I55: =IF('Transaction Mapping'!F29>0,'Transaction Mapping'!F29,0) -> 0 | J55: ='Transaction Mapping'!P29 -> Truck It In (Private) Limited | K55: ='Transaction Mapping'!O29 -> N/A | L55: ="Posted" -> Posted | M55: ='Transaction Mapping'!T29 -> Operating - Receipts
A56: ="JE-027" -> JE-027 | B56: ='Transaction Mapping'!C29 -> 45861 | C56: ="Bank Statement" -> Bank Statement | D56: ='Transaction Mapping'!E29 -> HBL250723028 | E56: ='Transaction Mapping'!D29 -> IBFT CR - COD settlement - Retail merchant pool | F56: ='Transaction Mapping'!M29 -> 1018 | G56: ='Transaction Mapping'!N29 -> GL not found | H56: =IF('Transaction Mapping'!F29>0,'Transaction Mapping'!F29,0) -> 0 | I56: =IF('Transaction Mapping'!G29>0,'Transaction Mapping'!G29,0) -> 389450 | J56: ='Transaction Mapping'!P29 -> Truck It In (Private) Limited | K56: ='Transaction Mapping'!O29 -> N/A | L56: ="Posted" -> Posted | M56: ='Transaction Mapping'!T29 -> Operating - Receipts
A57: ="JE-028" -> JE-028 | B57: ='Transaction Mapping'!C30 -> 45862 | C57: ="Bank Statement" -> Bank Statement | D57: ='Transaction Mapping'!E30 -> HBL250724029 | E57: ='Transaction Mapping'!D30 -> Card 8821 - AWS cloud services | F57: ='Transaction Mapping'!K30 -> 1029 | G57: ='Transaction Mapping'!L30 -> GL not found | H57: =IF('Transaction Mapping'!G30>0,'Transaction Mapping'!G30,0) -> 0 | I57: =IF('Transaction Mapping'!F30>0,'Transaction Mapping'!F30,0) -> 72600 | J57: ='Transaction Mapping'!P30 -> Truck It In (Private) Limited | K57: ='Transaction Mapping'!O30 -> Reverse charge review | L57: ="Posted" -> Posted | M57: ='Transaction Mapping'!T30 -> Operating - Payments
A58: ="JE-028" -> JE-028 | B58: ='Transaction Mapping'!C30 -> 45862 | C58: ="Bank Statement" -> Bank Statement | D58: ='Transaction Mapping'!E30 -> HBL250724029 | E58: ='Transaction Mapping'!D30 -> Card 8821 - AWS cloud services | F58: ='Transaction Mapping'!M30 -> 1068 | G58: ='Transaction Mapping'!N30 -> GL not found | H58: =IF('Transaction Mapping'!F30>0,'Transaction Mapping'!F30,0) -> 72600 | I58: =IF('Transaction Mapping'!G30>0,'Transaction Mapping'!G30,0) -> 0 | J58: ='Transaction Mapping'!P30 -> Truck It In (Private) Limited | K58: ='Transaction Mapping'!O30 -> Reverse charge review | L58: ="Posted" -> Posted | M58: ='Transaction Mapping'!T30 -> Operating - Payments
A59: ="JE-029" -> JE-029 | B59: ='Transaction Mapping'!C31 -> 45863 | C59: ="Bank Statement" -> Bank Statement | D59: ='Transaction Mapping'!E31 -> HBL250725030 | E59: ='Transaction Mapping'!D31 -> Cheque return charges - customer cheque 77891 | F59: ='Transaction Mapping'!K31 -> 1029 | G59: ='Transaction Mapping'!L31 -> GL not found | H59: =IF('Transaction Mapping'!G31>0,'Transaction Mapping'!G31,0) -> 0 | I59: =IF('Transaction Mapping'!F31>0,'Transaction Mapping'!F31,0) -> 1500 | J59: ='Transaction Mapping'!P31 -> Truck It In (Private) Limited | K59: ='Transaction Mapping'!O31 -> N/A | L59: ="Posted" -> Posted | M59: ='Transaction Mapping'!T31 -> Operating - Payments
A60: ="JE-029" -> JE-029 | B60: ='Transaction Mapping'!C31 -> 45863 | C60: ="Bank Statement" -> Bank Statement | D60: ='Transaction Mapping'!E31 -> HBL250725030 | E60: ='Transaction Mapping'!D31 -> Cheque return charges - customer cheque 77891 | F60: ='Transaction Mapping'!M31 -> 1057 | G60: ='Transaction Mapping'!N31 -> GL not found | H60: =IF('Transaction Mapping'!F31>0,'Transaction Mapping'!F31,0) -> 1500 | I60: =IF('Transaction Mapping'!G31>0,'Transaction Mapping'!G31,0) -> 0 | J60: ='Transaction Mapping'!P31 -> Truck It In (Private) Limited | K60: ='Transaction Mapping'!O31 -> N/A | L60: ="Posted" -> Posted | M60: ='Transaction Mapping'!T31 -> Operating - Payments
A61: ="JE-030" -> JE-030 | B61: ='Transaction Mapping'!C32 -> 45866 | C61: ="Bank Statement" -> Bank Statement | D61: ='Transaction Mapping'!E32 -> HBL250728031 | E61: ='Transaction Mapping'!D32 -> IBFT CR - Customer cheque 77891 redeposited | F61: ='Transaction Mapping'!K32 -> 1029 | G61: ='Transaction Mapping'!L32 -> GL not found | H61: =IF('Transaction Mapping'!G32>0,'Transaction Mapping'!G32,0) -> 265000 | I61: =IF('Transaction Mapping'!F32>0,'Transaction Mapping'!F32,0) -> 0 | J61: ='Transaction Mapping'!P32 -> Truck It In (Private) Limited | K61: ='Transaction Mapping'!O32 -> N/A | L61: ="Posted" -> Posted | M61: ='Transaction Mapping'!T32 -> Operating - Receipts
A62: ="JE-030" -> JE-030 | B62: ='Transaction Mapping'!C32 -> 45866 | C62: ="Bank Statement" -> Bank Statement | D62: ='Transaction Mapping'!E32 -> HBL250728031 | E62: ='Transaction Mapping'!D32 -> IBFT CR - Customer cheque 77891 redeposited | F62: ='Transaction Mapping'!M32 -> 1018 | G62: ='Transaction Mapping'!N32 -> GL not found | H62: =IF('Transaction Mapping'!F32>0,'Transaction Mapping'!F32,0) -> 0 | I62: =IF('Transaction Mapping'!G32>0,'Transaction Mapping'!G32,0) -> 265000 | J62: ='Transaction Mapping'!P32 -> Truck It In (Private) Limited | K62: ='Transaction Mapping'!O32 -> N/A | L62: ="Posted" -> Posted | M62: ='Transaction Mapping'!T32 -> Operating - Receipts
A63: ="JE-031" -> JE-031 | B63: ='Transaction Mapping'!C33 -> 45867 | C63: ="Bank Statement" -> Bank Statement | D63: ='Transaction Mapping'!E33 -> HBL250729032 | E63: ='Transaction Mapping'!D33 -> Online transfer - Legal and professional fee | F63: ='Transaction Mapping'!K33 -> 1029 | G63: ='Transaction Mapping'!L33 -> GL not found | H63: =IF('Transaction Mapping'!G33>0,'Transaction Mapping'!G33,0) -> 0 | I63: =IF('Transaction Mapping'!F33>0,'Transaction Mapping'!F33,0) -> 125000 | J63: ='Transaction Mapping'!P33 -> Truck It In (Private) Limited | K63: ='Transaction Mapping'!O33 -> WHT review | L63: ="Posted" -> Posted | M63: ='Transaction Mapping'!T33 -> Operating - Payments
A64: ="JE-031" -> JE-031 | B64: ='Transaction Mapping'!C33 -> 45867 | C64: ="Bank Statement" -> Bank Statement | D64: ='Transaction Mapping'!E33 -> HBL250729032 | E64: ='Transaction Mapping'!D33 -> Online transfer - Legal and professional fee | F64: ='Transaction Mapping'!M33 -> 1060 | G64: ='Transaction Mapping'!N33 -> GL not found | H64: =IF('Transaction Mapping'!F33>0,'Transaction Mapping'!F33,0) -> 125000 | I64: =IF('Transaction Mapping'!G33>0,'Transaction Mapping'!G33,0) -> 0 | J64: ='Transaction Mapping'!P33 -> Truck It In (Private) Limited | K64: ='Transaction Mapping'!O33 -> WHT review | L64: ="Posted" -> Posted | M64: ='Transaction Mapping'!T33 -> Operating - Payments
A65: ="JE-032" -> JE-032 | B65: ='Transaction Mapping'!C34 -> 45868 | C65: ="Bank Statement" -> Bank Statement | D65: ='Transaction Mapping'!E34 -> HBL250730033 | E65: ='Transaction Mapping'!D34 -> Profit credited on current-plus account | F65: ='Transaction Mapping'!K34 -> 1029 | G65: ='Transaction Mapping'!L34 -> GL not found | H65: =IF('Transaction Mapping'!G34>0,'Transaction Mapping'!G34,0) -> 18450 | I65: =IF('Transaction Mapping'!F34>0,'Transaction Mapping'!F34,0) -> 0 | J65: ='Transaction Mapping'!P34 -> Truck It In (Private) Limited | K65: ='Transaction Mapping'!O34 -> Advance tax review | L65: ="Posted" -> Posted | M65: ='Transaction Mapping'!T34 -> Operating - Receipts
A66: ="JE-032" -> JE-032 | B66: ='Transaction Mapping'!C34 -> 45868 | C66: ="Bank Statement" -> Bank Statement | D66: ='Transaction Mapping'!E34 -> HBL250730033 | E66: ='Transaction Mapping'!D34 -> Profit credited on current-plus account | F66: ='Transaction Mapping'!M34 -> 1066 | G66: ='Transaction Mapping'!N34 -> GL not found | H66: =IF('Transaction Mapping'!F34>0,'Transaction Mapping'!F34,0) -> 0 | I66: =IF('Transaction Mapping'!G34>0,'Transaction Mapping'!G34,0) -> 18450 | J66: ='Transaction Mapping'!P34 -> Truck It In (Private) Limited | K66: ='Transaction Mapping'!O34 -> Advance tax review | L66: ="Posted" -> Posted | M66: ='Transaction Mapping'!T34 -> Operating - Receipts
A67: ="JE-033" -> JE-033 | B67: ='Transaction Mapping'!C35 -> 45869 | C67: ="Bank Statement" -> Bank Statement | D67: ='Transaction Mapping'!E35 -> HBL250731034 | E67: ='Transaction Mapping'!D35 -> Zakat deduction on profit account | F67: ='Transaction Mapping'!K35 -> 1029 | G67: ='Transaction Mapping'!L35 -> GL not found | H67: =IF('Transaction Mapping'!G35>0,'Transaction Mapping'!G35,0) -> 0 | I67: =IF('Transaction Mapping'!F35>0,'Transaction Mapping'!F35,0) -> 461 | J67: ='Transaction Mapping'!P35 -> Truck It In (Private) Limited | K67: ='Transaction Mapping'!O35 -> N/A | L67: ="Posted" -> Posted | M67: ='Transaction Mapping'!T35 -> Operating - Payments
A68: ="JE-033" -> JE-033 | B68: ='Transaction Mapping'!C35 -> 45869 | C68: ="Bank Statement" -> Bank Statement | D68: ='Transaction Mapping'!E35 -> HBL250731034 | E68: ='Transaction Mapping'!D35 -> Zakat deduction on profit account | F68: ='Transaction Mapping'!M35 -> 1068 | G68: ='Transaction Mapping'!N35 -> GL not found | H68: =IF('Transaction Mapping'!F35>0,'Transaction Mapping'!F35,0) -> 461 | I68: =IF('Transaction Mapping'!G35>0,'Transaction Mapping'!G35,0) -> 0 | J68: ='Transaction Mapping'!P35 -> Truck It In (Private) Limited | K68: ='Transaction Mapping'!O35 -> N/A | L68: ="Posted" -> Posted | M68: ='Transaction Mapping'!T35 -> Operating - Payments
A69: ="JE-034" -> JE-034 | B69: ='Transaction Mapping'!C36 -> 45869 | C69: ="Bank Statement" -> Bank Statement | D69: ='Transaction Mapping'!E36 -> HBL250731035 | E69: ='Transaction Mapping'!D36 -> Advance tax on bank profit | F69: ='Transaction Mapping'!K36 -> 1029 | G69: ='Transaction Mapping'!L36 -> GL not found | H69: =IF('Transaction Mapping'!G36>0,'Transaction Mapping'!G36,0) -> 0 | I69: =IF('Transaction Mapping'!F36>0,'Transaction Mapping'!F36,0) -> 2768 | J69: ='Transaction Mapping'!P36 -> Truck It In (Private) Limited | K69: ='Transaction Mapping'!O36 -> Advance income tax | L69: ="Posted" -> Posted | M69: ='Transaction Mapping'!T36 -> Operating - Payments
A70: ="JE-034" -> JE-034 | B70: ='Transaction Mapping'!C36 -> 45869 | C70: ="Bank Statement" -> Bank Statement | D70: ='Transaction Mapping'!E36 -> HBL250731035 | E70: ='Transaction Mapping'!D36 -> Advance tax on bank profit | F70: ='Transaction Mapping'!M36 -> 1045 | G70: ='Transaction Mapping'!N36 -> GL not found | H70: =IF('Transaction Mapping'!F36>0,'Transaction Mapping'!F36,0) -> 2768 | I70: =IF('Transaction Mapping'!G36>0,'Transaction Mapping'!G36,0) -> 0 | J70: ='Transaction Mapping'!P36 -> Truck It In (Private) Limited | K70: ='Transaction Mapping'!O36 -> Advance income tax | L70: ="Posted" -> Posted | M70: ='Transaction Mapping'!T36 -> Operating - Payments
A71: ="JE-035" -> JE-035 | B71: ='Transaction Mapping'!C37 -> 45839 | C71: ="Bank Statement" -> Bank Statement | D71: ='Transaction Mapping'!E37 -> MBL250701001 | E71: ='Transaction Mapping'!D37 -> Opening-month cash deposit - payroll adjustments | F71: ='Transaction Mapping'!K37 -> 1030 | G71: ='Transaction Mapping'!L37 -> GL not found | H71: =IF('Transaction Mapping'!G37>0,'Transaction Mapping'!G37,0) -> 25000 | I71: =IF('Transaction Mapping'!F37>0,'Transaction Mapping'!F37,0) -> 0 | J71: ='Transaction Mapping'!P37 -> Truck It In (Private) Limited | K71: ='Transaction Mapping'!O37 -> N/A | L71: ="Posted" -> Posted | M71: ='Transaction Mapping'!T37 -> Operating - Receipts
A72: ="JE-035" -> JE-035 | B72: ='Transaction Mapping'!C37 -> 45839 | C72: ="Bank Statement" -> Bank Statement | D72: ='Transaction Mapping'!E37 -> MBL250701001 | E72: ='Transaction Mapping'!D37 -> Opening-month cash deposit - payroll adjustments | F72: ='Transaction Mapping'!M37 -> 1034 | G72: ='Transaction Mapping'!N37 -> GL not found | H72: =IF('Transaction Mapping'!F37>0,'Transaction Mapping'!F37,0) -> 0 | I72: =IF('Transaction Mapping'!G37>0,'Transaction Mapping'!G37,0) -> 25000 | J72: ='Transaction Mapping'!P37 -> Truck It In (Private) Limited | K72: ='Transaction Mapping'!O37 -> N/A | L72: ="Posted" -> Posted | M72: ='Transaction Mapping'!T37 -> Operating - Receipts
A73: ="JE-036" -> JE-036 | B73: ='Transaction Mapping'!C38 -> 45840 | C73: ="Bank Statement" -> Bank Statement | D73: ='Transaction Mapping'!E38 -> MBL250702002 | E73: ='Transaction Mapping'!D38 -> IBFT - Employee reimbursement - A. Khan | F73: ='Transaction Mapping'!K38 -> 1030 | G73: ='Transaction Mapping'!L38 -> GL not found | H73: =IF('Transaction Mapping'!G38>0,'Transaction Mapping'!G38,0) -> 0 | I73: =IF('Transaction Mapping'!F38>0,'Transaction Mapping'!F38,0) -> 18500 | J73: ='Transaction Mapping'!P38 -> Truck It In (Private) Limited | K73: ='Transaction Mapping'!O38 -> N/A | L73: ="Posted" -> Posted | M73: ='Transaction Mapping'!T38 -> Operating - Payments
A74: ="JE-036" -> JE-036 | B74: ='Transaction Mapping'!C38 -> 45840 | C74: ="Bank Statement" -> Bank Statement | D74: ='Transaction Mapping'!E38 -> MBL250702002 | E74: ='Transaction Mapping'!D38 -> IBFT - Employee reimbursement - A. Khan | F74: ='Transaction Mapping'!M38 -> 1068 | G74: ='Transaction Mapping'!N38 -> GL not found | H74: =IF('Transaction Mapping'!F38>0,'Transaction Mapping'!F38,0) -> 18500 | I74: =IF('Transaction Mapping'!G38>0,'Transaction Mapping'!G38,0) -> 0 | J74: ='Transaction Mapping'!P38 -> Truck It In (Private) Limited | K74: ='Transaction Mapping'!O38 -> N/A | L74: ="Posted" -> Posted | M74: ='Transaction Mapping'!T38 -> Operating - Payments
A75: ="JE-037" -> JE-037 | B75: ='Transaction Mapping'!C39 -> 45841 | C75: ="Bank Statement" -> Bank Statement | D75: ='Transaction Mapping'!E39 -> MBL250703003 | E75: ='Transaction Mapping'!D39 -> IBFT - Rider incentive batch 01 | F75: ='Transaction Mapping'!K39 -> 1030 | G75: ='Transaction Mapping'!L39 -> GL not found | H75: =IF('Transaction Mapping'!G39>0,'Transaction Mapping'!G39,0) -> 0 | I75: =IF('Transaction Mapping'!F39>0,'Transaction Mapping'!F39,0) -> 96500 | J75: ='Transaction Mapping'!P39 -> Truck It In (Private) Limited | K75: ='Transaction Mapping'!O39 -> Payroll | L75: ="Posted" -> Posted | M75: ='Transaction Mapping'!T39 -> Operating - Payments
A76: ="JE-037" -> JE-037 | B76: ='Transaction Mapping'!C39 -> 45841 | C76: ="Bank Statement" -> Bank Statement | D76: ='Transaction Mapping'!E39 -> MBL250703003 | E76: ='Transaction Mapping'!D39 -> IBFT - Rider incentive batch 01 | F76: ='Transaction Mapping'!M39 -> 1056 | G76: ='Transaction Mapping'!N39 -> GL not found | H76: =IF('Transaction Mapping'!F39>0,'Transaction Mapping'!F39,0) -> 96500 | I76: =IF('Transaction Mapping'!G39>0,'Transaction Mapping'!G39,0) -> 0 | J76: ='Transaction Mapping'!P39 -> Truck It In (Private) Limited | K76: ='Transaction Mapping'!O39 -> Payroll | L76: ="Posted" -> Posted | M76: ='Transaction Mapping'!T39 -> Operating - Payments
A77: ="JE-038" -> JE-038 | B77: ='Transaction Mapping'!C40 -> 45842 | C77: ="Bank Statement" -> Bank Statement | D77: ='Transaction Mapping'!E40 -> MBL250704004 | E77: ='Transaction Mapping'!D40 -> Online payment - EOBI contribution June | F77: ='Transaction Mapping'!K40 -> 1030 | G77: ='Transaction Mapping'!L40 -> GL not found | H77: =IF('Transaction Mapping'!G40>0,'Transaction Mapping'!G40,0) -> 0 | I77: =IF('Transaction Mapping'!F40>0,'Transaction Mapping'!F40,0) -> 68400 | J77: ='Transaction Mapping'!P40 -> Truck It In (Private) Limited | K77: ='Transaction Mapping'!O40 -> Payroll statutory | L77: ="Posted" -> Posted | M77: ='Transaction Mapping'!T40 -> Operating - Payments
A78: ="JE-038" -> JE-038 | B78: ='Transaction Mapping'!C40 -> 45842 | C78: ="Bank Statement" -> Bank Statement | D78: ='Transaction Mapping'!E40 -> MBL250704004 | E78: ='Transaction Mapping'!D40 -> Online payment - EOBI contribution June | F78: ='Transaction Mapping'!M40 -> 1034 | G78: ='Transaction Mapping'!N40 -> GL not found | H78: =IF('Transaction Mapping'!F40>0,'Transaction Mapping'!F40,0) -> 68400 | I78: =IF('Transaction Mapping'!G40>0,'Transaction Mapping'!G40,0) -> 0 | J78: ='Transaction Mapping'!P40 -> Truck It In (Private) Limited | K78: ='Transaction Mapping'!O40 -> Payroll statutory | L78: ="Posted" -> Posted | M78: ='Transaction Mapping'!T40 -> Operating - Payments
A79: ="JE-039" -> JE-039 | B79: ='Transaction Mapping'!C41 -> 45843 | C79: ="Bank Statement" -> Bank Statement | D79: ='Transaction Mapping'!E41 -> MBL250705005 | E79: ='Transaction Mapping'!D41 -> Online payment - Social Security contribution June | F79: ='Transaction Mapping'!K41 -> 1030 | G79: ='Transaction Mapping'!L41 -> GL not found | H79: =IF('Transaction Mapping'!G41>0,'Transaction Mapping'!G41,0) -> 0 | I79: =IF('Transaction Mapping'!F41>0,'Transaction Mapping'!F41,0) -> 42750 | J79: ='Transaction Mapping'!P41 -> Truck It In (Private) Limited | K79: ='Transaction Mapping'!O41 -> Payroll statutory | L79: ="Posted" -> Posted | M79: ='Transaction Mapping'!T41 -> Operating - Payments
A80: ="JE-039" -> JE-039 | B80: ='Transaction Mapping'!C41 -> 45843 | C80: ="Bank Statement" -> Bank Statement | D80: ='Transaction Mapping'!E41 -> MBL250705005 | E80: ='Transaction Mapping'!D41 -> Online payment - Social Security contribution June | F80: ='Transaction Mapping'!M41 -> 1034 | G80: ='Transaction Mapping'!N41 -> GL not found | H80: =IF('Transaction Mapping'!F41>0,'Transaction Mapping'!F41,0) -> 42750 | I80: =IF('Transaction Mapping'!G41>0,'Transaction Mapping'!G41,0) -> 0 | J80: ='Transaction Mapping'!P41 -> Truck It In (Private) Limited | K80: ='Transaction Mapping'!O41 -> Payroll statutory | L80: ="Posted" -> Posted | M80: ='Transaction Mapping'!T41 -> Operating - Payments
A81: ="JE-040" -> JE-040 | B81: ='Transaction Mapping'!C43 -> 45845 | C81: ="Bank Statement" -> Bank Statement | D81: ='Transaction Mapping'!E43 -> PAY250707A | E81: ='Transaction Mapping'!D43 -> Bulk salary transfer - July payroll batch A | F81: ='Transaction Mapping'!K43 -> 1030 | G81: ='Transaction Mapping'!L43 -> GL not found | H81: =IF('Transaction Mapping'!G43>0,'Transaction Mapping'!G43,0) -> 0 | I81: =IF('Transaction Mapping'!F43>0,'Transaction Mapping'!F43,0) -> 625000 | J81: ='Transaction Mapping'!P43 -> Truck It In (Private) Limited | K81: ='Transaction Mapping'!O43 -> Payroll | L81: ="Posted" -> Posted | M81: ='Transaction Mapping'!T43 -> Operating - Payments
A82: ="JE-040" -> JE-040 | B82: ='Transaction Mapping'!C43 -> 45845 | C82: ="Bank Statement" -> Bank Statement | D82: ='Transaction Mapping'!E43 -> PAY250707A | E82: ='Transaction Mapping'!D43 -> Bulk salary transfer - July payroll batch A | F82: ='Transaction Mapping'!M43 -> 1034 | G82: ='Transaction Mapping'!N43 -> GL not found | H82: =IF('Transaction Mapping'!F43>0,'Transaction Mapping'!F43,0) -> 625000 | I82: =IF('Transaction Mapping'!G43>0,'Transaction Mapping'!G43,0) -> 0 | J82: ='Transaction Mapping'!P43 -> Truck It In (Private) Limited | K82: ='Transaction Mapping'!O43 -> Payroll | L82: ="Posted" -> Posted | M82: ='Transaction Mapping'!T43 -> Operating - Payments
A83: ="JE-041" -> JE-041 | B83: ='Transaction Mapping'!C44 -> 45845 | C83: ="Bank Statement" -> Bank Statement | D83: ='Transaction Mapping'!E44 -> MBL250707008 | E83: ='Transaction Mapping'!D44 -> Payroll processing charges | F83: ='Transaction Mapping'!K44 -> 1030 | G83: ='Transaction Mapping'!L44 -> GL not found | H83: =IF('Transaction Mapping'!G44>0,'Transaction Mapping'!G44,0) -> 0 | I83: =IF('Transaction Mapping'!F44>0,'Transaction Mapping'!F44,0) -> 3750 | J83: ='Transaction Mapping'!P44 -> Truck It In (Private) Limited | K83: ='Transaction Mapping'!O44 -> N/A | L83: ="Posted" -> Posted | M83: ='Transaction Mapping'!T44 -> Operating - Payments
A84: ="JE-041" -> JE-041 | B84: ='Transaction Mapping'!C44 -> 45845 | C84: ="Bank Statement" -> Bank Statement | D84: ='Transaction Mapping'!E44 -> MBL250707008 | E84: ='Transaction Mapping'!D44 -> Payroll processing charges | F84: ='Transaction Mapping'!M44 -> 1057 | G84: ='Transaction Mapping'!N44 -> GL not found | H84: =IF('Transaction Mapping'!F44>0,'Transaction Mapping'!F44,0) -> 3750 | I84: =IF('Transaction Mapping'!G44>0,'Transaction Mapping'!G44,0) -> 0 | J84: ='Transaction Mapping'!P44 -> Truck It In (Private) Limited | K84: ='Transaction Mapping'!O44 -> N/A | L84: ="Posted" -> Posted | M84: ='Transaction Mapping'!T44 -> Operating - Payments
A85: ="JE-042" -> JE-042 | B85: ='Transaction Mapping'!C45 -> 45845 | C85: ="Bank Statement" -> Bank Statement | D85: ='Transaction Mapping'!E45 -> MBL250707009 | E85: ='Transaction Mapping'!D45 -> FED on payroll processing charges | F85: ='Transaction Mapping'!K45 -> 1030 | G85: ='Transaction Mapping'!L45 -> GL not found | H85: =IF('Transaction Mapping'!G45>0,'Transaction Mapping'!G45,0) -> 0 | I85: =IF('Transaction Mapping'!F45>0,'Transaction Mapping'!F45,0) -> 600 | J85: ='Transaction Mapping'!P45 -> Truck It In (Private) Limited | K85: ='Transaction Mapping'!O45 -> FED expense | L85: ="Posted" -> Posted | M85: ='Transaction Mapping'!T45 -> Operating - Payments
A86: ="JE-042" -> JE-042 | B86: ='Transaction Mapping'!C45 -> 45845 | C86: ="Bank Statement" -> Bank Statement | D86: ='Transaction Mapping'!E45 -> MBL250707009 | E86: ='Transaction Mapping'!D45 -> FED on payroll processing charges | F86: ='Transaction Mapping'!M45 -> 1068 | G86: ='Transaction Mapping'!N45 -> GL not found | H86: =IF('Transaction Mapping'!F45>0,'Transaction Mapping'!F45,0) -> 600 | I86: =IF('Transaction Mapping'!G45>0,'Transaction Mapping'!G45,0) -> 0 | J86: ='Transaction Mapping'!P45 -> Truck It In (Private) Limited | K86: ='Transaction Mapping'!O45 -> FED expense | L86: ="Posted" -> Posted | M86: ='Transaction Mapping'!T45 -> Operating - Payments
A87: ="JE-043" -> JE-043 | B87: ='Transaction Mapping'!C46 -> 45846 | C87: ="Bank Statement" -> Bank Statement | D87: ='Transaction Mapping'!E46 -> MBL250708010 | E87: ='Transaction Mapping'!D46 -> IBFT - Employee advance - M. Usman | F87: ='Transaction Mapping'!K46 -> 1030 | G87: ='Transaction Mapping'!L46 -> GL not found | H87: =IF('Transaction Mapping'!G46>0,'Transaction Mapping'!G46,0) -> 0 | I87: =IF('Transaction Mapping'!F46>0,'Transaction Mapping'!F46,0) -> 30000 | J87: ='Transaction Mapping'!P46 -> Truck It In (Private) Limited | K87: ='Transaction Mapping'!O46 -> N/A | L87: ="Posted" -> Posted | M87: ='Transaction Mapping'!T46 -> Operating - Payments
A88: ="JE-043" -> JE-043 | B88: ='Transaction Mapping'!C46 -> 45846 | C88: ="Bank Statement" -> Bank Statement | D88: ='Transaction Mapping'!E46 -> MBL250708010 | E88: ='Transaction Mapping'!D46 -> IBFT - Employee advance - M. Usman | F88: ='Transaction Mapping'!M46 -> 1025 | G88: ='Transaction Mapping'!N46 -> GL not found | H88: =IF('Transaction Mapping'!F46>0,'Transaction Mapping'!F46,0) -> 30000 | I88: =IF('Transaction Mapping'!G46>0,'Transaction Mapping'!G46,0) -> 0 | J88: ='Transaction Mapping'!P46 -> Truck It In (Private) Limited | K88: ='Transaction Mapping'!O46 -> N/A | L88: ="Posted" -> Posted | M88: ='Transaction Mapping'!T46 -> Operating - Payments
A89: ="JE-044" -> JE-044 | B89: ='Transaction Mapping'!C47 -> 45848 | C89: ="Bank Statement" -> Bank Statement | D89: ='Transaction Mapping'!E47 -> MBL250710011 | E89: ='Transaction Mapping'!D47 -> Bulk transfer - Contract drivers settlement W27 | F89: ='Transaction Mapping'!K47 -> 1030 | G89: ='Transaction Mapping'!L47 -> GL not found | H89: =IF('Transaction Mapping'!G47>0,'Transaction Mapping'!G47,0) -> 0 | I89: =IF('Transaction Mapping'!F47>0,'Transaction Mapping'!F47,0) -> 156000 | J89: ='Transaction Mapping'!P47 -> Truck It In (Private) Limited | K89: ='Transaction Mapping'!O47 -> WHT review | L89: ="Posted" -> Posted | M89: ='Transaction Mapping'!T47 -> Operating - Payments
A90: ="JE-044" -> JE-044 | B90: ='Transaction Mapping'!C47 -> 45848 | C90: ="Bank Statement" -> Bank Statement | D90: ='Transaction Mapping'!E47 -> MBL250710011 | E90: ='Transaction Mapping'!D47 -> Bulk transfer - Contract drivers settlement W27 | F90: ='Transaction Mapping'!M47 -> 1054 | G90: ='Transaction Mapping'!N47 -> GL not found | H90: =IF('Transaction Mapping'!F47>0,'Transaction Mapping'!F47,0) -> 156000 | I90: =IF('Transaction Mapping'!G47>0,'Transaction Mapping'!G47,0) -> 0 | J90: ='Transaction Mapping'!P47 -> Truck It In (Private) Limited | K90: ='Transaction Mapping'!O47 -> WHT review | L90: ="Posted" -> Posted | M90: ='Transaction Mapping'!T47 -> Operating - Payments
A91: ="JE-045" -> JE-045 | B91: ='Transaction Mapping'!C48 -> 45849 | C91: ="Bank Statement" -> Bank Statement | D91: ='Transaction Mapping'!E48 -> MBL250711012 | E91: ='Transaction Mapping'!D48 -> Raast reversal - failed driver payment W27 | F91: ='Transaction Mapping'!K48 -> 1030 | G91: ='Transaction Mapping'!L48 -> GL not found | H91: =IF('Transaction Mapping'!G48>0,'Transaction Mapping'!G48,0) -> 12000 | I91: =IF('Transaction Mapping'!F48>0,'Transaction Mapping'!F48,0) -> 0 | J91: ='Transaction Mapping'!P48 -> Truck It In (Private) Limited | K91: ='Transaction Mapping'!O48 -> N/A | L91: ="Posted" -> Posted | M91: ='Transaction Mapping'!T48 -> Operating - Receipts
A92: ="JE-045" -> JE-045 | B92: ='Transaction Mapping'!C48 -> 45849 | C92: ="Bank Statement" -> Bank Statement | D92: ='Transaction Mapping'!E48 -> MBL250711012 | E92: ='Transaction Mapping'!D48 -> Raast reversal - failed driver payment W27 | F92: ='Transaction Mapping'!M48 -> 1054 | G92: ='Transaction Mapping'!N48 -> GL not found | H92: =IF('Transaction Mapping'!F48>0,'Transaction Mapping'!F48,0) -> 0 | I92: =IF('Transaction Mapping'!G48>0,'Transaction Mapping'!G48,0) -> 12000 | J92: ='Transaction Mapping'!P48 -> Truck It In (Private) Limited | K92: ='Transaction Mapping'!O48 -> N/A | L92: ="Posted" -> Posted | M92: ='Transaction Mapping'!T48 -> Operating - Receipts
A93: ="JE-046" -> JE-046 | B93: ='Transaction Mapping'!C49 -> 45850 | C93: ="Bank Statement" -> Bank Statement | D93: ='Transaction Mapping'!E49 -> MBL250712013 | E93: ='Transaction Mapping'!D49 -> Raast retry - driver payment W27 | F93: ='Transaction Mapping'!K49 -> 1030 | G93: ='Transaction Mapping'!L49 -> GL not found | H93: =IF('Transaction Mapping'!G49>0,'Transaction Mapping'!G49,0) -> 0 | I93: =IF('Transaction Mapping'!F49>0,'Transaction Mapping'!F49,0) -> 12000 | J93: ='Transaction Mapping'!P49 -> Truck It In (Private) Limited | K93: ='Transaction Mapping'!O49 -> WHT review | L93: ="Posted" -> Posted | M93: ='Transaction Mapping'!T49 -> Operating - Payments
A94: ="JE-046" -> JE-046 | B94: ='Transaction Mapping'!C49 -> 45850 | C94: ="Bank Statement" -> Bank Statement | D94: ='Transaction Mapping'!E49 -> MBL250712013 | E94: ='Transaction Mapping'!D49 -> Raast retry - driver payment W27 | F94: ='Transaction Mapping'!M49 -> 1054 | G94: ='Transaction Mapping'!N49 -> GL not found | H94: =IF('Transaction Mapping'!F49>0,'Transaction Mapping'!F49,0) -> 12000 | I94: =IF('Transaction Mapping'!G49>0,'Transaction Mapping'!G49,0) -> 0 | J94: ='Transaction Mapping'!P49 -> Truck It In (Private) Limited | K94: ='Transaction Mapping'!O49 -> WHT review | L94: ="Posted" -> Posted | M94: ='Transaction Mapping'!T49 -> Operating - Payments
A95: ="JE-047" -> JE-047 | B95: ='Transaction Mapping'!C50 -> 45852 | C95: ="Bank Statement" -> Bank Statement | D95: ='Transaction Mapping'!E50 -> MBL250714014 | E95: ='Transaction Mapping'!D50 -> IBFT - Staff travel advance - Lahore operations | F95: ='Transaction Mapping'!K50 -> 1030 | G95: ='Transaction Mapping'!L50 -> GL not found | H95: =IF('Transaction Mapping'!G50>0,'Transaction Mapping'!G50,0) -> 0 | I95: =IF('Transaction Mapping'!F50>0,'Transaction Mapping'!F50,0) -> 45000 | J95: ='Transaction Mapping'!P50 -> Truck It In (Private) Limited | K95: ='Transaction Mapping'!O50 -> N/A | L95: ="Posted" -> Posted | M95: ='Transaction Mapping'!T50 -> Operating - Payments
A96: ="JE-047" -> JE-047 | B96: ='Transaction Mapping'!C50 -> 45852 | C96: ="Bank Statement" -> Bank Statement | D96: ='Transaction Mapping'!E50 -> MBL250714014 | E96: ='Transaction Mapping'!D50 -> IBFT - Staff travel advance - Lahore operations | F96: ='Transaction Mapping'!M50 -> 1025 | G96: ='Transaction Mapping'!N50 -> GL not found | H96: =IF('Transaction Mapping'!F50>0,'Transaction Mapping'!F50,0) -> 45000 | I96: =IF('Transaction Mapping'!G50>0,'Transaction Mapping'!G50,0) -> 0 | J96: ='Transaction Mapping'!P50 -> Truck It In (Private) Limited | K96: ='Transaction Mapping'!O50 -> N/A | L96: ="Posted" -> Posted | M96: ='Transaction Mapping'!T50 -> Operating - Payments
A97: ="JE-048" -> JE-048 | B97: ='Transaction Mapping'!C51 -> 45854 | C97: ="Bank Statement" -> Bank Statement | D97: ='Transaction Mapping'!E51 -> CD250716 | E97: ='Transaction Mapping'!D51 -> Cash deposit - unused staff advance returned | F97: ='Transaction Mapping'!K51 -> 1030 | G97: ='Transaction Mapping'!L51 -> GL not found | H97: =IF('Transaction Mapping'!G51>0,'Transaction Mapping'!G51,0) -> 7500 | I97: =IF('Transaction Mapping'!F51>0,'Transaction Mapping'!F51,0) -> 0 | J97: ='Transaction Mapping'!P51 -> Truck It In (Private) Limited | K97: ='Transaction Mapping'!O51 -> N/A | L97: ="Posted" -> Posted | M97: ='Transaction Mapping'!T51 -> Operating - Receipts
A98: ="JE-048" -> JE-048 | B98: ='Transaction Mapping'!C51 -> 45854 | C98: ="Bank Statement" -> Bank Statement | D98: ='Transaction Mapping'!E51 -> CD250716 | E98: ='Transaction Mapping'!D51 -> Cash deposit - unused staff advance returned | F98: ='Transaction Mapping'!M51 -> 1025 | G98: ='Transaction Mapping'!N51 -> GL not found | H98: =IF('Transaction Mapping'!F51>0,'Transaction Mapping'!F51,0) -> 0 | I98: =IF('Transaction Mapping'!G51>0,'Transaction Mapping'!G51,0) -> 7500 | J98: ='Transaction Mapping'!P51 -> Truck It In (Private) Limited | K98: ='Transaction Mapping'!O51 -> N/A | L98: ="Posted" -> Posted | M98: ='Transaction Mapping'!T51 -> Operating - Receipts
A99: ="JE-049" -> JE-049 | B99: ='Transaction Mapping'!C52 -> 45856 | C99: ="Bank Statement" -> Bank Statement | D99: ='Transaction Mapping'!E52 -> MBL250718016 | E99: ='Transaction Mapping'!D52 -> Bulk transfer - Contract drivers settlement W28 | F99: ='Transaction Mapping'!K52 -> 1030 | G99: ='Transaction Mapping'!L52 -> GL not found | H99: =IF('Transaction Mapping'!G52>0,'Transaction Mapping'!G52,0) -> 0 | I99: =IF('Transaction Mapping'!F52>0,'Transaction Mapping'!F52,0) -> 142500 | J99: ='Transaction Mapping'!P52 -> Truck It In (Private) Limited | K99: ='Transaction Mapping'!O52 -> WHT review | L99: ="Posted" -> Posted | M99: ='Transaction Mapping'!T52 -> Operating - Payments
A100: ="JE-049" -> JE-049 | B100: ='Transaction Mapping'!C52 -> 45856 | C100: ="Bank Statement" -> Bank Statement | D100: ='Transaction Mapping'!E52 -> MBL250718016 | E100: ='Transaction Mapping'!D52 -> Bulk transfer - Contract drivers settlement W28 | F100: ='Transaction Mapping'!M52 -> 1054 | G100: ='Transaction Mapping'!N52 -> GL not found | H100: =IF('Transaction Mapping'!F52>0,'Transaction Mapping'!F52,0) -> 142500 | I100: =IF('Transaction Mapping'!G52>0,'Transaction Mapping'!G52,0) -> 0 | J100: ='Transaction Mapping'!P52 -> Truck It In (Private) Limited | K100: ='Transaction Mapping'!O52 -> WHT review | L100: ="Posted" -> Posted | M100: ='Transaction Mapping'!T52 -> Operating - Payments
...

Sheet General Ledger
A1: General Ledger
A2: Date | B2: JE ID | C2: Reference | D2: GL Code | E2: GL Account | F2: Description | G2: Debit | H2: Credit | I2: Net Movement | J2: Running Balance | K2: Posting Status
A3: ='Journal Entries'!B3 -> 45839 | B3: ='Journal Entries'!A3 -> JE-001 | C3: ='Journal Entries'!D3 -> HBL250701001 | D3: ='Journal Entries'!F3 -> 1029 | E3: ='Journal Entries'!G3 -> GL not found | F3: ='Journal Entries'!E3 -> IBFT CR - Daraz Pakistan settlement INV-DZ-250701 | G3: ='Journal Entries'!H3 -> 685000 | H3: ='Journal Entries'!I3 -> 0 | I3: =G3-H3 -> 685000 | J3: =SUMIFS($I$3:I3,$D$3:D3,D3) -> 685000 | K3: ='Journal Entries'!L3 -> Posted
A4: ='Journal Entries'!B4 -> 45839 | B4: ='Journal Entries'!A4 -> JE-001 | C4: ='Journal Entries'!D4 -> HBL250701001 | D4: ='Journal Entries'!F4 -> 1018 | E4: ='Journal Entries'!G4 -> GL not found | F4: ='Journal Entries'!E4 -> IBFT CR - Daraz Pakistan settlement INV-DZ-250701 | G4: ='Journal Entries'!H4 -> 0 | H4: ='Journal Entries'!I4 -> 685000 | I4: =G4-H4 -> -685000 | J4: =SUMIFS($I$3:I4,$D$3:D4,D4) -> -685000 | K4: ='Journal Entries'!L4 -> Posted
A5: ='Journal Entries'!B5 -> 45839 | B5: ='Journal Entries'!A5 -> JE-002 | C5: ='Journal Entries'!D5 -> HBL250701002 | D5: ='Journal Entries'!F5 -> 1029 | E5: ='Journal Entries'!G5 -> GL not found | F5: ='Journal Entries'!E5 -> Online transfer - Office rent July - Blue Area Properties | G5: ='Journal Entries'!H5 -> 0 | H5: ='Journal Entries'!I5 -> 275000 | I5: =G5-H5 -> -275000 | J5: =SUMIFS($I$3:I5,$D$3:D5,D5) -> 410000 | K5: ='Journal Entries'!L5 -> Posted
A6: ='Journal Entries'!B6 -> 45839 | B6: ='Journal Entries'!A6 -> JE-002 | C6: ='Journal Entries'!D6 -> HBL250701002 | D6: ='Journal Entries'!F6 -> 1058 | E6: ='Journal Entries'!G6 -> GL not found | F6: ='Journal Entries'!E6 -> Online transfer - Office rent July - Blue Area Properties | G6: ='Journal Entries'!H6 -> 275000 | H6: ='Journal Entries'!I6 -> 0 | I6: =G6-H6 -> 275000 | J6: =SUMIFS($I$3:I6,$D$3:D6,D6) -> 275000 | K6: ='Journal Entries'!L6 -> Posted
A7: ='Journal Entries'!B7 -> 45840 | B7: ='Journal Entries'!A7 -> JE-003 | C7: ='Journal Entries'!D7 -> HBL250702003 | D7: ='Journal Entries'!F7 -> 1029 | E7: ='Journal Entries'!G7 -> GL not found | F7: ='Journal Entries'!E7 -> Raast CR - Onic distribution collection Batch 0702 | G7: ='Journal Entries'!H7 -> 412500 | H7: ='Journal Entries'!I7 -> 0 | I7: =G7-H7 -> 412500 | J7: =SUMIFS($I$3:I7,$D$3:D7,D7) -> 822500 | K7: ='Journal Entries'!L7 -> Posted
A8: ='Journal Entries'!B8 -> 45840 | B8: ='Journal Entries'!A8 -> JE-003 | C8: ='Journal Entries'!D8 -> HBL250702003 | D8: ='Journal Entries'!F8 -> 1018 | E8: ='Journal Entries'!G8 -> GL not found | F8: ='Journal Entries'!E8 -> Raast CR - Onic distribution collection Batch 0702 | G8: ='Journal Entries'!H8 -> 0 | H8: ='Journal Entries'!I8 -> 412500 | I8: =G8-H8 -> -412500 | J8: =SUMIFS($I$3:I8,$D$3:D8,D8) -> -1097500 | K8: ='Journal Entries'!L8 -> Posted
A9: ='Journal Entries'!B9 -> 45840 | B9: ='Journal Entries'!A9 -> JE-004 | C9: ='Journal Entries'!D9 -> HBL250702004 | D9: ='Journal Entries'!F9 -> 1029 | E9: ='Journal Entries'!G9 -> GL not found | F9: ='Journal Entries'!E9 -> POS 7712 - Shell F-8 Islamabad | G9: ='Journal Entries'!H9 -> 0 | H9: ='Journal Entries'!I9 -> 18450 | I9: =G9-H9 -> -18450 | J9: =SUMIFS($I$3:I9,$D$3:D9,D9) -> 804050 | K9: ='Journal Entries'!L9 -> Posted
A10: ='Journal Entries'!B10 -> 45840 | B10: ='Journal Entries'!A10 -> JE-004 | C10: ='Journal Entries'!D10 -> HBL250702004 | D10: ='Journal Entries'!F10 -> 1055 | E10: ='Journal Entries'!G10 -> GL not found | F10: ='Journal Entries'!E10 -> POS 7712 - Shell F-8 Islamabad | G10: ='Journal Entries'!H10 -> 18450 | H10: ='Journal Entries'!I10 -> 0 | I10: =G10-H10 -> 18450 | J10: =SUMIFS($I$3:I10,$D$3:D10,D10) -> 18450 | K10: ='Journal Entries'!L10 -> Posted
A11: ='Journal Entries'!B11 -> 45841 | B11: ='Journal Entries'!A11 -> JE-005 | C11: ='Journal Entries'!D11 -> CHQ104583 | D11: ='Journal Entries'!F11 -> 1029 | E11: ='Journal Entries'!G11 -> GL not found | F11: ='Journal Entries'!E11 -> Cheque 104583 - Pak Cargo Fleet Services | G11: ='Journal Entries'!H11 -> 0 | H11: ='Journal Entries'!I11 -> 335000 | I11: =G11-H11 -> -335000 | J11: =SUMIFS($I$3:I11,$D$3:D11,D11) -> 469050 | K11: ='Journal Entries'!L11 -> Posted
A12: ='Journal Entries'!B12 -> 45841 | B12: ='Journal Entries'!A12 -> JE-005 | C12: ='Journal Entries'!D12 -> CHQ104583 | D12: ='Journal Entries'!F12 -> 1054 | E12: ='Journal Entries'!G12 -> GL not found | F12: ='Journal Entries'!E12 -> Cheque 104583 - Pak Cargo Fleet Services | G12: ='Journal Entries'!H12 -> 335000 | H12: ='Journal Entries'!I12 -> 0 | I12: =G12-H12 -> 335000 | J12: =SUMIFS($I$3:I12,$D$3:D12,D12) -> 335000 | K12: ='Journal Entries'!L12 -> Posted
A13: ='Journal Entries'!B13 -> 45841 | B13: ='Journal Entries'!A13 -> JE-006 | C13: ='Journal Entries'!D13 -> WHT104583 | D13: ='Journal Entries'!F13 -> 1029 | E13: ='Journal Entries'!G13 -> GL not found | F13: ='Journal Entries'!E13 -> Withholding tax on cheque 104583 | G13: ='Journal Entries'!H13 -> 0 | H13: ='Journal Entries'!I13 -> 3350 | I13: =G13-H13 -> -3350 | J13: =SUMIFS($I$3:I13,$D$3:D13,D13) -> 465700 | K13: ='Journal Entries'!L13 -> Posted
A14: ='Journal Entries'!B14 -> 45841 | B14: ='Journal Entries'!A14 -> JE-006 | C14: ='Journal Entries'!D14 -> WHT104583 | D14: ='Journal Entries'!F14 -> 1036 | E14: ='Journal Entries'!G14 -> GL not found | F14: ='Journal Entries'!E14 -> Withholding tax on cheque 104583 | G14: ='Journal Entries'!H14 -> 3350 | H14: ='Journal Entries'!I14 -> 0 | I14: =G14-H14 -> 3350 | J14: =SUMIFS($I$3:I14,$D$3:D14,D14) -> 3350 | K14: ='Journal Entries'!L14 -> Posted
... A135: ='Journal Entries'!B135 -> 45869 | B135: ='Journal Entries'!A135 -> JE-065 | C135: ='Journal Entries'!D135 -> NB-007 | D135: ='Journal Entries'!F135 -> 1047 | E135: ='Journal Entries'!G135 -> GL not found | F135: ='Journal Entries'!E135 -> Current income tax provision | G135: ='Journal Entries'!H135 -> 0 | H135: ='Journal Entries'!I135 -> 140000 | I135: =G135-H135 -> -140000 | J135: =SUMIFS($I$3:I135,$D$3:D135,D135) -> -140000 | K135: ='Journal Entries'!L135 -> Posted

Sheet Trial Balance
A1: Trial Balance — 31 July 2025
A2: GL Code | B2: GL Account | C2: Nature | D2: Classification 1 | E2: Opening Debit | F2: Opening Credit | G2: Period Debit | H2: Period Credit | I2: Closing Debit | J2: Closing Credit
A3: ='Chart of Accounts'!H4 | B3: ='Chart of Accounts'!I4 | C3: ='Chart of Accounts'!A4 | D3: ='Chart of Accounts'!B4 | E3: =SUMIFS('Journal Entries'!$H$3:$H$135,'Journal Entries'!$F$3:$F$135,A3,'Journal Entries'!$C$3:$C$135,"Opening Balance") -> 0 | F3: =SUMIFS('Journal Entries'!$I$3:$I$135,'Journal Entries'!$F$3:$F$135,A3,'Journal Entries'!$C$3:$C$135,"Opening Balance") -> 0 | G3: =SUMIFS('Journal Entries'!$H$3:$H$135,'Journal Entries'!$F$3:$F$135,A3)-E3 -> 0 | H3: =SUMIFS('Journal Entries'!$I$3:$I$135,'Journal Entries'!$F$3:$F$135,A3)-F3 -> 0 | I3: =MAX(0,E3+G3-F3-H3) -> 0 | J3: =MAX(0,F3+H3-E3-G3) -> 0
A4: ='Chart of Accounts'!H5 -> Code | B4: ='Chart of Accounts'!I5 -> Title | C4: ='Chart of Accounts'!A5 -> Nature | D4: ='Chart of Accounts'!B5 -> Classification 1 | E4: =SUMIFS('Journal Entries'!$H$3:$H$135,'Journal Entries'!$F$3:$F$135,A4,'Journal Entries'!$C$3:$C$135,"Opening Balance") -> 0 | F4: =SUMIFS('Journal Entries'!$I$3:$I$135,'Journal Entries'!$F$3:$F$135,A4,'Journal Entries'!$C$3:$C$135,"Opening Balance") -> 0 | G4: =SUMIFS('Journal Entries'!$H$3:$H$135,'Journal Entries'!$F$3:$F$135,A4)-E4 -> 0 | H4: =SUMIFS('Journal Entries'!$I$3:$I$135,'Journal Entries'!$F$3:$F$135,A4)-F4 -> 0 | I4: =MAX(0,E4+G4-F4-H4) -> 0 | J4: =MAX(0,F4+H4-E4-G4) -> 0
A5: ='Chart of Accounts'!H6 -> 1011 | B5: ='Chart of Accounts'!I6 -> Furniture and fixture | C5: ='Chart of Accounts'!A6 -> B/S | D5: ='Chart of Accounts'!B6 -> Assets | E5: =SUMIFS('Journal Entries'!$H$3:$H$135,'Journal Entries'!$F$3:$F$135,A5,'Journal Entries'!$C$3:$C$135,"Opening Balance") -> 0 | F5: =SUMIFS('Journal Entries'!$I$3:$I$135,'Journal Entries'!$F$3:$F$135,A5,'Journal Entries'!$C$3:$C$135,"Opening Balance") -> 0 | G5: =SUMIFS('Journal Entries'!$H$3:$H$135,'Journal Entries'!$F$3:$F$135,A5)-E5 -> 0 | H5: =SUMIFS('Journal Entries'!$I$3:$I$135,'Journal Entries'!$F$3:$F$135,A5)-F5 -> 0 | I5: =MAX(0,E5+G5-F5-H5) -> 0 | J5: =MAX(0,F5+H5-E5-G5) -> 0
A6: ='Chart of Accounts'!H7 -> 1012 | B6: ='Chart of Accounts'!I7 -> Leasehold building | C6: ='Chart of Accounts'!A7 -> B/S | D6: ='Chart of Accounts'!B7 -> Assets | E6: =SUMIFS('Journal Entries'!$H$3:$H$135,'Journal Entries'!$F$3:$F$135,A6,'Journal Entries'!$C$3:$C$135,"Opening Balance") -> 0 | F6: =SUMIFS('Journal Entries'!$I$3:$I$135,'Journal Entries'!$F$3:$F$135,A6,'Journal Entries'!$C$3:$C$135,"Opening Balance") -> 0 | G6: =SUMIFS('Journal Entries'!$H$3:$H$135,'Journal Entries'!$F$3:$F$135,A6)-E6 -> 0 | H6: =SUMIFS('Journal Entries'!$I$3:$I$135,'Journal Entries'!$F$3:$F$135,A6)-F6 -> 0 | I6: =MAX(0,E6+G6-F6-H6) -> 0 | J6: =MAX(0,F6+H6-E6-G6) -> 0
A7: ='Chart of Accounts'!H8 -> 1013 | B7: ='Chart of Accounts'!I8 -> Computers | C7: ='Chart of Accounts'!A8 -> B/S | D7: ='Chart of Accounts'!B8 -> Assets | E7: =SUMIFS('Journal Entries'!$H$3:$H$135,'Journal Entries'!$F$3:$F$135,A7,'Journal Entries'!$C$3:$C$135,"Opening Balance") -> 0 | F7: =SUMIFS('Journal Entries'!$I$3:$I$135,'Journal Entries'!$F$3:$F$135,A7,'Journal Entries'!$C$3:$C$135,"Opening Balance") -> 0 | G7: =SUMIFS('Journal Entries'!$H$3:$H$135,'Journal Entries'!$F$3:$F$135,A7)-E7 -> 0 | H7: =SUMIFS('Journal Entries'!$I$3:$I$135,'Journal Entries'!$F$3:$F$135,A7)-F7 -> 0 | I7: =MAX(0,E7+G7-F7-H7) -> 0 | J7: =MAX(0,F7+H7-E7-G7) -> 0
A8: ='Chart of Accounts'!H9 -> 1014 | B8: ='Chart of Accounts'!I9 -> Office Equipments | C8: ='Chart of Accounts'!A9 -> B/S | D8: ='Chart of Accounts'!B9 -> Assets | E8: =SUMIFS('Journal Entries'!$H$3:$H$135,'Journal Entries'!$F$3:$F$135,A8,'Journal Entries'!$C$3:$C$135,"Opening Balance") -> 0 | F8: =SUMIFS('Journal Entries'!$I$3:$I$135,'Journal Entries'!$F$3:$F$135,A8,'Journal Entries'!$C$3:$C$135,"Opening Balance") -> 0 | G8: =SUMIFS('Journal Entries'!$H$3:$H$135,'Journal Entries'!$F$3:$F$135,A8)-E8 -> 0 | H8: =SUMIFS('Journal Entries'!$I$3:$I$135,'Journal Entries'!$F$3:$F$135,A8)-F8 -> 0 | I8: =MAX(0,E8+G8-F8-H8) -> 0 | J8: =MAX(0,F8+H8-E8-G8) -> 0
A9: ='Chart of Accounts'!H10 -> 1015 | B9: ='Chart of Accounts'!I10 -> Vehicles | C9: ='Chart of Accounts'!A10 -> B/S | D9: ='Chart of Accounts'!B10 -> Assets | E9: =SUMIFS('Journal Entries'!$H$3:$H$135,'Journal Entries'!$F$3:$F$135,A9,'Journal Entries'!$C$3:$C$135,"Opening Balance") -> 0 | F9: =SUMIFS('Journal Entries'!$I$3:$I$135,'Journal Entries'!$F$3:$F$135,A9,'Journal Entries'!$C$3:$C$135,"Opening Balance") -> 0 | G9: =SUMIFS('Journal Entries'!$H$3:$H$135,'Journal Entries'!$F$3:$F$135,A9)-E9 -> 0 | H9: =SUMIFS('Journal Entries'!$I$3:$I$135,'Journal Entries'!$F$3:$F$135,A9)-F9 -> 0 | I9: =MAX(0,E9+G9-F9-H9) -> 0 | J9: =MAX(0,F9+H9-E9-G9) -> 0
A10: ='Chart of Accounts'!H11 -> 1016 | B10: ='Chart of Accounts'!I11 -> Intangible Assets | C10: ='Chart of Accounts'!A11 -> B/S | D10: ='Chart of Accounts'!B11 -> Assets | E10: =SUMIFS('Journal Entries'!$H$3:$H$135,'Journal Entries'!$F$3:$F$135,A10,'Journal Entries'!$C$3:$C$135,"Opening Balance") -> 0 | F10: =SUMIFS('Journal Entries'!$I$3:$I$135,'Journal Entries'!$F$3:$F$135,A10,'Journal Entries'!$C$3:$C$135,"Opening Balance") -> 0 | G10: =SUMIFS('Journal Entries'!$H$3:$H$135,'Journal Entries'!$F$3:$F$135,A10)-E10 -> 0 | H10: =SUMIFS('Journal Entries'!$I$3:$I$135,'Journal Entries'!$F$3:$F$135,A10)-F10 -> 0 | I10: =MAX(0,E10+G10-F10-H10) -> 0 | J10: =MAX(0,F10+H10-E10-G10) -> 0
A11: ='Chart of Accounts'!H12 -> 1017 | B11: ='Chart of Accounts'!I12 -> Accumulated depreciation | C11: ='Chart of Accounts'!A12 -> B/S | D11: ='Chart of Accounts'!B12 -> Assets | E11: =SUMIFS('Journal Entries'!$H$3:$H$135,'Journal Entries'!$F$3:$F$135,A11,'Journal Entries'!$C$3:$C$135,"Opening Balance") -> 0 | F11: =SUMIFS('Journal Entries'!$I$3:$I$135,'Journal Entries'!$F$3:$F$135,A11,'Journal Entries'!$C$3:$C$135,"Opening Balance") -> 0 | G11: =SUMIFS('Journal Entries'!$H$3:$H$135,'Journal Entries'!$F$3:$F$135,A11)-E11 -> 0 | H11: =SUMIFS('Journal Entries'!$I$3:$I$135,'Journal Entries'!$F$3:$F$135,A11)-F11 -> 120000 | I11: =MAX(0,E11+G11-F11-H11) -> 0 | J11: =MAX(0,F11+H11-E11-G11) -> 120000
A12: ='Chart of Accounts'!H13 -> 1018 | B12: ='Chart of Accounts'!I13 -> Trade Debtors | C12: ='Chart of Accounts'!A13 -> B/S | D12: ='Chart of Accounts'!B13 -> Assets | E12: =SUMIFS('Journal Entries'!$H$3:$H$135,'Journal Entries'!$F$3:$F$135,A12,'Journal Entries'!$C$3:$C$135,"Opening Balance") -> 4000000 | F12: =SUMIFS('Journal Entries'!$I$3:$I$135,'Journal Entries'!$F$3:$F$135,A12,'Journal Entries'!$C$3:$C$135,"Opening Balance") -> 0 | G12: =SUMIFS('Journal Entries'!$H$3:$H$135,'Journal Entries'!$F$3:$F$135,A12)-E12 -> 925000 | H12: =SUMIFS('Journal Entries'!$I$3:$I$135,'Journal Entries'!$F$3:$F$135,A12)-F12 -> 3943200 | I12: =MAX(0,E12+G12-F12-H12) -> 981800 | J12: =MAX(0,F12+H12-E12-G12) -> 0
A13: ='Chart of Accounts'!H14 -> 1019 | B13: ='Chart of Accounts'!I14 -> Advance to carriers | C13: ='Chart of Accounts'!A14 -> B/S | D13: ='Chart of Accounts'!B14 -> Assets | E13: =SUMIFS('Journal Entries'!$H$3:$H$135,'Journal Entries'!$F$3:$F$135,A13,'Journal Entries'!$C$3:$C$135,"Opening Balance") -> 0 | F13: =SUMIFS('Journal Entries'!$I$3:$I$135,'Journal Entries'!$F$3:$F$135,A13,'Journal Entries'!$C$3:$C$135,"Opening Balance") -> 0 | G13: =SUMIFS('Journal Entries'!$H$3:$H$135,'Journal Entries'!$F$3:$F$135,A13)-E13 -> 0 | H13: =SUMIFS('Journal Entries'!$I$3:$I$135,'Journal Entries'!$F$3:$F$135,A13)-F13 -> 0 | I13: =MAX(0,E13+G13-F13-H13) -> 0 | J13: =MAX(0,F13+H13-E13-G13) -> 0
A14: ='Chart of Accounts'!H15 -> 1020 | B14: ='Chart of Accounts'!I15 -> Advance to BYOD | C14: ='Chart of Accounts'!A15 -> B/S | D14: ='Chart of Accounts'!B15 -> Assets | E14: =SUMIFS('Journal Entries'!$H$3:$H$135,'Journal Entries'!$F$3:$F$135,A14,'Journal Entries'!$C$3:$C$135,"Opening Balance") -> 0 | F14: =SUMIFS('Journal Entries'!$I$3:$I$135,'Journal Entries'!$F$3:$F$135,A14,'Journal Entries'!$C$3:$C$135,"Opening Balance") -> 0 | G14: =SUMIFS('Journal Entries'!$H$3:$H$135,'Journal Entries'!$F$3:$F$135,A14)-E14 -> 0 | H14: =SUMIFS('Journal Entries'!$I$3:$I$135,'Journal Entries'!$F$3:$F$135,A14)-F14 -> 0 | I14: =MAX(0,E14+G14-F14-H14) -> 0 | J14: =MAX(0,F14+H14-E14-G14) -> 0
... A61: ='Chart of Accounts'!H62 -> 1067 | B61: ='Chart of Accounts'!I62 -> Amortization | C61: ='Chart of Accounts'!A62 -> P&L | D61: ='Chart of Accounts'!B62 -> Expenses | E61: =SUMIFS('Journal Entries'!$H$3:$H$135,'Journal Entries'!$F$3:$F$135,A61,'Journal Entries'!$C$3:$C$135,"Opening Balance") -> 0 | F61: =SUMIFS('Journal Entries'!$I$3:$I$135,'Journal Entries'!$F$3:$F$135,A61,'Journal Entries'!$C$3:$C$135,"Opening Balance") -> 0 | G61: =SUMIFS('Journal Entries'!$H$3:$H$135,'Journal Entries'!$F$3:$F$135,A61)-E61 -> 0 | H61: =SUMIFS('Journal Entries'!$I$3:$I$135,'Journal Entries'!$F$3:$F$135,A61)-F61 -> 0 | I61: =MAX(0,E61+G61-F61-H61) -> 0 | J61: =MAX(0,F61+H61-E61-G61) -> 0
A62: TOTAL | E62: =SUM(E3:E61) -> 7730000 | F62: =SUM(F3:F61) -> 7730000 | G62: =SUM(G3:G61) -> 10981763 | H62: =SUM(H3:H61) -> 11443462 | I62: =SUM(I3:I61) -> 8351101 | J62: =SUM(J3:J61) -> 8812800

Sheet Balance Sheet
A1: Balance Sheet — 31 July 2025
A3: GL Code | B3: Account | C3: Classification | D3: Amount (PKR)
A4: 1011 | B4: Furniture and fixture | C4: Assets | D4: =SUMIFS('Trial Balance'!$I$3:$I$61,'Trial Balance'!$A$3:$A$61,A4)-SUMIFS('Trial Balance'!$J$3:$J$61,'Trial Balance'!$A$3:$A$61,A4) -> 0
A5: 1012 | B5: Leasehold building | C5: Assets | D5: =SUMIFS('Trial Balance'!$I$3:$I$61,'Trial Balance'!$A$3:$A$61,A5)-SUMIFS('Trial Balance'!$J$3:$J$61,'Trial Balance'!$A$3:$A$61,A5) -> 0
A6: 1013 | B6: Computers | C6: Assets | D6: =SUMIFS('Trial Balance'!$I$3:$I$61,'Trial Balance'!$A$3:$A$61,A6)-SUMIFS('Trial Balance'!$J$3:$J$61,'Trial Balance'!$A$3:$A$61,A6) -> 0
A7: 1014 | B7: Office Equipments | C7: Assets | D7: =SUMIFS('Trial Balance'!$I$3:$I$61,'Trial Balance'!$A$3:$A$61,A7)-SUMIFS('Trial Balance'!$J$3:$J$61,'Trial Balance'!$A$3:$A$61,A7) -> 0
A8: 1015 | B8: Vehicles | C8: Assets | D8: =SUMIFS('Trial Balance'!$I$3:$I$61,'Trial Balance'!$A$3:$A$61,A8)-SUMIFS('Trial Balance'!$J$3:$J$61,'Trial Balance'!$A$3:$A$61,A8) -> 0
A9: 1016 | B9: Intangible Assets | C9: Assets | D9: =SUMIFS('Trial Balance'!$I$3:$I$61,'Trial Balance'!$A$3:$A$61,A9)-SUMIFS('Trial Balance'!$J$3:$J$61,'Trial Balance'!$A$3:$A$61,A9) -> 0
A10: 1017 | B10: Accumulated depreciation | C10: Assets | D10: =SUMIFS('Trial Balance'!$I$3:$I$61,'Trial Balance'!$A$3:$A$61,A10)-SUMIFS('Trial Balance'!$J$3:$J$61,'Trial Balance'!$A$3:$A$61,A10) -> -120000
A11: 1018 | B11: Trade Debtors | C11: Assets | D11: =SUMIFS('Trial Balance'!$I$3:$I$61,'Trial Balance'!$A$3:$A$61,A11)-SUMIFS('Trial Balance'!$J$3:$J$61,'Trial Balance'!$A$3:$A$61,A11) -> 981800
A12: 1019 | B12: Advance to carriers | C12: Assets | D12: =SUMIFS('Trial Balance'!$I$3:$I$61,'Trial Balance'!$A$3:$A$61,A12)-SUMIFS('Trial Balance'!$J$3:$J$61,'Trial Balance'!$A$3:$A$61,A12) -> 0
A13: 1020 | B13: Advance to BYOD | C13: Assets | D13: =SUMIFS('Trial Balance'!$I$3:$I$61,'Trial Balance'!$A$3:$A$61,A13)-SUMIFS('Trial Balance'!$J$3:$J$61,'Trial Balance'!$A$3:$A$61,A13) -> 0
A14: 1021 | B14: Security deposit-Office | C14: Assets | D14: =SUMIFS('Trial Balance'!$I$3:$I$61,'Trial Balance'!$A$3:$A$61,A14)-SUMIFS('Trial Balance'!$J$3:$J$61,'Trial Balance'!$A$3:$A$61,A14) -> 200000
A15: 1022 | B15: Security Deposits - Customer | C15: Assets | D15: =SUMIFS('Trial Balance'!$I$3:$I$61,'Trial Balance'!$A$3:$A$61,A15)-SUMIFS('Trial Balance'!$J$3:$J$61,'Trial Balance'!$A$3:$A$61,A15) -> 0
... A19: 1026 | B19: Prepayments | C19: Assets | D19: =SUMIFS('Trial Balance'!$I$3:$I$61,'Trial Balance'!$A$3:$A$61,A19)-SUMIFS('Trial Balance'!$J$3:$J$61,'Trial Balance'!$A$3:$A$61,A19) -> 165000
A20: 1027 | B20: Input sales tax | C20: Libailities | D20: =SUMIFS('Trial Balance'!$J$3:$J$61,'Trial Balance'!$A$3:$A$61,A20)-SUMIFS('Trial Balance'!$I$3:$I$61,'Trial Balance'!$A$3:$A$61,A20) -> 0
A21: 1028 | B21: PK49DUIB0000000627075001 | C21: Assets | D21: =SUMIFS('Trial Balance'!$I$3:$I$61,'Trial Balance'!$A$3:$A$61,A21)-SUMIFS('Trial Balance'!$J$3:$J$61,'Trial Balance'!$A$3:$A$61,A21) -> 0
A22: 1029 | B22: HBL Operating Account | C22: Assets | D22: =SUMIFS('Trial Balance'!$I$3:$I$61,'Trial Balance'!$A$3:$A$61,A22)-SUMIFS('Trial Balance'!$J$3:$J$61,'Trial Balance'!$A$3:$A$61,A22) -> 3997926
A23: 1030 | B23: Meezan Payroll Account | C23: Assets | D23: =SUMIFS('Trial Balance'!$I$3:$I$61,'Trial Balance'!$A$3:$A$61,A23)-SUMIFS('Trial Balance'!$J$3:$J$61,'Trial Balance'!$A$3:$A$61,A23) -> 58912
A24: 1031 | B24: PK75MPBL0124067140164610 | C24: Assets | D24: =SUMIFS('Trial Balance'!$I$3:$I$61,'Trial Balance'!$A$3:$A$61,A24)-SUMIFS('Trial Balance'!$J$3:$J$61,'Trial Balance'!$A$3:$A$61,A24) -> 0
A25: 1032 | B25: Sales Tax Payable | C25: Libailities | D25: =SUMIFS('Trial Balance'!$J$3:$J$61,'Trial Balance'!$A$3:$A$61,A25)-SUMIFS('Trial Balance'!$I$3:$I$61,'Trial Balance'!$A$3:$A$61,A25) -> 0
A26: 1033 | B26: Contract liability | C26: Libailities | D26: =SUMIFS('Trial Balance'!$J$3:$J$61,'Trial Balance'!$A$3:$A$61,A26)-SUMIFS('Trial Balance'!$I$3:$I$61,'Trial Balance'!$A$3:$A$61,A26) -> 0
A27: 1034 | B27: Accrued payroll | C27: Libailities | D27: =SUMIFS('Trial Balance'!$J$3:$J$61,'Trial Balance'!$A$3:$A$61,A27)-SUMIFS('Trial Balance'!$I$3:$I$61,'Trial Balance'!$A$3:$A$61,A27) -> 355350
A28: 1035 | B28: Accrued expenses | C28: Libailities | D28: =SUMIFS('Trial Balance'!$J$3:$J$61,'Trial Balance'!$A$3:$A$61,A28)-SUMIFS('Trial Balance'!$I$3:$I$61,'Trial Balance'!$A$3:$A$61,A28) -> 400000
A29: 1036 | B29: Withholding tax payable:Withholding tax - Vendors | C29: Libailities | D29: =SUMIFS('Trial Balance'!$J$3:$J$61,'Trial Balance'!$A$3:$A$61,A29)-SUMIFS('Trial Balance'!$I$3:$I$61,'Trial Balance'!$A$3:$A$61,A29) -> -3350
A30: 1037 | B30: Advance against issue of shares | C30: Equity | D30: =SUMIFS('Trial Balance'!$J$3:$J$61,'Trial Balance'!$A$3:$A$61,A30)-SUMIFS('Trial Balance'!$I$3:$I$61,'Trial Balance'!$A$3:$A$61,A30) -> 0
A31: 1038 | B31: Retained Earnings | C31: Equity | D31: =SUMIFS('Trial Balance'!$J$3:$J$61,'Trial Balance'!$A$3:$A$61,A31)-SUMIFS('Trial Balance'!$I$3:$I$61,'Trial Balance'!$A$3:$A$61,A31) -> 6630000
A32: 1039 | B32: Share premium | C32: Equity | D32: =SUMIFS('Trial Balance'!$J$3:$J$61,'Trial Balance'!$A$3:$A$61,A32)-SUMIFS('Trial Balance'!$I$3:$I$61,'Trial Balance'!$A$3:$A$61,A32) -> 0
A33: 1040 | B33: Share capital | C33: Equity | D33: =SUMIFS('Trial Balance'!$J$3:$J$61,'Trial Balance'!$A$3:$A$61,A33)-SUMIFS('Trial Balance'!$I$3:$I$61,'Trial Balance'!$A$3:$A$61,A33) -> 0
A34: 1041 | B34: ABHI | C34: Libailities | D34: =SUMIFS('Trial Balance'!$J$3:$J$61,'Trial Balance'!$A$3:$A$61,A34)-SUMIFS('Trial Balance'!$I$3:$I$61,'Trial Balance'!$A$3:$A$61,A34) -> 0
A35: 1042 | B35: Audit Fee Payable | C35: Libailities | D35: =SUMIFS('Trial Balance'!$J$3:$J$61,'Trial Balance'!$A$3:$A$61,A35)-SUMIFS('Trial Balance'!$I$3:$I$61,'Trial Balance'!$A$3:$A$61,A35) -> 0
A36: 1043 | B36: Prepaid Leasehold | C36: Assets | D36: =SUMIFS('Trial Balance'!$I$3:$I$61,'Trial Balance'!$A$3:$A$61,A36)-SUMIFS('Trial Balance'!$J$3:$J$61,'Trial Balance'!$A$3:$A$61,A36) -> 0
A37: 1044 | B37: Advance tax | C37: Assets | D37: =SUMIFS('Trial Balance'!$I$3:$I$61,'Trial Balance'!$A$3:$A$61,A37)-SUMIFS('Trial Balance'!$J$3:$J$61,'Trial Balance'!$A$3:$A$61,A37) -> 0
A38: 1045 | B38: WHT on Bank Profit | C38: Assets | D38: =SUMIFS('Trial Balance'!$I$3:$I$61,'Trial Balance'!$A$3:$A$61,A38)-SUMIFS('Trial Balance'!$J$3:$J$61,'Trial Balance'!$A$3:$A$61,A38) -> 2768
A39: 1046 | B39: Withholding tax :Withholding tax - Utilities | C39: Assets | D39: =SUMIFS('Trial Balance'!$I$3:$I$61,'Trial Balance'!$A$3:$A$61,A39)-SUMIFS('Trial Balance'!$J$3:$J$61,'Trial Balance'!$A$3:$A$61,A39) -> 0
A40: 1047 | B40: Provision for Taxation | C40: Libailities | D40: =SUMIFS('Trial Balance'!$J$3:$J$61,'Trial Balance'!$A$3:$A$61,A40)-SUMIFS('Trial Balance'!$I$3:$I$61,'Trial Balance'!$A$3:$A$61,A40) -> 140000
A42: Total Assets | D42: =SUMIFS(D4:D40,C4:C40,"Assets") -> 5343906
A43: Total Liabilities | D43: =SUMIFS(D4:D40,C4:C40,"Libailities") -> 892000
A44: Equity before current-period profit | D44: =SUMIFS(D4:D40,C4:C40,"Equity") -> 6630000
A45: Current-period profit | D45: ='Profit and Loss'!D29 -> -1716395
A46: Total Liabilities and Equity | D46: =D43+D44+D45 -> 5805605
A47: Balance Sheet Check | D47: =D42-D46 -> -461699

Sheet Profit and Loss
A1: Profit and Loss Statement — July 2025
A3: GL Code | B3: Account | C3: Classification | D3: Amount (PKR)
A4: 1048 | B4: Taxation ( Current Year) | C4: Expenses | D4: =SUMIFS('Trial Balance'!$I$3:$I$61,'Trial Balance'!$A$3:$A$61,A4)-SUMIFS('Trial Balance'!$J$3:$J$61,'Trial Balance'!$A$3:$A$61,A4) -> 140000
A5: 1049 | B5: Fleet Subsidy | C5: Expenses | D5: =SUMIFS('Trial Balance'!$I$3:$I$61,'Trial Balance'!$A$3:$A$61,A5)-SUMIFS('Trial Balance'!$J$3:$J$61,'Trial Balance'!$A$3:$A$61,A5) -> 0
A6: 1050 | B6: Sales revenue | C6: Revenue | D6: =SUMIFS('Trial Balance'!$J$3:$J$61,'Trial Balance'!$A$3:$A$61,A6)-SUMIFS('Trial Balance'!$I$3:$I$61,'Trial Balance'!$A$3:$A$61,A6) -> 1149000
A7: 1051 | B7: Allowance for doubtful debts | C7: Expenses | D7: =SUMIFS('Trial Balance'!$I$3:$I$61,'Trial Balance'!$A$3:$A$61,A7)-SUMIFS('Trial Balance'!$J$3:$J$61,'Trial Balance'!$A$3:$A$61,A7) -> 0
A8: 1052 | B8: Allowance for doubtful debts | C8: Expenses | D8: =SUMIFS('Trial Balance'!$I$3:$I$61,'Trial Balance'!$A$3:$A$61,A8)-SUMIFS('Trial Balance'!$J$3:$J$61,'Trial Balance'!$A$3:$A$61,A8) -> 0
A9: 1053 | B9: Allowance for advance for laptops | C9: Expenses | D9: =SUMIFS('Trial Balance'!$I$3:$I$61,'Trial Balance'!$A$3:$A$61,A9)-SUMIFS('Trial Balance'!$J$3:$J$61,'Trial Balance'!$A$3:$A$61,A9) -> 0
A10: 1054 | B10: Trucker's Commission | C10: Expenses | D10: =SUMIFS('Trial Balance'!$I$3:$I$61,'Trial Balance'!$A$3:$A$61,A10)-SUMIFS('Trial Balance'!$J$3:$J$61,'Trial Balance'!$A$3:$A$61,A10) -> 1235500
A11: 1055 | B11: Trucker's Cost - Fuel | C11: Expenses | D11: =SUMIFS('Trial Balance'!$I$3:$I$61,'Trial Balance'!$A$3:$A$61,A11)-SUMIFS('Trial Balance'!$J$3:$J$61,'Trial Balance'!$A$3:$A$61,A11) -> 404650
A12: 1056 | B12: SALARIES & WAGES | C12: Expenses | D12: =SUMIFS('Trial Balance'!$I$3:$I$61,'Trial Balance'!$A$3:$A$61,A12)-SUMIFS('Trial Balance'!$J$3:$J$61,'Trial Balance'!$A$3:$A$61,A12) -> 386500
A13: 1057 | B13: Bank Charges | C13: Expenses | D13: =SUMIFS('Trial Balance'!$I$3:$I$61,'Trial Balance'!$A$3:$A$61,A13)-SUMIFS('Trial Balance'!$J$3:$J$61,'Trial Balance'!$A$3:$A$61,A13) -> 10645
A14: 1058 | B14: Rent and utilities | C14: Expenses | D14: =SUMIFS('Trial Balance'!$I$3:$I$61,'Trial Balance'!$A$3:$A$61,A14)-SUMIFS('Trial Balance'!$J$3:$J$61,'Trial Balance'!$A$3:$A$61,A14) -> 461550
A15: 1059 | B15: Travel and entertainment | C15: Expenses | D15: =SUMIFS('Trial Balance'!$I$3:$I$61,'Trial Balance'!$A$3:$A$61,A15)-SUMIFS('Trial Balance'!$J$3:$J$61,'Trial Balance'!$A$3:$A$61,A15) -> 0
A16: 1060 | B16: LEGAL & PROFESSIONAL FEE | C16: Expenses | D16: =SUMIFS('Trial Balance'!$I$3:$I$61,'Trial Balance'!$A$3:$A$61,A16)-SUMIFS('Trial Balance'!$J$3:$J$61,'Trial Balance'!$A$3:$A$61,A16) -> 125000
A17: 1061 | B17: Offline marketing and channel | C17: Expenses | D17: =SUMIFS('Trial Balance'!$I$3:$I$61,'Trial Balance'!$A$3:$A$61,A17)-SUMIFS('Trial Balance'!$J$3:$J$61,'Trial Balance'!$A$3:$A$61,A17) -> 0
A18: 1062 | B18: Call center | C18: Expenses | D18: =SUMIFS('Trial Balance'!$I$3:$I$61,'Trial Balance'!$A$3:$A$61,A18)-SUMIFS('Trial Balance'!$J$3:$J$61,'Trial Balance'!$A$3:$A$61,A18) -> 0
... A20: 1064 | B20: Depreciation | C20: Expenses | D20: =SUMIFS('Trial Balance'!$I$3:$I$61,'Trial Balance'!$A$3:$A$61,A20)-SUMIFS('Trial Balance'!$J$3:$J$61,'Trial Balance'!$A$3:$A$61,A20) -> 120000
A21: 1065 | B21: Other Income | C21: Income | D21: =SUMIFS('Trial Balance'!$J$3:$J$61,'Trial Balance'!$A$3:$A$61,A21)-SUMIFS('Trial Balance'!$I$3:$I$61,'Trial Balance'!$A$3:$A$61,A21) -> 0
A22: 1066 | B22: Profit on PLS | C22: Income | D22: =SUMIFS('Trial Balance'!$J$3:$J$61,'Trial Balance'!$A$3:$A$61,A22)-SUMIFS('Trial Balance'!$I$3:$I$61,'Trial Balance'!$A$3:$A$61,A22) -> 18450
A23: 1067 | B23: Amortization | C23: Expenses | D23: =SUMIFS('Trial Balance'!$I$3:$I$61,'Trial Balance'!$A$3:$A$61,A23)-SUMIFS('Trial Balance'!$J$3:$J$61,'Trial Balance'!$A$3:$A$61,A23) -> 0
A24: 1068 | B24: Other Expenses | C24: Expenses | D24: =SUMIFS('Trial Balance'!$I$3:$I$61,'Trial Balance'!$A$3:$A$61,A24)-SUMIFS('Trial Balance'!$J$3:$J$61,'Trial Balance'!$A$3:$A$61,A24) -> 0
A25: 1069 | B25: Bank Charges | C25: Expenses | D25: =SUMIFS('Trial Balance'!$I$3:$I$61,'Trial Balance'!$A$3:$A$61,A25)-SUMIFS('Trial Balance'!$J$3:$J$61,'Trial Balance'!$A$3:$A$61,A25) -> 0
A27: Total Revenue and Other Income | D27: =SUMIFS(D4:D25,C4:C25,"Revenue")+SUMIFS(D4:D25,C4:C25,"Income") -> 1167450
A28: Total Expenses | D28: =SUMIFS(D4:D25,C4:C25,"Expenses") -> 2883845
A29: Net Profit / (Loss) | D29: =D27-D28 -> -1716395

Sheet Cash Flow Statement
A1: Cash Flow Statement — July 2025 (Direct Method)
A3: Section | B3: Cash Flow Category | C3: Calculation | D3: Amount (PKR)
A4: Operating | B4: Operating - Receipts | C4: Bank credits classified as operating receipts | D4: =SUMIFS('Transaction Mapping'!$G$3:$G$61,'Transaction Mapping'!$T$3:$T$61,B4)-SUMIFS('Transaction Mapping'!$F$3:$F$61,'Transaction Mapping'!$T$3:$T$61,B4) -> 4240150
A5: Operating | B5: Operating - Payments | C5: Bank debits classified as operating payments | D5: =SUMIFS('Transaction Mapping'!$G$3:$G$61,'Transaction Mapping'!$T$3:$T$61,B5)-SUMIFS('Transaction Mapping'!$F$3:$F$61,'Transaction Mapping'!$T$3:$T$61,B5) -> -3713312
A6: Investing | B6: Investing - Receipts | C6: Investing receipts | D6: =SUMIFS('Transaction Mapping'!$G$3:$G$61,'Transaction Mapping'!$T$3:$T$61,B6)-SUMIFS('Transaction Mapping'!$F$3:$F$61,'Transaction Mapping'!$T$3:$T$61,B6) -> 0
A7: Investing | B7: Investing - Payments | C7: Investing payments | D7: =SUMIFS('Transaction Mapping'!$G$3:$G$61,'Transaction Mapping'!$T$3:$T$61,B7)-SUMIFS('Transaction Mapping'!$F$3:$F$61,'Transaction Mapping'!$T$3:$T$61,B7) -> -200000
A8: Financing | B8: Financing - Receipts | C8: Financing receipts | D8: =SUMIFS('Transaction Mapping'!$G$3:$G$61,'Transaction Mapping'!$T$3:$T$61,B8)-SUMIFS('Transaction Mapping'!$F$3:$F$61,'Transaction Mapping'!$T$3:$T$61,B8) -> 0
A9: Financing | B9: Financing - Payments | C9: Financing payments | D9: =SUMIFS('Transaction Mapping'!$G$3:$G$61,'Transaction Mapping'!$T$3:$T$61,B9)-SUMIFS('Transaction Mapping'!$F$3:$F$61,'Transaction Mapping'!$T$3:$T$61,B9) -> 0
A10: Transfer | B10: Transfer | C10: Internal transfers (net zero) | D10: =SUMIFS('Transaction Mapping'!$G$3:$G$61,'Transaction Mapping'!$T$3:$T$61,B10)-SUMIFS('Transaction Mapping'!$F$3:$F$61,'Transaction Mapping'!$T$3:$T$61,B10) -> 0
A12: Net change in cash | D12: =SUM(D4:D10) -> 326838
A13: Opening cash | D13: ='HBL Operating Account'!G2+'Meezan Payroll Account'!G2 -> 3730000
A14: Ending cash | D14: =D12+D13 -> 4056838
A15: Balance Sheet cash | D15: =SUMIFS('Balance Sheet'!$D$4:$D$40,'Balance Sheet'!$A$4:$A$40,1029)+SUMIFS('Balance Sheet'!$D$4:$D$40,'Balance Sheet'!$A$4:$A$40,1030) -> 4056838
A16: Cash Flow Check | D16: =D14-D15 -> 0

Sheet Checks
A1: Accounting Reconciliation Checks
A3: Check | B3: Actual | C3: Expected | D3: Difference | E3: Tolerance | F3: Status | G3: Where to fix
A4: Journal debits = credits | B4: =SUM('Journal Entries'!H3:H135) -> 19173462 | C4: =SUM('Journal Entries'!I3:I135) -> 19173462 | D4: =B4-C4 -> 0 | E4: 1 | F4: =IF(ABS(D4)<=E4,"PASS","FAIL") -> PASS | G4: Journal Entries
A5: Trial Balance closing debits = credits | B5: ='Trial Balance'!I62 -> 8351101 | C5: ='Trial Balance'!J62 -> 8812800 | D5: =B5-C5 -> -461699 | E5: 1 | F5: =IF(ABS(D5)<=E5,"PASS","FAIL") -> FAIL | G5: Trial Balance / Journal Entries
A6: HBL bank ledger = statement closing | B6: =SUMIFS('Trial Balance'!I3:I61,'Trial Balance'!A3:A61,1029)-SUMIFS('Trial Balance'!J3:J61,'Trial Balance'!A3:A61,1029) -> 3997926 | C6: ='HBL Operating Account'!G5 -> 3997926 | D6: =B6-C6 -> 0 | E6: 1 | F6: =IF(ABS(D6)<=E6,"PASS","FAIL") -> PASS | G6: Mapping / HBL statement
A7: Meezan bank ledger = statement closing | B7: =SUMIFS('Trial Balance'!I3:I61,'Trial Balance'!A3:A61,1030)-SUMIFS('Trial Balance'!J3:J61,'Trial Balance'!A3:A61,1030) -> 58912 | C7: ='Meezan Payroll Account'!G5 -> 58912 | D7: =B7-C7 -> 0 | E7: 1 | F7: =IF(ABS(D7)<=E7,"PASS","FAIL") -> PASS | G7: Mapping / Meezan statement
A8: Assets = liabilities + equity | B8: ='Balance Sheet'!D42 -> 5343906 | C8: ='Balance Sheet'!D46 -> 5805605 | D8: =B8-C8 -> -461699 | E8: 1 | F8: =IF(ABS(D8)<=E8,"PASS","FAIL") -> FAIL | G8: Balance Sheet / mappings
A9: Cash Flow ending cash = Balance Sheet cash | B9: ='Cash Flow Statement'!D14 -> 4056838 | C9: ='Cash Flow Statement'!D15 -> 4056838 | D9: =B9-C9 -> 0 | E9: 1 | F9: =IF(ABS(D9)<=E9,"PASS","FAIL") -> PASS | G9: Cash Flow classification
A10: All GL codes found | B10: =COUNTIF('Transaction Mapping'!L3:L61,"GL not found")+COUNTIF('Transaction Mapping'!N3:N61,"GL not found")+COUNTIF('Non-Bank Entries'!E3:E9,"GL not found")+COUNTIF('Non-Bank Entries'!G3:G9,"GL not found") -> 132 | C10: =0 -> 0 | D10: =B10-C10 -> 132 | E10: 1 | F10: =IF(ABS(D10)<=E10,"PASS","FAIL") -> FAIL | G10: Chart of Accounts / Mapping
A11: All mappings approved or transfer-matched | B11: =COUNTIF('Transaction Mapping'!Q3:Q61,"Approved") -> 59 | C11: =ROWS('Transaction Mapping'!Q3:Q61) -> 59 | D11: =B11-C11 -> 0 | E11: 1 | F11: =IF(ABS(D11)<=E11,"PASS","FAIL") -> PASS | G11: Transaction Mapping
A12: Matched transfer pairs complete | B12: =COUNTIF('Transaction Mapping'!R3:R61,"TRF-0707")+COUNTIF('Transaction Mapping'!R3:R61,"TRF-0721") -> 4 | C12: =4 -> 4 | D12: =B12-C12 -> 0 | E12: 1 | F12: =IF(ABS(D12)<=E12,"PASS","FAIL") -> PASS | G12: Transaction Mapping transfer IDs
A15: MODEL STATUS | F15: =IF(COUNTIF(F4:F12,"FAIL")=0,"PASS","FAIL") -> FAIL
